Workbook

Sheet ETFs
A1: Name | B1: Ticker | C1: Fund Name | D1: Last Update | E1: Last Price | F1: 1d% | G1: Net Change | H1: Open | I1: Lo | J1: Hi | K1: Prev Cls | M1: 52W Lo | N1: 52W Hi | O1: Volume | P1: Avg Volume | Q1: Sector/Strategy | R1: Sub-Sector | S1: Fund Family | T1: Expense Ratio (net) | U1: Market Cap | V1: Total Assets (AUM) | W1: Net Assets | X1: 1 Yr % Change | Y1: Inception Date | Z1: NAV | AA1: PE Ratio (TTM) | AB1: Yield | AC1: Avg. Volume | AD1: Beta (5Y Monthly) | AE1: YTD Return | AF1: 1-Year Return | AG1: 3-Year Return | AH1: Shares Outstanding | AI1: Avg Volume (30d) | AJ1: Avg $ Volume (Est) | AK1: Expense Ratio | AL1: 52 Week High | AM1: 52 Week Low | AN1: Liquidity Rating | AO1: FX | AP1: Exchange | AQ1: Exh Abbr | AR1: Type
A2: ABXB | B2: ABXB | C2: Abacus Flexible Bond Leaders ETF | D2: {=_FV(A2,"Last trade time",TRUE)} -> #VALUE! | E2: {=_FV(A2,"Price")} -> #VALUE! | F2: {=_FV(A2,"Change (%)",TRUE)} -> #VALUE! | G2: {=_FV(A2,"Change")} -> #VALUE! | H2: {=_FV(A2,"Open")} -> #VALUE! | I2: {=_FV(A2,"Low")} -> #VALUE! | J2: {=_FV(A2,"High")} -> #VALUE! | K2: {=_FV(A2,"Previous close",TRUE)} -> #VALUE! | M2: {=_FV(A2,"52 week low",TRUE)} -> #VALUE! | N2: {=_FV(A2,"52 week high",TRUE)} -> #VALUE! | O2: {=_FV(A2,"Volume")} -> #VALUE! | P2: {=_FV(A2,"Volume average",TRUE)} -> #VALUE! | Q2: Fixed Income | T2: {=_FV(A2,"Expense ratio",TRUE)} -> #VALUE! | U2: {=_FV(A2,"Market cap",TRUE)} -> #VALUE! | X2: -6.18% | Z2: 19.51 | AC2: 841 | AE2: 3.438108 | AF2: 6.8381539 | AI2: 841 | AJ2: 16416.32 | AL2: 21.883 | AM2: 17.11 | AN2: Low | AO2: {=_FV(A2,"Currency")} -> #VALUE! | AP2: {=_FV(A2,"Exchange")} -> #VALUE! | AQ2: {=_FV(A2,"Exchange abbreviation",TRUE)} -> #VALUE! | AR2: {=_FV(A2,"Instrument type",TRUE)} -> #VALUE!
A3: NXTI | B3: NXTI | C3: Simplify Exchange Traded Funds Simplify Next Intangible Core I | D3: {=_FV(A3,"Last trade time",TRUE)} -> #VALUE! | E3: {=_FV(A3,"Price")} -> #VALUE! | F3: {=_FV(A3,"Change (%)",TRUE)} -> #VALUE! | G3: {=_FV(A3,"Change")} -> #VALUE! | H3: {=_FV(A3,"Open")} -> #VALUE! | I3: {=_FV(A3,"Low")} -> #VALUE! | J3: {=_FV(A3,"High")} -> #VALUE! | K3: {=_FV(A3,"Previous close",TRUE)} -> #VALUE! | M3: {=_FV(A3,"52 week low",TRUE)} -> #VALUE! | N3: {=_FV(A3,"52 week high",TRUE)} -> #VALUE! | O3: {=_FV(A3,"Volume")} -> #VALUE! | P3: {=_FV(A3,"Volume average",TRUE)} -> #VALUE! | Q3: Large Blend | S3: Simplify Asset Management | T3: {=_FV(A3,"Expense ratio",TRUE)} -> #VALUE! | U3: {=_FV(A3,"Market cap",TRUE)} -> #VALUE! | V3: 1494565 | W3: 1494565 | Y3: 2024-04-14 | Z3: 30.4136 | AA3: 31.761068 | AB3: 0.0364 | AC3: 1003 | AE3: 8.4555618 | AF3: 23.769972 | AI3: 1003 | AJ3: 30506.145 | AL3: 31.04 | AM3: 24.653 | AN3: Low | AO3: {=_FV(A3,"Currency")} -> #VALUE! | AP3: {=_FV(A3,"Exchange")} -> #VALUE! | AQ3: {=_FV(A3,"Exchange abbreviation",TRUE)} -> #VALUE! | AR3: {=_FV(A3,"Instrument type",TRUE)} -> #VALUE!
A4: OPPE | B4: OPPE | C4: WisdomTree European Opportunities Fund | D4: {=_FV(A4,"Last trade time",TRUE)} -> #VALUE! | E4: {=_FV(A4,"Price")} -> #VALUE! | F4: {=_FV(A4,"Change (%)",TRUE)} -> #VALUE! | G4: {=_FV(A4,"Change")} -> #VALUE! | H4: {=_FV(A4,"Open")} -> #VALUE! | I4: {=_FV(A4,"Low")} -> #VALUE! | J4: {=_FV(A4,"High")} -> #VALUE! | K4: {=_FV(A4,"Previous close",TRUE)} -> #VALUE! | M4: {=_FV(A4,"52 week low",TRUE)} -> #VALUE! | N4: {=_FV(A4,"52 week high",TRUE)} -> #VALUE! | O4: {=_FV(A4,"Volume")} -> #VALUE! | P4: {=_FV(A4,"Volume average",TRUE)} -> #VALUE! | Q4: Europe Stock | S4: WisdomTree | T4: {=_FV(A4,"Expense ratio",TRUE)} -> #VALUE! | U4: {=_FV(A4,"Market cap",TRUE)} -> #VALUE! | V4: 129346408 | W4: 129346408 | Y4: 2015-03-03 | Z4: 46.522 | AA4: 11.491941 | AB4: 0.0328 | AC4: 17476 | AE4: 22.404768 | AF4: 19.481549 | AI4: 17476 | AJ4: 816786.3 | AL4: 46.89 | AM4: 35.84 | AN4: Low | AO4: {=_FV(A4,"Currency")} -> #VALUE! | AP4: {=_FV(A4,"Exchange")} -> #VALUE! | AQ4: {=_FV(A4,"Exchange abbreviation",TRUE)} -> #VALUE! | AR4: {=_FV(A4,"Instrument type",TRUE)} -> #VALUE!
A5: TMDV | B5: TMDV | C5: ProShares Russell US Dividend Growers ETF | D5: {=_FV(A5,"Last trade time",TRUE)} -> #VALUE! | E5: {=_FV(A5,"Price")} -> #VALUE! | F5: {=_FV(A5,"Change (%)",TRUE)} -> #VALUE! | G5: {=_FV(A5,"Change")} -> #VALUE! | H5: {=_FV(A5,"Open")} -> #VALUE! | I5: {=_FV(A5,"Low")} -> #VALUE! | J5: {=_FV(A5,"High")} -> #VALUE! | K5: {=_FV(A5,"Previous close",TRUE)} -> #VALUE! | M5: {=_FV(A5,"52 week low",TRUE)} -> #VALUE! | N5: {=_FV(A5,"52 week high",TRUE)} -> #VALUE! | O5: {=_FV(A5,"Volume")} -> #VALUE! | P5: {=_FV(A5,"Volume average",TRUE)} -> #VALUE! | Q5: Mid-Cap Value | S5: ProShares | T5: {=_FV(A5,"Expense ratio",TRUE)} -> #VALUE! | U5: {=_FV(A5,"Market cap",TRUE)} -> #VALUE! | V5: 4248592 | W5: 4248592 | Y5: 2019-11-04 | Z5: 46.9521 | AA5: 20.130634 | AB5: 0.027999999 | AC5: 233 | AE5: 1.8690309 | AF5: 4.9194103 | AI5: 233 | AJ5: 10938.581 | AL5: 51.754 | AM5: 42.69 | AN5: Low | AO5: {=_FV(A5,"Currency")} -> #VALUE! | AP5: {=_FV(A5,"Exchange")} -> #VALUE! | AQ5: {=_FV(A5,"Exchange abbreviation",TRUE)} -> #VALUE! | AR5: {=_FV(A5,"Instrument type",TRUE)} -> #VALUE!
A6: #VALUE! | B6: CARD | C6: Bank Of Montreal MAX Auto Industry -3x Inverse Leveraged ETN | D6: {=_FV(A6,"Last trade time",TRUE)} -> 45824.84 | E6: {=_FV(A6,"Price")} -> 4.4 | F6: {=_FV(A6,"Change (%)",TRUE)} -> -0.022222 | G6: {=_FV(A6,"Change")} -> -0.1 | H6: {=_FV(A6,"Open")} -> 4.4099 | I6: {=_FV(A6,"Low")} -> 4.3392 | J6: {=_FV(A6,"High")} -> 4.4399 | K6: {=_FV(A6,"Previous close",TRUE)} -> 4.5 | M6: {=_FV(A6,"52 week low",TRUE)} -> 3.845 | N6: {=_FV(A6,"52 week high",TRUE)} -> 15.35 | O6: {=_FV(A6,"Volume")} -> 5763 | P6: {=_FV(A6,"Volume average",TRUE)} -> 16572 | Q6: Trading--Inverse Equity | R6: Equities - Autos - Short | S6: Bank of Montreal | T6: {=_FV(A6,"Expense ratio",TRUE)} -> #VALUE! | U6: {=_FV(A6,"Market cap",TRUE)} -> 104909700000 | V6: 1240271 | W6: 1240271 | X6: -71.20% | Y6: 2023-06-26 | Z6: 4.31998 | AA6: 15.021212 | AB6: 0 | AC6: 32947 | AE6: -41.222659 | AI6: 32947 | AJ6: 142327.75 | AL6: 13.6 | AM6: 3.845 | AN6: Low | AO6: {=_FV(A6,"Currency")} -> USD | AP6: {=_FV(A6,"Exchange")} -> NYSE Arca | AQ6: {=_FV(A6,"Exchange abbreviation",TRUE)} -> ARCX | AR6: {=_FV(A6,"Instrument type",TRUE)} -> Stock
A7: #VALUE! | B7: FLYD | C7: Bank of Montreal MicroSectors Travel -3x Inverse Leveraged ETN | D7: {=_FV(A7,"Last trade time",TRUE)} -> 45824.84 | E7: {=_FV(A7,"Price")} -> 10.37 | F7: {=_FV(A7,"Change (%)",TRUE)} -> -0.079041 | G7: {=_FV(A7,"Change")} -> -0.89 | H7: {=_FV(A7,"Open")} -> 10.695 | I7: {=_FV(A7,"Low")} -> 10.335 | J7: {=_FV(A7,"High")} -> 10.73 | K7: {=_FV(A7,"Previous close",TRUE)} -> 11.26 | M7: {=_FV(A7,"52 week low",TRUE)} -> 9.59 | N7: {=_FV(A7,"52 week high",TRUE)} -> 42.88 | O7: {=_FV(A7,"Volume")} -> 10616 | P7: {=_FV(A7,"Volume average",TRUE)} -> 9870 | Q7: Financial | T7: {=_FV(A7,"Expense ratio",TRUE)} -> #VALUE! | U7: {=_FV(A7,"Market cap",TRUE)} -> 104909700000 | AC7: 7131 | AN7: Unknown | AO7: {=_FV(A7,"Currency")} -> USD | AP7: {=_FV(A7,"Exchange")} -> NYSE Arca | AQ7: {=_FV(A7,"Exchange abbreviation",TRUE)} -> ARCX | AR7: {=_FV(A7,"Instrument type",TRUE)} -> Stock
A8: #VALUE! | B8: NRGU | C8: Bank Of Montreal MicroSectors U.S. Big Oil 3 Leveraged ETNs du | D8: {=_FV(A8,"Last trade time",TRUE)} -> 45824.918 | E8: {=_FV(A8,"Price")} -> 18.51 | F8: {=_FV(A8,"Change (%)",TRUE)} -> -0.010689 | G8: {=_FV(A8,"Change")} -> -0.2 | H8: {=_FV(A8,"Open")} -> 18.71 | I8: {=_FV(A8,"Low")} -> 17.97 | J8: {=_FV(A8,"High")} -> 19 | K8: {=_FV(A8,"Previous close",TRUE)} -> 18.71 | M8: {=_FV(A8,"52 week low",TRUE)} -> 10.2801 | N8: {=_FV(A8,"52 week high",TRUE)} -> 26.1206 | O8: {=_FV(A8,"Volume")} -> 174302 | P8: {=_FV(A8,"Volume average",TRUE)} -> 46231 | Q8: Financial | T8: {=_FV(A8,"Expense ratio",TRUE)} -> #VALUE! | U8: {=_FV(A8,"Market cap",TRUE)} -> 104909700000 | Z8: 15.6417 | AA8: 9.666164 | AC8: 32011 | AE8: -40.117147 | AI8: 32011 | AJ8: 490728.63 | AL8: 26.121 | AM8: 10.28 | AN8: Low | AO8: {=_FV(A8,"Currency")} -> USD | AP8: {=_FV(A8,"Exchange")} -> NYSE Arca | AQ8: {=_FV(A8,"Exchange abbreviation",TRUE)} -> ARCX | AR8: {=_FV(A8,"Instrument type",TRUE)} -> Stock
A9: #VALUE! | B9: GDXU | C9: MicroSectors Gold Miners 3X Leveraged ETN | D9: {=_FV(A9,"Last trade time",TRUE)} -> 45824.941 | E9: {=_FV(A9,"Price")} -> 80.93 | F9: {=_FV(A9,"Change (%)",TRUE)} -> -0.05665 | G9: {=_FV(A9,"Change")} -> -4.86 | H9: {=_FV(A9,"Open")} -> 82.39 | I9: {=_FV(A9,"Low")} -> 80.5 | J9: {=_FV(A9,"High")} -> 84.1605 | K9: {=_FV(A9,"Previous close",TRUE)} -> 85.79 | M9: {=_FV(A9,"52 week low",TRUE)} -> 25.83 | N9: {=_FV(A9,"52 week high",TRUE)} -> 87.5 | O9: {=_FV(A9,"Volume")} -> 485805 | P9: {=_FV(A9,"Volume average",TRUE)} -> 824987 | Q9: Trading--Leveraged Commodities | R9: Commodities - Gold | S9: BMO Capital Markets | T9: {=_FV(A9,"Expense ratio",TRUE)} -> #VALUE! | U9: {=_FV(A9,"Market cap",TRUE)} -> 104909700000 | V9: 593497472 | W9: 593497472 | Y9: 2020-12-01 | Z9: 74.89052 | AA9: 23.022688 | AB9: 0 | AC9: 809814 | AE9: 150.81593 | AF9: 83.632022 | AI9: 809814 | AJ9: 60574087 | AL9: 87.5 | AM9: 25.83 | AN9: High | AO9: {=_FV(A9,"Currency")} -> USD | AP9: {=_FV(A9,"Exchange")} -> NYSE Arca | AQ9: {=_FV(A9,"Exchange abbreviation",TRUE)} -> ARCX | AR9: {=_FV(A9,"Instrument type",TRUE)} -> Stock
A10: #VALUE! | B10: WTIU | C10: Bank Of Montreal MicroSectors Energy 3X Leveraged ETNs | D10: {=_FV(A10,"Last trade time",TRUE)} -> 45824.92 | E10: {=_FV(A10,"Price")} -> 10.48 | F10: {=_FV(A10,"Change (%)",TRUE)} -> -0.003802 | G10: {=_FV(A10,"Change")} -> -0.04 | H10: {=_FV(A10,"Open")} -> 10.5 | I10: {=_FV(A10,"Low")} -> 10.19 | J10: {=_FV(A10,"High")} -> 10.78 | K10: {=_FV(A10,"Previous close",TRUE)} -> 10.52 | M10: {=_FV(A10,"52 week low",TRUE)} -> 6.056 | N10: {=_FV(A10,"52 week high",TRUE)} -> 20.33 | O10: {=_FV(A10,"Volume")} -> 192442 | P10: {=_FV(A10,"Volume average",TRUE)} -> 79504 | Q10: Trading--Leveraged Equity | S10: BMO Capital Markets | T10: {=_FV(A10,"Expense ratio",TRUE)} -> #VALUE! | U10: {=_FV(A10,"Market cap",TRUE)} -> 104909700000 | V10: 12352514 | W10: 12352514 | Y10: 2023-02-15 | Z10: 8.77648 | AA10: 15.339239 | AB10: 0 | AC10: 69295 | AE10: -24.72388 | AF10: -52.224321 | AI10: 69295 | AJ10: 609103.05 | AL10: 20.33 | AM10: 6.056 | AN10: Low | AO10: {=_FV(A10,"Currency")} -> USD | AP10: {=_FV(A10,"Exchange")} -> NYSE Arca | AQ10: {=_FV(A10,"Exchange abbreviation",TRUE)} -> ARCX | AR10: {=_FV(A10,"Instrument type",TRUE)} -> Stock
A11: #VALUE! | B11: OILU | C11: MicroSectors Oil & Gas Exp. & Prod. 3x Leveraged ETN | D11: {=_FV(A11,"Last trade time",TRUE)} -> 45824.94 | E11: {=_FV(A11,"Price")} -> 24.15 | F11: {=_FV(A11,"Change (%)",TRUE)} -> -0.014688 | G11: {=_FV(A11,"Change")} -> -0.36 | H11: {=_FV(A11,"Open")} -> 24.3 | I11: {=_FV(A11,"Low")} -> 23.66 | J11: {=_FV(A11,"High")} -> 25 | K11: {=_FV(A11,"Previous close",TRUE)} -> 24.51 | M11: {=_FV(A11,"52 week low",TRUE)} -> 15.15 | N11: {=_FV(A11,"52 week high",TRUE)} -> 43.77 | O11: {=_FV(A11,"Volume")} -> 618210 | P11: {=_FV(A11,"Volume average",TRUE)} -> 255748 | Q11: Trading--Leveraged Equity | S11: BMO Capital Markets | T11: {=_FV(A11,"Expense ratio",TRUE)} -> #VALUE! | U11: {=_FV(A11,"Market cap",TRUE)} -> 104909700000 | V11: 29153108 | W11: 29153108 | Y11: 2021-11-07 | Z11: 20.85666 | AA11: 15.421977 | AB11: 0 | AC11: 229084 | AE11: -26.781207 | AF11: -46.552342 | AI11: 229084 | AJ11: 4764947.2 | AL11: 43.77 | AM11: 15.15 | AN11: Medium | AO11: {=_FV(A11,"Currency")} -> USD | AP11: {=_FV(A11,"Exchange")} -> NYSE Arca | AQ11: {=_FV(A11,"Exchange abbreviation",TRUE)} -> ARCX | AR11: {=_FV(A11,"Instrument type",TRUE)} -> Stock
A12: #VALUE! | B12: JETD | C12: Bank Of Montreal MAX Airlines -3X Inverse Leveraged ETNs | D12: {=_FV(A12,"Last trade time",TRUE)} -> 45824.84 | E12: {=_FV(A12,"Price")} -> 9.7482 | F12: {=_FV(A12,"Change (%)",TRUE)} -> -0.056682 | G12: {=_FV(A12,"Change")} -> -0.5857 | H12: {=_FV(A12,"Open")} -> 9.91 | I12: {=_FV(A12,"Low")} -> 9.62 | J12: {=_FV(A12,"High")} -> 9.919 | K12: {=_FV(A12,"Previous close",TRUE)} -> 10.3339 | M12: {=_FV(A12,"52 week low",TRUE)} -> 8.78 | N12: {=_FV(A12,"52 week high",TRUE)} -> 27.74 | O12: {=_FV(A12,"Volume")} -> 11594 | P12: {=_FV(A12,"Volume average",TRUE)} -> 15050 | Q12: Trading--Inverse Equity | R12: Equities - Airlines - Short | S12: Bank of Montreal | T12: {=_FV(A12,"Expense ratio",TRUE)} -> #VALUE! | U12: {=_FV(A12,"Market cap",TRUE)} -> 104909700000 | V12: 1932554 | W12: 1932554 | Y12: 2023-06-19 | Z12: 8.98953 | AA12: 14.365964 | AB12: 0 | AC12: 15596 | AE12: -28.907496 | AF12: -58.023356 | AI12: 15596 | AJ12: 140675.92 | AL12: 27.74 | AM12: 8.78 | AN12: Low | AO12: {=_FV(A12,"Currency")} -> USD | AP12: {=_FV(A12,"Exchange")} -> NYSE Arca | AQ12: {=_FV(A12,"Exchange abbreviation",TRUE)} -> ARCX | AR12: {=_FV(A12,"Instrument type",TRUE)} -> Stock
A13: #VALUE! | B13: VXX | C13: Barclays PLC | D13: {=_FV(A13,"Last trade time",TRUE)} -> 45824.941 | E13: {=_FV(A13,"Price")} -> 51.37 | F13: {=_FV(A13,"Change (%)",TRUE)} -> -0.06854 | G13: {=_FV(A13,"Change")} -> -3.78 | H13: {=_FV(A13,"Open")} -> 52.97 | I13: {=_FV(A13,"Low")} -> 50.84 | J13: {=_FV(A13,"High")} -> 52.98 | K13: {=_FV(A13,"Previous close",TRUE)} -> 55.15 | M13: {=_FV(A13,"52 week low",TRUE)} -> 39.98 | N13: {=_FV(A13,"52 week high",TRUE)} -> 91.19 | O13: {=_FV(A13,"Volume")} -> 6923148 | P13: {=_FV(A13,"Volume average",TRUE)} -> 4636047 | Q13: Trading--Miscellaneous | S13: iPath | T13: {=_FV(A13,"Expense ratio",TRUE)} -> #VALUE! | U13: {=_FV(A13,"Market cap",TRUE)} -> #VALUE! | V13: 389340224 | W13: 389340224 | Y13: 2018-01-16 | Z13: 50.7358 | AB13: 0 | AC13: 6998523 | AE13: 7.4295464 | AF13: 11.822222 | AI13: 6998523 | AJ13: 3.5559495e+08 | AL13: 91.19 | AM13: 39.98 | AN13: High | AO13: {=_FV(A13,"Currency")} -> USD | AP13: {=_FV(A13,"Exchange")} -> CBOE BZX Exchange | AQ13: {=_FV(A13,"Exchange abbreviation",TRUE)} -> BATS | AR13: {=_FV(A13,"Instrument type",TRUE)} -> Stock
A14: #VALUE! | B14: SHNY | C14: Bank Of Montreal MicroSectors Gold 3X Leveraged ETNs due Janua | D14: {=_FV(A14,"Last trade time",TRUE)} -> 45824.916 | E14: {=_FV(A14,"Price")} -> 76.28 | F14: {=_FV(A14,"Change (%)",TRUE)} -> -0.041829 | G14: {=_FV(A14,"Change")} -> -3.33 | H14: {=_FV(A14,"Open")} -> 78.45 | I14: {=_FV(A14,"Low")} -> 76.08 | J14: {=_FV(A14,"High")} -> 78.45 | K14: {=_FV(A14,"Previous close",TRUE)} -> 79.61 | M14: {=_FV(A14,"52 week low",TRUE)} -> 32.68 | N14: {=_FV(A14,"52 week high",TRUE)} -> 86.5625 | O14: {=_FV(A14,"Volume")} -> 107325 | P14: {=_FV(A14,"Volume average",TRUE)} -> 123633 | Q14: Trading--Leveraged Commodities | R14: Commodities - Gold | S14: BMO Capital Markets | T14: {=_FV(A14,"Expense ratio",TRUE)} -> #VALUE! | U14: {=_FV(A14,"Market cap",TRUE)} -> 104909700000 | V14: 71322512 | W14: 71322512 | Y14: 2023-02-20 | Z14: 71.93627 | AB14: 0 | AC14: 113239 | AE14: 68.71379 | AF14: 97.890634 | AI14: 113239 | AJ14: 8143016.5 | AL14: 86.563 | AM14: 32.68 | AN14: Medium | AO14: {=_FV(A14,"Currency")} -> USD | AP14: {=_FV(A14,"Exchange")} -> NYSE Arca | AQ14: {=_FV(A14,"Exchange abbreviation",TRUE)} -> ARCX | AR14: {=_FV(A14,"Instrument type",TRUE)} -> Stock
A15: #VALUE! | B15: DGP | C15: DB Gold Double Long ETN Exp 15 Feb 2038 | D15: {=_FV(A15,"Last trade time",TRUE)} -> 45824.849 | E15: {=_FV(A15,"Price")} -> 105.01 | F15: {=_FV(A15,"Change (%)",TRUE)} -> -0.021342 | G15: {=_FV(A15,"Change")} -> -2.29 | H15: {=_FV(A15,"Open")} -> 106.8 | I15: {=_FV(A15,"Low")} -> 104.95 | J15: {=_FV(A15,"High")} -> 106.83 | K15: {=_FV(A15,"Previous close",TRUE)} -> 107.3 | M15: {=_FV(A15,"52 week low",TRUE)} -> 52.2301 | N15: {=_FV(A15,"52 week high",TRUE)} -> 109.72 | O15: {=_FV(A15,"Volume")} -> 46206 | P15: {=_FV(A15,"Volume average",TRUE)} -> 23389 | Q15: Trading--Leveraged Commodities | R15: Commodities - Gold | S15: Deutsche Bank AG | T15: {=_FV(A15,"Expense ratio",TRUE)} -> #VALUE! | U15: {=_FV(A15,"Market cap",TRUE)} -> #VALUE! | V15: 163395040 | W15: 163395040 | Y15: 2008-02-26 | Z15: 101.34806 | AB15: 0 | AC15: 29142 | AE15: 48.8515 | AF15: 81.516502 | AI15: 29142 | AJ15: 2922942.6 | AL15: 109.72 | AM15: 52.23 | AN15: Medium | AO15: {=_FV(A15,"Currency")} -> USD | AP15: {=_FV(A15,"Exchange")} -> NYSE Arca | AQ15: {=_FV(A15,"Exchange abbreviation",TRUE)} -> ARCX | AR15: {=_FV(A15,"Instrument type",TRUE)} -> Stock
A16: #VALUE! | B16: BERZ | C16: MicroSectors FANG & Innovation -3x Inverse Leveraged ETN | D16: {=_FV(A16,"Last trade time",TRUE)} -> 45824.878 | E16: {=_FV(A16,"Price")} -> 6.51 | F16: {=_FV(A16,"Change (%)",TRUE)} -> -0.073969 | G16: {=_FV(A16,"Change")} -> -0.52 | H16: {=_FV(A16,"Open")} -> 6.81 | I16: {=_FV(A16,"Low")} -> 6.48 | J16: {=_FV(A16,"High")} -> 6.81 | K16: {=_FV(A16,"Previous close",TRUE)} -> 7.03 | M16: {=_FV(A16,"52 week low",TRUE)} -> 6.48 | N16: {=_FV(A16,"52 week high",TRUE)} -> 31.62 | O16: {=_FV(A16,"Volume")} -> 511193 | P16: {=_FV(A16,"Volume average",TRUE)} -> 301662 | Q16: Trading--Inverse Equity | R16: Equities - - Short | S16: BMO Capital Markets | T16: {=_FV(A16,"Expense ratio",TRUE)} -> #VALUE! | U16: {=_FV(A16,"Market cap",TRUE)} -> 104909700000 | V16: 5334667 | W16: 5334667 | X16: -70.34% | Y16: 2021-08-16 | Z16: 7.1063 | AA16: 31.97148 | AB16: 0 | AC16: 274288 | AE16: -48.624536 | AF16: -71.136175 | AI16: 274288 | AJ16: 1947444.8 | AL16: 31.62 | AM16: 6.86 | AN16: Medium | AO16: {=_FV(A16,"Currency")} -> USD | AP16: {=_FV(A16,"Exchange")} -> NYSE Arca | AQ16: {=_FV(A16,"Exchange abbreviation",TRUE)} -> ARCX | AR16: {=_FV(A16,"Instrument type",TRUE)} -> Stock
A17: #VALUE! | B17: DJP | C17: Barclays Bank iPath Bloomberg Commodity Index Total Return ETN Exp 12 June | D17: {=_FV(A17,"Last trade time",TRUE)} -> 45824.84 | E17: {=_FV(A17,"Price")} -> 35.27 | F17: {=_FV(A17,"Change (%)",TRUE)} -> 0.003414 | G17: {=_FV(A17,"Change")} -> 0.12 | H17: {=_FV(A17,"Open")} -> 35.28 | I17: {=_FV(A17,"Low")} -> 35.01 | J17: {=_FV(A17,"High")} -> 35.3646 | K17: {=_FV(A17,"Previous close",TRUE)} -> 35.15 | M17: {=_FV(A17,"52 week low",TRUE)} -> 29.3501 | N17: {=_FV(A17,"52 week high",TRUE)} -> 35.78 | O17: {=_FV(A17,"Volume")} -> 316915 | P17: {=_FV(A17,"Volume average",TRUE)} -> 37367 | Q17: Commodities Broad Basket | R17: Commodities - Diversified | S17: iPath | T17: {=_FV(A17,"Expense ratio",TRUE)} -> #VALUE! | U17: {=_FV(A17,"Market cap",TRUE)} -> #VALUE! | V17: 558780352 | W17: 558780352 | Y17: 2006-06-05 | Z17: 34.3786 | AB17: 0 | AC17: 60212 | AE17: 6.0839943 | AF17: 4.2805097 | AI17: 60212 | AJ17: 2068884.3 | AL17: 35.78 | AM17: 29.35 | AN17: Medium | AO17: {=_FV(A17,"Currency")} -> USD | AP17: {=_FV(A17,"Exchange")} -> NYSE Arca | AQ17: {=_FV(A17,"Exchange abbreviation",TRUE)} -> ARCX | AR17: {=_FV(A17,"Instrument type",TRUE)} -> Stock
A18: #VALUE! | B18: FNGD | C18: NO Name | D18: {=_FV(A18,"Last trade time",TRUE)} -> 45824.932 | E18: {=_FV(A18,"Price")} -> 7.4893 | F18: {=_FV(A18,"Change (%)",TRUE)} -> -0.038601 | G18: {=_FV(A18,"Change")} -> -0.3007 | H18: {=_FV(A18,"Open")} -> 7.66 | I18: {=_FV(A18,"Low")} -> 7.4 | J18: {=_FV(A18,"High")} -> 7.66 | K18: {=_FV(A18,"Previous close",TRUE)} -> 7.79 | M18: {=_FV(A18,"52 week low",TRUE)} -> 7.4 | N18: {=_FV(A18,"52 week high",TRUE)} -> 36.67 | O18: {=_FV(A18,"Volume")} -> 4431949 | P18: {=_FV(A18,"Volume average",TRUE)} -> 4344211 | Q18: Other | T18: {=_FV(A18,"Expense ratio",TRUE)} -> #VALUE! | U18: {=_FV(A18,"Market cap",TRUE)} -> 104909700000 | AC18: 4425987 | AN18: Unknown | AO18: {=_FV(A18,"Currency")} -> USD | AP18: {=_FV(A18,"Exchange")} -> NYSE Arca | AQ18: {=_FV(A18,"Exchange abbreviation",TRUE)} -> ARCX | AR18: {=_FV(A18,"Instrument type",TRUE)} -> Stock
A19: #VALUE! | B19: USML | C19: ETRACS 2x Leveraged MSCI US Minimum Volatility Factor TR ETN | D19: {=_FV(A19,"Last trade time",TRUE)} -> 45824.84 | E19: {=_FV(A19,"Price")} -> 41.2629 | F19: {=_FV(A19,"Change (%)",TRUE)} -> 0.001908 | G19: {=_FV(A19,"Change")} -> 0.0786 | H19: {=_FV(A19,"Open")} -> 41.2629 | I19: {=_FV(A19,"Low")} -> 41.2629 | J19: {=_FV(A19,"High")} -> 41.2629 | K19: {=_FV(A19,"Previous close",TRUE)} -> 41.1843 | M19: {=_FV(A19,"52 week low",TRUE)} -> 34.2953 | N19: {=_FV(A19,"52 week high",TRUE)} -> 47.66 | O19: {=_FV(A19,"Volume")} -> 0 | P19: {=_FV(A19,"Volume average",TRUE)} -> 253 | Q19: Trading--Leveraged Equity | S19: UBS | T19: {=_FV(A19,"Expense ratio",TRUE)} -> #VALUE! | U19: {=_FV(A19,"Market cap",TRUE)} -> 76546930000 | V19: 12542970 | W19: 12542970 | Y19: 2021-02-04 | Z19: 41.9514 | AB19: 0 | AC19: 214 | AE19: 8.6122114 | AF19: 20.705484 | AI19: 214 | AJ19: 8993.3928 | AL19: 47.66 | AM19: 34.278 | AN19: Low | AO19: {=_FV(A19,"Currency")} -> USD | AP19: {=_FV(A19,"Exchange")} -> NYSE Arca | AQ19: {=_FV(A19,"Exchange abbreviation",TRUE)} -> ARCX | AR19: {=_FV(A19,"Instrument type",TRUE)} -> Stock
A20: #VALUE! | B20: VXZ | C20: Barclays PLC | D20: {=_FV(A20,"Last trade time",TRUE)} -> 45824.84 | E20: {=_FV(A20,"Price")} -> 59.38 | F20: {=_FV(A20,"Change (%)",TRUE)} -> -0.026876 | G20: {=_FV(A20,"Change")} -> -1.64 | H20: {=_FV(A20,"Open")} -> 59.55 | I20: {=_FV(A20,"Low")} -> 58.84 | J20: {=_FV(A20,"High")} -> 59.55 | K20: {=_FV(A20,"Previous close",TRUE)} -> 61.02 | M20: {=_FV(A20,"52 week low",TRUE)} -> 47.5 | N20: {=_FV(A20,"52 week high",TRUE)} -> 69.33 | O20: {=_FV(A20,"Volume")} -> 6140 | P20: {=_FV(A20,"Volume average",TRUE)} -> 11620 | Q20: Trading--Miscellaneous | S20: iPath | T20: {=_FV(A20,"Expense ratio",TRUE)} -> #VALUE! | U20: {=_FV(A20,"Market cap",TRUE)} -> #VALUE! | V20: 36265044 | W20: 36265044 | Y20: 2018-01-16 | Z20: 58.8354 | AB20: 0 | AC20: 31736 | AE20: 15.566034 | AF20: 20.196242 | AI20: 31736 | AJ20: 1868615.7 | AL20: 69.33 | AM20: 47.5 | AN20: Medium | AO20: {=_FV(A20,"Currency")} -> USD | AP20: {=_FV(A20,"Exchange")} -> CBOE BZX Exchange | AQ20: {=_FV(A20,"Exchange abbreviation",TRUE)} -> BATS | AR20: {=_FV(A20,"Instrument type",TRUE)} -> Stock
A21: #VALUE! | B21: SCDL | C21: ETRACS 2x Leveraged US Dividend Factor TR ETN | D21: {=_FV(A21,"Last trade time",TRUE)} -> 45824.84 | E21: {=_FV(A21,"Price")} -> 37.1143 | F21: {=_FV(A21,"Change (%)",TRUE)} -> 0.001863 | G21: {=_FV(A21,"Change")} -> 0.069 | H21: {=_FV(A21,"Open")} -> 37.1143 | I21: {=_FV(A21,"Low")} -> 37.1143 | J21: {=_FV(A21,"High")} -> 37.1143 | K21: {=_FV(A21,"Previous close",TRUE)} -> 37.0453 | M21: {=_FV(A21,"52 week low",TRUE)} -> 29.83 | N21: {=_FV(A21,"52 week high",TRUE)} -> 44.8993 | O21: {=_FV(A21,"Volume")} -> 22 | P21: {=_FV(A21,"Volume average",TRUE)} -> 3 | Q21: Trading--Leveraged Equity | S21: UBS | T21: {=_FV(A21,"Expense ratio",TRUE)} -> #VALUE! | U21: {=_FV(A21,"Market cap",TRUE)} -> 76546930000 | V21: 10595610 | W21: 10595610 | Y21: 2021-02-04 | Z21: 36.2171 | AB21: 0 | AC21: 711 | AE21: -5.6190533 | AF21: 4.5696804 | AI21: 711 | AJ21: 25763.369 | AL21: 44.899 | AM21: 29.83 | AN21: Low | AO21: {=_FV(A21,"Currency")} -> USD | AP21: {=_FV(A21,"Exchange")} -> NYSE Arca | AQ21: {=_FV(A21,"Exchange abbreviation",TRUE)} -> ARCX | AR21: {=_FV(A21,"Instrument type",TRUE)} -> Stock
A22: #VALUE! | B22: USOI | C22: Ubs Ag Etracs Crude Oil Shares Covered Call ETN Exp 24th Apr 2037 | D22: {=_FV(A22,"Last trade time",TRUE)} -> 45824.929 | E22: {=_FV(A22,"Price")} -> 56.22 | F22: {=_FV(A22,"Change (%)",TRUE)} -> -0.005484 | G22: {=_FV(A22,"Change")} -> -0.31 | H22: {=_FV(A22,"Open")} -> 56.89 | I22: {=_FV(A22,"Low")} -> 55.77 | J22: {=_FV(A22,"High")} -> 56.9455 | K22: {=_FV(A22,"Previous close",TRUE)} -> 56.53 | M22: {=_FV(A22,"52 week low",TRUE)} -> 50.05 | N22: {=_FV(A22,"52 week high",TRUE)} -> 75.9903 | O22: {=_FV(A22,"Volume")} -> 142590 | P22: {=_FV(A22,"Volume average",TRUE)} -> 70145 | Q22: Commodities Focused | R22: Commodities - Oil | S22: UBS AG | T22: {=_FV(A22,"Expense ratio",TRUE)} -> #VALUE! | U22: {=_FV(A22,"Market cap",TRUE)} -> 76546930000 | V22: 290861312 | W22: 290861312 | Y22: 2017-04-24 | Z22: 55.6482 | AB22: 0.24120001 | AC22: 48207 | AE22: -7.6515029 | AF22: -2.0416446 | AI22: 48207 | AJ22: 2700556.1 | AL22: 75.99 | AM22: 50.05 | AN22: Medium | AO22: {=_FV(A22,"Currency")} -> USD | AP22: {=_FV(A22,"Exchange")} -> Nasdaq Stock Market | AQ22: {=_FV(A22,"Exchange abbreviation",TRUE)} -> XNAS | AR22: {=_FV(A22,"Instrument type",TRUE)} -> Stock
A23: #VALUE! | B23: BNKD | C23: Bank Of Montreal MicroSectors U.S. Big Banks -3 Inverse Leve | D23: {=_FV(A23,"Last trade time",TRUE)} -> 45824.84 | E23: {=_FV(A23,"Price")} -> 23.2586 | F23: {=_FV(A23,"Change (%)",TRUE)} -> -0.047161 | G23: {=_FV(A23,"Change")} -> -1.1512 | H23: {=_FV(A23,"Open")} -> 23.2586 | I23: {=_FV(A23,"Low")} -> 23.2586 | J23: {=_FV(A23,"High")} -> 23.2586 | K23: {=_FV(A23,"Previous close",TRUE)} -> 24.4098 | M23: {=_FV(A23,"52 week low",TRUE)} -> 22.46 | N23: {=_FV(A23,"52 week high",TRUE)} -> 56.76 | O23: {=_FV(A23,"Volume")} -> 88 | P23: {=_FV(A23,"Volume average",TRUE)} -> 445 | Q23: Financial | T23: {=_FV(A23,"Expense ratio",TRUE)} -> #VALUE! | U23: {=_FV(A23,"Market cap",TRUE)} -> 104909700000 | X23: -15.14% | AC23: 455 | AN23: Unknown | AO23: {=_FV(A23,"Currency")} -> USD | AP23: {=_FV(A23,"Exchange")} -> NYSE Arca | AQ23: {=_FV(A23,"Exchange abbreviation",TRUE)} -> ARCX | AR23: {=_FV(A23,"Instrument type",TRUE)} -> Stock
A24: #VALUE! | B24: GLDI | C24: Ubs Ag Etracs Gold Shares Covered Call ETN Exp 02 Feb 2033 | D24: {=_FV(A24,"Last trade time",TRUE)} -> 45824.867 | E24: {=_FV(A24,"Price")} -> 163.56 | F24: {=_FV(A24,"Change (%)",TRUE)} -> -0.007524 | G24: {=_FV(A24,"Change")} -> -1.24 | H24: {=_FV(A24,"Open")} -> 164.51 | I24: {=_FV(A24,"Low")} -> 163.11 | J24: {=_FV(A24,"High")} -> 164.8923 | K24: {=_FV(A24,"Previous close",TRUE)} -> 164.8 | M24: {=_FV(A24,"52 week low",TRUE)} -> 141.74 | N24: {=_FV(A24,"52 week high",TRUE)} -> 166.79 | O24: {=_FV(A24,"Volume")} -> 6574 | P24: {=_FV(A24,"Volume average",TRUE)} -> 8851 | Q24: Commodities Focused | R24: Commodities - Gold | S24: UBS AG | T24: {=_FV(A24,"Expense ratio",TRUE)} -> #VALUE! | U24: {=_FV(A24,"Market cap",TRUE)} -> 76546930000 | V24: 111699984 | W24: 111699984 | Y24: 2013-01-28 | Z24: 162.1176 | AB24: 0.14050001 | AC24: 8811 | AE24: 11.995684 | AF24: 23.632736 | AI24: 8811 | AJ24: 1423240.8 | AL24: 166.79 | AM24: 141.74 | AN24: Medium | AO24: {=_FV(A24,"Currency")} -> USD | AP24: {=_FV(A24,"Exchange")} -> Nasdaq Stock Market | AQ24: {=_FV(A24,"Exchange abbreviation",TRUE)} -> XNAS | AR24: {=_FV(A24,"Instrument type",TRUE)} -> Stock
A25: #VALUE! | B25: ATMP | C25: Barclays PLC | D25: {=_FV(A25,"Last trade time",TRUE)} -> 45824.84 | E25: {=_FV(A25,"Price")} -> 29.02 | F25: {=_FV(A25,"Change (%)",TRUE)} -> -0.012253 | G25: {=_FV(A25,"Change")} -> -0.36 | H25: {=_FV(A25,"Open")} -> 29.19 | I25: {=_FV(A25,"Low")} -> 28.95 | J25: {=_FV(A25,"High")} -> 29.261 | K25: {=_FV(A25,"Previous close",TRUE)} -> 29.38 | M25: {=_FV(A25,"52 week low",TRUE)} -> 24.02 | N25: {=_FV(A25,"52 week high",TRUE)} -> 32.09 | O25: {=_FV(A25,"Volume")} -> 14815 | P25: {=_FV(A25,"Volume average",TRUE)} -> 21132 | Q25: Other | T25: {=_FV(A25,"Expense ratio",TRUE)} -> #VALUE! | U25: {=_FV(A25,"Market cap",TRUE)} -> 45350550000 | X25: 20.04% | AC25: 21313 | AN25: Unknown | AO25: {=_FV(A25,"Currency")} -> USD | AP25: {=_FV(A25,"Exchange")} -> CBOE BZX Exchange | AQ25: {=_FV(A25,"Exchange abbreviation",TRUE)} -> BATS | AR25: {=_FV(A25,"Instrument type",TRUE)} -> Stock
A26: #VALUE! | B26: IWFL | C26: ETRACS 2x Leveraged US Growth Factor TR ETN | D26: {=_FV(A26,"Last trade time",TRUE)} -> 45824.84 | E26: {=_FV(A26,"Price")} -> 44.8862 | F26: {=_FV(A26,"Change (%)",TRUE)} -> 0.022113 | G26: {=_FV(A26,"Change")} -> 0.9711 | H26: {=_FV(A26,"Open")} -> 44.8862 | I26: {=_FV(A26,"Low")} -> 44.8862 | J26: {=_FV(A26,"High")} -> 44.8862 | K26: {=_FV(A26,"Previous close",TRUE)} -> 43.9151 | M26: {=_FV(A26,"52 week low",TRUE)} -> 26.45 | N26: {=_FV(A26,"52 week high",TRUE)} -> 53.85 | O26: {=_FV(A26,"Volume")} -> 64 | P26: {=_FV(A26,"Volume average",TRUE)} -> 413 | Q26: Size/Style | R26: Equities - Growth Factor | T26: {=_FV(A26,"Expense ratio",TRUE)} -> #VALUE! | U26: {=_FV(A26,"Market cap",TRUE)} -> 76546930000 | AC26: 366 | AN26: Unknown | AO26: {=_FV(A26,"Currency")} -> USD | AP26: {=_FV(A26,"Exchange")} -> NYSE Arca | AQ26: {=_FV(A26,"Exchange abbreviation",TRUE)} -> ARCX | AR26: {=_FV(A26,"Instrument type",TRUE)} -> Stock
A27: #VALUE! | B27: TXUG | C27: Thornburg International Growth Fund ETF | D27: {=_FV(A27,"Last trade time",TRUE)} -> 45824.844 | E27: {=_FV(A27,"Price")} -> 25.6725 | F27: {=_FV(A27,"Change (%)",TRUE)} -> 0.004166 | G27: {=_FV(A27,"Change")} -> 0.1065 | H27: {=_FV(A27,"Open")} -> 25.6725 | I27: {=_FV(A27,"Low")} -> 25.6725 | J27: {=_FV(A27,"High")} -> 25.6725 | K27: {=_FV(A27,"Previous close",TRUE)} -> 25.566 | M27: {=_FV(A27,"52 week low",TRUE)} -> 21.26 | N27: {=_FV(A27,"52 week high",TRUE)} -> 26.1405 | O27: {=_FV(A27,"Volume")} -> 68 | P27: {=_FV(A27,"Volume average",TRUE)} -> 313 | Q27: Foreign Large Growth | S27: Thornburg | T27: {=_FV(A27,"Expense ratio",TRUE)} -> #VALUE! | U27: {=_FV(A27,"Market cap",TRUE)} -> #VALUE! | V27: 5082172 | W27: 5082172 | Y27: 2025-01-21 | Z27: 25.60452 | AC27: 642 | AE27: 2.7330955 | AI27: 642 | AJ27: 16461.586 | AL27: 26.141 | AM27: 21.26 | AN27: Low | AO27: {=_FV(A27,"Currency")} -> USD | AP27: {=_FV(A27,"Exchange")} -> Nasdaq Stock Market | AQ27: {=_FV(A27,"Exchange abbreviation",TRUE)} -> XNAS | AR27: {=_FV(A27,"Instrument type",TRUE)} -> ETF
A28: #VALUE! | B28: MLPB | C28: NO Name | D28: {=_FV(A28,"Last trade time",TRUE)} -> 45824.84 | E28: {=_FV(A28,"Price")} -> 26.0115 | F28: {=_FV(A28,"Change (%)",TRUE)} -> -0.00878 | G28: {=_FV(A28,"Change")} -> -0.2304 | H28: {=_FV(A28,"Open")} -> 26.19 | I28: {=_FV(A28,"Low")} -> 25.92 | J28: {=_FV(A28,"High")} -> 26.19 | K28: {=_FV(A28,"Previous close",TRUE)} -> 26.2419 | M28: {=_FV(A28,"52 week low",TRUE)} -> 22.75 | N28: {=_FV(A28,"52 week high",TRUE)} -> 28.96 | O28: {=_FV(A28,"Volume")} -> 1812 | P28: {=_FV(A28,"Volume average",TRUE)} -> 6635 | Q28: Energy Limited Partnership | S28: UBS | T28: {=_FV(A28,"Expense ratio",TRUE)} -> #VALUE! | U28: {=_FV(A28,"Market cap",TRUE)} -> 76546930000 | V28: 208112720 | W28: 208112720 | Y28: 2015-10-08 | Z28: 25.9645 | AB28: 0.0622 | AC28: 6979 | AE28: 3.9953461 | AF28: 15.727175 | AI28: 6979 | AJ28: 181094.58 | AL28: 28.96 | AM28: 22.75 | AN28: Low | AO28: {=_FV(A28,"Currency")} -> USD | AP28: {=_FV(A28,"Exchange")} -> NYSE Arca | AQ28: {=_FV(A28,"Exchange abbreviation",TRUE)} -> ARCX | AR28: {=_FV(A28,"Instrument type",TRUE)} -> Stock
A29: #VALUE! | B29: IWDL | C29: ETRACS 2x Leveraged US Value Factor TR ETN | D29: {=_FV(A29,"Last trade time",TRUE)} -> 45824.84 | E29: {=_FV(A29,"Price")} -> 40.0263 | F29: {=_FV(A29,"Change (%)",TRUE)} -> 0.014884 | G29: {=_FV(A29,"Change")} -> 0.587 | H29: {=_FV(A29,"Open")} -> 40.05 | I29: {=_FV(A29,"Low")} -> 40.0263 | J29: {=_FV(A29,"High")} -> 40.0501 | K29: {=_FV(A29,"Previous close",TRUE)} -> 39.4393 | M29: {=_FV(A29,"52 week low",TRUE)} -> 30.21 | N29: {=_FV(A29,"52 week high",TRUE)} -> 57.62 | O29: {=_FV(A29,"Volume")} -> 2017 | P29: {=_FV(A29,"Volume average",TRUE)} -> 108 | Q29: Size/Style | R29: Equities - Value Factor | T29: {=_FV(A29,"Expense ratio",TRUE)} -> #VALUE! | U29: {=_FV(A29,"Market cap",TRUE)} -> 76546930000 | AC29: 76 | AN29: Unknown | AO29: {=_FV(A29,"Currency")} -> USD | AP29: {=_FV(A29,"Exchange")} -> NYSE Arca | AQ29: {=_FV(A29,"Exchange abbreviation",TRUE)} -> ARCX | AR29: {=_FV(A29,"Instrument type",TRUE)} -> Stock
A30: #VALUE! | B30: QULL | C30: ETRACS 2x Leveraged MSCI US Quality Factor TR ETN | D30: {=_FV(A30,"Last trade time",TRUE)} -> 45824.84 | E30: {=_FV(A30,"Price")} -> 47.339 | F30: {=_FV(A30,"Change (%)",TRUE)} -> 0.017918 | G30: {=_FV(A30,"Change")} -> 0.8333 | H30: {=_FV(A30,"Open")} -> 47.339 | I30: {=_FV(A30,"Low")} -> 47.339 | J30: {=_FV(A30,"High")} -> 47.339 | K30: {=_FV(A30,"Previous close",TRUE)} -> 46.5057 | M30: {=_FV(A30,"52 week low",TRUE)} -> 33.51 | N30: {=_FV(A30,"52 week high",TRUE)} -> 53.0381 | O30: {=_FV(A30,"Volume")} -> 5 | P30: {=_FV(A30,"Volume average",TRUE)} -> 32 | Q30: Trading--Leveraged Equity | R30: Equities - Quality Factor | S30: UBS | T30: {=_FV(A30,"Expense ratio",TRUE)} -> #VALUE! | U30: {=_FV(A30,"Market cap",TRUE)} -> 76546930000 | V30: 13856700 | W30: 13856700 | Y30: 2021-02-04 | Z30: 47.6938 | AB30: 0 | AC30: 196 | AE30: -0.87630031 | AF30: 7.6544794 | AI30: 196 | AJ30: 9366.0952 | AL30: 53.038 | AM30: 33.51 | AN30: Low | AO30: {=_FV(A30,"Currency")} -> USD | AP30: {=_FV(A30,"Exchange")} -> NYSE Arca | AQ30: {=_FV(A30,"Exchange abbreviation",TRUE)} -> ARCX | AR30: {=_FV(A30,"Instrument type",TRUE)} -> Stock
A31: #VALUE! | B31: AMUB | C31: NO Name | D31: {=_FV(A31,"Last trade time",TRUE)} -> 45824.84 | E31: {=_FV(A31,"Price")} -> 19.1793 | F31: {=_FV(A31,"Change (%)",TRUE)} -> -0.007955 | G31: {=_FV(A31,"Change")} -> -0.1538 | H31: {=_FV(A31,"Open")} -> 19.1793 | I31: {=_FV(A31,"Low")} -> 19.1793 | J31: {=_FV(A31,"High")} -> 19.1793 | K31: {=_FV(A31,"Previous close",TRUE)} -> 19.3331 | M31: {=_FV(A31,"52 week low",TRUE)} -> 16.8574 | N31: {=_FV(A31,"52 week high",TRUE)} -> 20.8771 | O31: {=_FV(A31,"Volume")} -> 5 | P31: {=_FV(A31,"Volume average",TRUE)} -> 2995 | Q31: Energy Limited Partnership | S31: UBS | T31: {=_FV(A31,"Expense ratio",TRUE)} -> #VALUE! | U31: {=_FV(A31,"Market cap",TRUE)} -> 76546930000 | V31: 48549540 | W31: 48549540 | X31: 8.83% | Y31: 2015-10-08 | Z31: 19.1277 | AB31: 0.062800005 | AC31: 2303 | AE31: 3.994512 | AF31: 14.701926 | AI31: 2303 | AJ31: 44002.96 | AL31: 20.877 | AM31: 16.857 | AN31: Low | AO31: {=_FV(A31,"Currency")} -> USD | AP31: {=_FV(A31,"Exchange")} -> NYSE Arca | AQ31: {=_FV(A31,"Exchange abbreviation",TRUE)} -> ARCX | AR31: {=_FV(A31,"Instrument type",TRUE)} -> Stock
A32: #VALUE! | B32: GRN | C32: iPathA Series B Carbon ETN | D32: {=_FV(A32,"Last trade time",TRUE)} -> 45824.84 | E32: {=_FV(A32,"Price")} -> 29.51 | F32: {=_FV(A32,"Change (%)",TRUE)} -> -0.00789 | G32: {=_FV(A32,"Change")} -> -0.2347 | H32: {=_FV(A32,"Open")} -> 29.51 | I32: {=_FV(A32,"Low")} -> 29.51 | J32: {=_FV(A32,"High")} -> 29.51 | K32: {=_FV(A32,"Previous close",TRUE)} -> 29.7447 | M32: {=_FV(A32,"52 week low",TRUE)} -> 23.825 | N32: {=_FV(A32,"52 week high",TRUE)} -> 32.88 | O32: {=_FV(A32,"Volume")} -> 580 | P32: {=_FV(A32,"Volume average",TRUE)} -> 1148 | Q32: Commodities Focused | R32: Commodities - Carbon | S32: iPath | T32: {=_FV(A32,"Expense ratio",TRUE)} -> #VALUE! | U32: {=_FV(A32,"Market cap",TRUE)} -> #VALUE! | V32: 20309600 | W32: 20309600 | Y32: 2019-09-09 | Z32: 28.9432 | AA32: 3.1318347 | AB32: 0 | AC32: 3895 | AE32: 0.49923753 | AF32: 4.3582406 | AI32: 3895 | AJ32: 113069.51 | AL32: 32.88 | AM32: 23.825 | AN32: Low | AO32: {=_FV(A32,"Currency")} -> USD | AP32: {=_FV(A32,"Exchange")} -> NYSE Arca | AQ32: {=_FV(A32,"Exchange abbreviation",TRUE)} -> ARCX | AR32: {=_FV(A32,"Instrument type",TRUE)} -> Stock
A33: #VALUE! | B33: IFED | C33: ETRACS IFED Invest with the Fed TR Index ETN | D33: {=_FV(A33,"Last trade time",TRUE)} -> 45824.84 | E33: {=_FV(A33,"Price")} -> 43.7644 | F33: {=_FV(A33,"Change (%)",TRUE)} -> 0.015401 | G33: {=_FV(A33,"Change")} -> 0.6638 | H33: {=_FV(A33,"Open")} -> 43.7644 | I33: {=_FV(A33,"Low")} -> 43.7644 | J33: {=_FV(A33,"High")} -> 43.7644 | K33: {=_FV(A33,"Previous close",TRUE)} -> 43.1006 | M33: {=_FV(A33,"52 week low",TRUE)} -> 34 | N33: {=_FV(A33,"52 week high",TRUE)} -> 49.7 | O33: {=_FV(A33,"Volume")} -> 10 | P33: {=_FV(A33,"Volume average",TRUE)} -> 451 | Q33: Large Blend | S33: UBS | T33: {=_FV(A33,"Expense ratio",TRUE)} -> #VALUE! | U33: {=_FV(A33,"Market cap",TRUE)} -> 76546930000 | V33: 86366000 | W33: 86366000 | Y33: 2021-09-13 | Z33: 44.2323 | AB33: 0 | AC33: 215 | AE33: 8.5125805 | AF33: 19.407729 | AI33: 215 | AJ33: 9510.7185 | AL33: 49.7 | AM33: 34 | AN33: Low | AO33: {=_FV(A33,"Currency")} -> USD | AP33: {=_FV(A33,"Exchange")} -> NYSE Arca | AQ33: {=_FV(A33,"Exchange abbreviation",TRUE)} -> ARCX | AR33: {=_FV(A33,"Instrument type",TRUE)} -> Stock
A34: #VALUE! | B34: MTUL | C34: ETRACS 2x Leveraged MSCI US Momentum Factor TR ETN | D34: {=_FV(A34,"Last trade time",TRUE)} -> 45824.84 | E34: {=_FV(A34,"Price")} -> 33.5746 | F34: {=_FV(A34,"Change (%)",TRUE)} -> 0.012821 | G34: {=_FV(A34,"Change")} -> 0.425 | H34: {=_FV(A34,"Open")} -> 33.5746 | I34: {=_FV(A34,"Low")} -> 33.5746 | J34: {=_FV(A34,"High")} -> 33.5746 | K34: {=_FV(A34,"Previous close",TRUE)} -> 33.1496 | M34: {=_FV(A34,"52 week low",TRUE)} -> 20.38 | N34: {=_FV(A34,"52 week high",TRUE)} -> 35.4782 | O34: {=_FV(A34,"Volume")} -> 11 | P34: {=_FV(A34,"Volume average",TRUE)} -> 21 | Q34: Trading--Leveraged Equity | R34: Equities - Momentum Factor | S34: UBS | T34: {=_FV(A34,"Expense ratio",TRUE)} -> #VALUE! | U34: {=_FV(A34,"Market cap",TRUE)} -> 76546930000 | V34: 10121400 | W34: 10121400 | Y34: 2021-02-04 | Z34: 34.0553 | AB34: 0 | AC34: 371 | AE34: 13.010613 | AF34: 26.488938 | AI34: 371 | AJ34: 12647.576 | AL34: 35.478 | AM34: 20.38 | AN34: Low | AO34: {=_FV(A34,"Currency")} -> USD | AP34: {=_FV(A34,"Exchange")} -> NYSE Arca | AQ34: {=_FV(A34,"Exchange abbreviation",TRUE)} -> ARCX | AR34: {=_FV(A34,"Instrument type",TRUE)} -> Stock
A35: #VALUE! | B35: SLVO | C35: Ubs Ag Etracs Silver Shares Covered Call ETN Exp 21 Apr 2033 | D35: {=_FV(A35,"Last trade time",TRUE)} -> 45824.876 | E35: {=_FV(A35,"Price")} -> 81.2 | F35: {=_FV(A35,"Change (%)",TRUE)} -> 0.002098 | G35: {=_FV(A35,"Change")} -> 0.17 | H35: {=_FV(A35,"Open")} -> 80.88 | I35: {=_FV(A35,"Low")} -> 80.88 | J35: {=_FV(A35,"High")} -> 81.4 | K35: {=_FV(A35,"Previous close",TRUE)} -> 81.03 | M35: {=_FV(A35,"52 week low",TRUE)} -> 72.6 | N35: {=_FV(A35,"52 week high",TRUE)} -> 86.36 | O35: {=_FV(A35,"Volume")} -> 29762 | P35: {=_FV(A35,"Volume average",TRUE)} -> 45169 | Q35: Commodities Focused | R35: Commodities - Silver | S35: UBS AG | T35: {=_FV(A35,"Expense ratio",TRUE)} -> #VALUE! | U35: {=_FV(A35,"Market cap",TRUE)} -> 76546930000 | V35: 191519984 | W35: 191519984 | Y35: 2013-04-15 | Z35: 80.6223 | AB35: 0.2317 | AC35: 38738 | AE35: 19.227609 | AF35: 22.670746 | AI35: 38738 | AJ35: 3123251.2 | AL35: 86.36 | AM35: 72.6 | AN35: Medium | AO35: {=_FV(A35,"Currency")} -> USD | AP35: {=_FV(A35,"Exchange")} -> Nasdaq Stock Market | AQ35: {=_FV(A35,"Exchange abbreviation",TRUE)} -> XNAS | AR35: {=_FV(A35,"Instrument type",TRUE)} -> Stock
A36: #VALUE! | B36: BDCZ | C36: NO Name | D36: {=_FV(A36,"Last trade time",TRUE)} -> 45824.84 | E36: {=_FV(A36,"Price")} -> 18.0452 | F36: {=_FV(A36,"Change (%)",TRUE)} -> -0.007917 | G36: {=_FV(A36,"Change")} -> -0.144 | H36: {=_FV(A36,"Open")} -> 18.15 | I36: {=_FV(A36,"Low")} -> 18.0452 | J36: {=_FV(A36,"High")} -> 18.15 | K36: {=_FV(A36,"Previous close",TRUE)} -> 18.1892 | M36: {=_FV(A36,"52 week low",TRUE)} -> 16.31 | N36: {=_FV(A36,"52 week high",TRUE)} -> 20.4154 | O36: {=_FV(A36,"Volume")} -> 276 | P36: {=_FV(A36,"Volume average",TRUE)} -> 876 | Q36: Financial | S36: UBS | T36: {=_FV(A36,"Expense ratio",TRUE)} -> #VALUE! | U36: {=_FV(A36,"Market cap",TRUE)} -> 76546930000 | V36: 19551040 | W36: 19551040 | X36: -7.73% | Y36: 2015-10-08 | Z36: 18.2797 | AB36: 0.098500006 | AC36: 3700 | AE36: -1.1192863 | AF36: 2.3906965 | AI36: 3700 | AJ36: 67650.06 | AL36: 20.415 | AM36: 16.31 | AN36: Low | AO36: {=_FV(A36,"Currency")} -> USD | AP36: {=_FV(A36,"Exchange")} -> NYSE Arca | AQ36: {=_FV(A36,"Exchange abbreviation",TRUE)} -> ARCX | AR36: {=_FV(A36,"Instrument type",TRUE)} -> Stock
A37: #VALUE! | B37: BDCX | C37: ETRACS Quarterly Pay 1.5x Leveraged MarketVector BDC Liquid In | D37: {=_FV(A37,"Last trade time",TRUE)} -> 45824.84 | E37: {=_FV(A37,"Price")} -> 28 | F37: {=_FV(A37,"Change (%)",TRUE)} -> -0.011341 | G37: {=_FV(A37,"Change")} -> -0.3212 | H37: {=_FV(A37,"Open")} -> 28.22 | I37: {=_FV(A37,"Low")} -> 28 | J37: {=_FV(A37,"High")} -> 28.36 | K37: {=_FV(A37,"Previous close",TRUE)} -> 28.3212 | M37: {=_FV(A37,"52 week low",TRUE)} -> 23.9495 | N37: {=_FV(A37,"52 week high",TRUE)} -> 35.98 | O37: {=_FV(A37,"Volume")} -> 4142 | P37: {=_FV(A37,"Volume average",TRUE)} -> 2379 | Q37: Trading--Leveraged Equity | S37: UBS | T37: {=_FV(A37,"Expense ratio",TRUE)} -> #VALUE! | U37: {=_FV(A37,"Market cap",TRUE)} -> 76546930000 | V37: 11418320 | W37: 11418320 | X37: -16.71% | Y37: 2020-06-01 | Z37: 28.5505 | AB37: 0.1733 | AC37: 2971 | AE37: -4.2221448 | AF37: -0.80989501 | AI37: 2971 | AJ37: 84833.934 | AL37: 35.98 | AM37: 23.95 | AN37: Low | AO37: {=_FV(A37,"Currency")} -> USD | AP37: {=_FV(A37,"Exchange")} -> NYSE Arca | AQ37: {=_FV(A37,"Exchange abbreviation",TRUE)} -> ARCX | AR37: {=_FV(A37,"Instrument type",TRUE)} -> Stock
A38: #VALUE! | B38: MLPR | C38: ETRACS Quarterly Pay 1.5X Leveraged Alerian MLP Index ETN | D38: {=_FV(A38,"Last trade time",TRUE)} -> 45824.84 | E38: {=_FV(A38,"Price")} -> 60.9326 | F38: {=_FV(A38,"Change (%)",TRUE)} -> -0.011545 | G38: {=_FV(A38,"Change")} -> -0.7117 | H38: {=_FV(A38,"Open")} -> 60.9326 | I38: {=_FV(A38,"Low")} -> 60.9326 | J38: {=_FV(A38,"High")} -> 60.9326 | K38: {=_FV(A38,"Previous close",TRUE)} -> 61.6443 | M38: {=_FV(A38,"52 week low",TRUE)} -> 50.7179 | N38: {=_FV(A38,"52 week high",TRUE)} -> 73.37 | O38: {=_FV(A38,"Volume")} -> 64 | P38: {=_FV(A38,"Volume average",TRUE)} -> 1078 | Q38: Trading--Leveraged Equity | S38: UBS | T38: {=_FV(A38,"Expense ratio",TRUE)} -> #VALUE! | U38: {=_FV(A38,"Market cap",TRUE)} -> 76546930000 | V38: 17595480 | W38: 17595480 | Y38: 2020-06-01 | Z38: 60.7127 | AB38: 0.10439999 | AC38: 1330 | AE38: 4.3829776 | AF38: 18.479675 | AI38: 1330 | AJ38: 80682.322 | AL38: 73.37 | AM38: 50.718 | AN38: Low | AO38: {=_FV(A38,"Currency")} -> USD | AP38: {=_FV(A38,"Exchange")} -> NYSE Arca | AQ38: {=_FV(A38,"Exchange abbreviation",TRUE)} -> ARCX | AR38: {=_FV(A38,"Instrument type",TRUE)} -> Stock
A39: #VALUE! | B39: AMJB | C39: JPMorgan Chase & Co. Alerian MLP Index ETNs due January 28 20 | D39: {=_FV(A39,"Last trade time",TRUE)} -> 45824.84 | E39: {=_FV(A39,"Price")} -> 30.54 | F39: {=_FV(A39,"Change (%)",TRUE)} -> -0.007475 | G39: {=_FV(A39,"Change")} -> -0.23 | H39: {=_FV(A39,"Open")} -> 30.77 | I39: {=_FV(A39,"Low")} -> 30.3 | J39: {=_FV(A39,"High")} -> 30.81 | K39: {=_FV(A39,"Previous close",TRUE)} -> 30.77 | M39: {=_FV(A39,"52 week low",TRUE)} -> 26.645 | N39: {=_FV(A39,"52 week high",TRUE)} -> 33.4 | O39: {=_FV(A39,"Volume")} -> 24878 | P39: {=_FV(A39,"Volume average",TRUE)} -> 40063 | Q39: Energy Limited Partnership | S39: JPMorgan Chase & Co | T39: {=_FV(A39,"Expense ratio",TRUE)} -> #VALUE! | U39: {=_FV(A39,"Market cap",TRUE)} -> 736321100000 | V39: 724508288 | W39: 724508288 | X39: 8.83% | Y39: 2024-01-25 | Z39: 30.45 | AB39: 0.0625 | AC39: 56019 | AE39: 3.8842622 | AF39: 14.656205 | AI39: 56019 | AJ39: 1705778.6 | AL39: 33.4 | AM39: 26.645 | AN39: Medium | AO39: {=_FV(A39,"Currency")} -> USD | AP39: {=_FV(A39,"Exchange")} -> NYSE Arca | AQ39: {=_FV(A39,"Exchange abbreviation",TRUE)} -> ARCX | AR39: {=_FV(A39,"Instrument type",TRUE)} -> Stock
A40: #VALUE! | B40: SMHB | C40: NO Name | D40: {=_FV(A40,"Last trade time",TRUE)} -> 45824.934 | E40: {=_FV(A40,"Price")} -> 4.43 | F40: {=_FV(A40,"Change (%)",TRUE)} -> 0.026413 | G40: {=_FV(A40,"Change")} -> 0.114 | H40: {=_FV(A40,"Open")} -> 4.4004 | I40: {=_FV(A40,"Low")} -> 4.38 | J40: {=_FV(A40,"High")} -> 4.4432 | K40: {=_FV(A40,"Previous close",TRUE)} -> 4.316 | M40: {=_FV(A40,"52 week low",TRUE)} -> 3.165 | N40: {=_FV(A40,"52 week high",TRUE)} -> 6.66 | O40: {=_FV(A40,"Volume")} -> 16213 | P40: {=_FV(A40,"Volume average",TRUE)} -> 31655 | Q40: Other | T40: {=_FV(A40,"Expense ratio",TRUE)} -> #VALUE! | U40: {=_FV(A40,"Market cap",TRUE)} -> 76546930000 | AC40: 34677 | AN40: Unknown | AO40: {=_FV(A40,"Currency")} -> USD | AP40: {=_FV(A40,"Exchange")} -> NYSE Arca | AQ40: {=_FV(A40,"Exchange abbreviation",TRUE)} -> ARCX | AR40: {=_FV(A40,"Instrument type",TRUE)} -> Stock
A41: #VALUE! | B41: IWML | C41: ETRACS 2x Leveraged US Size Factor TR ETN | D41: {=_FV(A41,"Last trade time",TRUE)} -> 45824.84 | E41: {=_FV(A41,"Price")} -> 17.7815 | F41: {=_FV(A41,"Change (%)",TRUE)} -> 0.021344 | G41: {=_FV(A41,"Change")} -> 0.3716 | H41: {=_FV(A41,"Open")} -> 17.7815 | I41: {=_FV(A41,"Low")} -> 17.7815 | J41: {=_FV(A41,"High")} -> 17.7815 | K41: {=_FV(A41,"Previous close",TRUE)} -> 17.4099 | M41: {=_FV(A41,"52 week low",TRUE)} -> 12.0871 | N41: {=_FV(A41,"52 week high",TRUE)} -> 27 | O41: {=_FV(A41,"Volume")} -> 152 | P41: {=_FV(A41,"Volume average",TRUE)} -> 269 | Q41: Alternative/Volatility | T41: {=_FV(A41,"Expense ratio",TRUE)} -> #VALUE! | U41: {=_FV(A41,"Market cap",TRUE)} -> 76546930000 | AC41: 297 | AN41: Unknown | AO41: {=_FV(A41,"Currency")} -> USD | AP41: {=_FV(A41,"Exchange")} -> NYSE Arca | AQ41: {=_FV(A41,"Exchange abbreviation",TRUE)} -> ARCX | AR41: {=_FV(A41,"Instrument type",TRUE)} -> Stock
A42: #VALUE! | B42: CEFD | C42: ETRACS Monthly Pay 1.5X Leveraged Closed-End Fund Index ETN | D42: {=_FV(A42,"Last trade time",TRUE)} -> 45824.84 | E42: {=_FV(A42,"Price")} -> 18.7899 | F42: {=_FV(A42,"Change (%)",TRUE)} -> 0.003187 | G42: {=_FV(A42,"Change")} -> 0.0597 | H42: {=_FV(A42,"Open")} -> 18.8495 | I42: {=_FV(A42,"Low")} -> 18.7899 | J42: {=_FV(A42,"High")} -> 18.8495 | K42: {=_FV(A42,"Previous close",TRUE)} -> 18.7302 | M42: {=_FV(A42,"52 week low",TRUE)} -> 14.935 | N42: {=_FV(A42,"52 week high",TRUE)} -> 21.2 | O42: {=_FV(A42,"Volume")} -> 848 | P42: {=_FV(A42,"Volume average",TRUE)} -> 1299 | Q42: Trading--Miscellaneous | S42: UBS | T42: {=_FV(A42,"Expense ratio",TRUE)} -> #VALUE! | U42: {=_FV(A42,"Market cap",TRUE)} -> 76546930000 | V42: 9342400 | W42: 9342400 | X42: -3.34% | Y42: 2020-06-01 | Z42: 18.8914 | AB42: 0.1559 | AC42: 2098 | AE42: 2.8923091 | AF42: 12.429708 | AI42: 2098 | AJ42: 39653.459 | AL42: 21.2 | AM42: 14.935 | AN42: Low | AO42: {=_FV(A42,"Currency")} -> USD | AP42: {=_FV(A42,"Exchange")} -> NYSE Arca | AQ42: {=_FV(A42,"Exchange abbreviation",TRUE)} -> ARCX | AR42: {=_FV(A42,"Instrument type",TRUE)} -> Stock
A43: #VALUE! | B43: FNGS | C43: MicroSectors FANG ETNs due January 8 2038 | D43: {=_FV(A43,"Last trade time",TRUE)} -> 45824.905 | E43: {=_FV(A43,"Price")} -> 61.73 | F43: {=_FV(A43,"Change (%)",TRUE)} -> 0.011636 | G43: {=_FV(A43,"Change")} -> 0.71 | H43: {=_FV(A43,"Open")} -> 61.67 | I43: {=_FV(A43,"Low")} -> 61.5101 | J43: {=_FV(A43,"High")} -> 62.2 | K43: {=_FV(A43,"Previous close",TRUE)} -> 61.02 | M43: {=_FV(A43,"52 week low",TRUE)} -> 41.62 | N43: {=_FV(A43,"52 week high",TRUE)} -> 62.26 | O43: {=_FV(A43,"Volume")} -> 104554 | P43: {=_FV(A43,"Volume average",TRUE)} -> 207449 | Q43: Other | T43: {=_FV(A43,"Expense ratio",TRUE)} -> #VALUE! | U43: {=_FV(A43,"Market cap",TRUE)} -> 104909700000 | AC43: 208420 | AN43: Unknown | AO43: {=_FV(A43,"Currency")} -> USD | AP43: {=_FV(A43,"Exchange")} -> NYSE Arca | AQ43: {=_FV(A43,"Exchange abbreviation",TRUE)} -> ARCX | AR43: {=_FV(A43,"Instrument type",TRUE)} -> Stock
A44: #VALUE! | B44: DBC | C44: Invesco DB Commodity Index Tracking Fund | D44: {=_FV(A44,"Last trade time",TRUE)} -> 45824.337 | E44: {=_FV(A44,"Price")} -> 30750 | F44: {=_FV(A44,"Change (%)",TRUE)} -> 0.01318 | G44: {=_FV(A44,"Change")} -> 400 | H44: {=_FV(A44,"Open")} -> 30300 | I44: {=_FV(A44,"Low")} -> 30200 | J44: {=_FV(A44,"High")} -> 31000 | K44: {=_FV(A44,"Previous close",TRUE)} -> 30350 | M44: {=_FV(A44,"52 week low",TRUE)} -> 21950 | N44: {=_FV(A44,"52 week high",TRUE)} -> 32304 | O44: {=_FV(A44,"Volume")} -> 8681100 | P44: {=_FV(A44,"Volume average",TRUE)} -> 11361090 | Q44: Commodities | R44: Commodities - Diversified | T44: {=_FV(A44,"Expense ratio",TRUE)} -> #VALUE! | U44: {=_FV(A44,"Market cap",TRUE)} -> 10157210000000 | AC44: 651461 | AN44: Unknown | AO44: {=_FV(A44,"Currency")} -> VND | AP44: {=_FV(A44,"Exchange")} -> Hochiminh Stock Exchange | AQ44: {=_FV(A44,"Exchange abbreviation",TRUE)} -> XSTC | AR44: {=_FV(A44,"Instrument type",TRUE)} -> Stock
A45: #VALUE! | B45: MVRL | C45: ETRACS Monthly Pay 1.5X Leveraged Mortgage REIT ETN | D45: {=_FV(A45,"Last trade time",TRUE)} -> 45824.84 | E45: {=_FV(A45,"Price")} -> 14.3513 | F45: {=_FV(A45,"Change (%)",TRUE)} -> -0.00151 | G45: {=_FV(A45,"Change")} -> -0.0217 | H45: {=_FV(A45,"Open")} -> 13.34 | I45: {=_FV(A45,"Low")} -> 13.34 | J45: {=_FV(A45,"High")} -> 14.46 | K45: {=_FV(A45,"Previous close",TRUE)} -> 14.373 | M45: {=_FV(A45,"52 week low",TRUE)} -> 11.78 | N45: {=_FV(A45,"52 week high",TRUE)} -> 19.21 | O45: {=_FV(A45,"Volume")} -> 4286 | P45: {=_FV(A45,"Volume average",TRUE)} -> 3629 | Q45: Trading--Leveraged Equity | S45: UBS | T45: {=_FV(A45,"Expense ratio",TRUE)} -> #VALUE! | U45: {=_FV(A45,"Market cap",TRUE)} -> 76546930000 | V45: 20967300 | W45: 20967300 | Y45: 2020-06-01 | Z45: 14.3296 | AB45: 0.2141 | AC45: 7828 | AE45: -0.17541435 | AF45: 3.0344383 | AI45: 7828 | AJ45: 112127.49 | AL45: 19.21 | AM45: 11.78 | AN45: Low | AO45: {=_FV(A45,"Currency")} -> USD | AP45: {=_FV(A45,"Exchange")} -> NYSE Arca | AQ45: {=_FV(A45,"Exchange abbreviation",TRUE)} -> ARCX | AR45: {=_FV(A45,"Instrument type",TRUE)} -> Stock
A46: #VALUE! | B46: FNGO | C46: NO Name | D46: {=_FV(A46,"Last trade time",TRUE)} -> 45824.87 | E46: {=_FV(A46,"Price")} -> 100.1352 | F46: {=_FV(A46,"Change (%)",TRUE)} -> 0.019499 | G46: {=_FV(A46,"Change")} -> 1.9152 | H46: {=_FV(A46,"Open")} -> 99.17 | I46: {=_FV(A46,"Low")} -> 99.13 | J46: {=_FV(A46,"High")} -> 100.85 | K46: {=_FV(A46,"Previous close",TRUE)} -> 98.22 | M46: {=_FV(A46,"52 week low",TRUE)} -> 48.67 | N46: {=_FV(A46,"52 week high",TRUE)} -> 106.25 | O46: {=_FV(A46,"Volume")} -> 22709 | P46: {=_FV(A46,"Volume average",TRUE)} -> 32945 | Q46: Other | T46: {=_FV(A46,"Expense ratio",TRUE)} -> #VALUE! | U46: {=_FV(A46,"Market cap",TRUE)} -> 104909700000 | AC46: 31313 | AN46: Unknown | AO46: {=_FV(A46,"Currency")} -> USD | AP46: {=_FV(A46,"Exchange")} -> NYSE Arca | AQ46: {=_FV(A46,"Exchange abbreviation",TRUE)} -> ARCX | AR46: {=_FV(A46,"Instrument type",TRUE)} -> Stock
A47: #VALUE! | B47: GBTC | C47: Grayscale Bitcoin Trust (BTC) Common Units of fractional undiv | D47: {=_FV(A47,"Last trade time",TRUE)} -> 45824.937 | E47: {=_FV(A47,"Price")} -> 85.655 | F47: {=_FV(A47,"Change (%)",TRUE)} -> 0.034106 | G47: {=_FV(A47,"Change")} -> 2.825 | H47: {=_FV(A47,"Open")} -> 84.02 | I47: {=_FV(A47,"Low")} -> 83.9 | J47: {=_FV(A47,"High")} -> 85.85 | K47: {=_FV(A47,"Previous close",TRUE)} -> 82.83 | M47: {=_FV(A47,"52 week low",TRUE)} -> 39.56 | N47: {=_FV(A47,"52 week high",TRUE)} -> 88.355 | O47: {=_FV(A47,"Volume")} -> 1652106 | P47: {=_FV(A47,"Volume average",TRUE)} -> 2102879 | Q47: Digital Assets | S47: Grayscale | T47: {=_FV(A47,"Expense ratio",TRUE)} -> #VALUE! | U47: {=_FV(A47,"Market cap",TRUE)} -> #VALUE! | V47: 19427721216 | W47: 19427721216 | Y47: 2013-09-24 | Z47: 82.21 | AB47: 0 | AC47: 2027055 | AE47: 10.957129 | AF47: 36.787477 | AH47: 692369984 | AI47: 2027055 | AJ47: 1.6668473e+08 | AL47: 88.355 | AM47: 39.56 | AN47: High | AO47: {=_FV(A47,"Currency")} -> USD | AP47: {=_FV(A47,"Exchange")} -> NYSE Arca | AQ47: {=_FV(A47,"Exchange abbreviation",TRUE)} -> ARCX | AR47: {=_FV(A47,"Instrument type",TRUE)} -> Stock
A48: #VALUE! | B48: PFFL | C48: NO Name | D48: {=_FV(A48,"Last trade time",TRUE)} -> 45824.84 | E48: {=_FV(A48,"Price")} -> 8.1203 | F48: {=_FV(A48,"Change (%)",TRUE)} -> 0.00127 | G48: {=_FV(A48,"Change")} -> 0.0103 | H48: {=_FV(A48,"Open")} -> 8.13 | I48: {=_FV(A48,"Low")} -> 8.1203 | J48: {=_FV(A48,"High")} -> 8.19 | K48: {=_FV(A48,"Previous close",TRUE)} -> 8.11 | M48: {=_FV(A48,"52 week low",TRUE)} -> 7.625 | N48: {=_FV(A48,"52 week high",TRUE)} -> 11.65 | O48: {=_FV(A48,"Volume")} -> 951 | P48: {=_FV(A48,"Volume average",TRUE)} -> 2227 | Q48: Other | T48: {=_FV(A48,"Expense ratio",TRUE)} -> #VALUE! | U48: {=_FV(A48,"Market cap",TRUE)} -> 76546930000 | AC48: 1864 | AN48: Unknown | AO48: {=_FV(A48,"Currency")} -> USD | AP48: {=_FV(A48,"Exchange")} -> NYSE Arca | AQ48: {=_FV(A48,"Exchange abbreviation",TRUE)} -> ARCX | AR48: {=_FV(A48,"Instrument type",TRUE)} -> Stock
A49: #VALUE! | B49: UCIB | C49: UBS ETRACS Bloomberg Constant Maturity Commodity CMCI Total Return ETN Seri | D49: {=_FV(A49,"Last trade time",TRUE)} -> 45824.84 | E49: {=_FV(A49,"Price")} -> 27.0243 | F49: {=_FV(A49,"Change (%)",TRUE)} -> 0.003703 | G49: {=_FV(A49,"Change")} -> 0.0997 | H49: {=_FV(A49,"Open")} -> 26.959 | I49: {=_FV(A49,"Low")} -> 26.94 | J49: {=_FV(A49,"High")} -> 27.1299 | K49: {=_FV(A49,"Previous close",TRUE)} -> 26.9246 | M49: {=_FV(A49,"52 week low",TRUE)} -> 22 | N49: {=_FV(A49,"52 week high",TRUE)} -> 29.18 | O49: {=_FV(A49,"Volume")} -> 1311 | P49: {=_FV(A49,"Volume average",TRUE)} -> 1288 | Q49: Commodities Broad Basket | R49: Commodities - Diversified | S49: UBS | T49: {=_FV(A49,"Expense ratio",TRUE)} -> #VALUE! | U49: {=_FV(A49,"Market cap",TRUE)} -> 76546930000 | V49: 24289600 | W49: 24289600 | Y49: 2015-10-08 | Z49: 26.3355 | AB49: 0 | AC49: 958 | AE49: 1.7501872 | AF49: 0.4987953 | AI49: 958 | AJ49: 25209.291 | AL49: 29.18 | AM49: 22 | AN49: Low | AO49: {=_FV(A49,"Currency")} -> USD | AP49: {=_FV(A49,"Exchange")} -> NYSE Arca | AQ49: {=_FV(A49,"Exchange abbreviation",TRUE)} -> ARCX | AR49: {=_FV(A49,"Instrument type",TRUE)} -> Stock
A50: #VALUE! | B50: DZZ | C50: DB Gold Double Short ETN Exp 15 Feb 2038 | D50: {=_FV(A50,"Last trade time",TRUE)} -> 45824.84 | E50: {=_FV(A50,"Price")} -> 1.825 | F50: {=_FV(A50,"Change (%)",TRUE)} -> 0.013889 | G50: {=_FV(A50,"Change")} -> 0.025 | H50: {=_FV(A50,"Open")} -> 1.8 | I50: {=_FV(A50,"Low")} -> 1.8 | J50: {=_FV(A50,"High")} -> 1.85 | K50: {=_FV(A50,"Previous close",TRUE)} -> 1.8 | M50: {=_FV(A50,"52 week low",TRUE)} -> 1.35 | N50: {=_FV(A50,"52 week high",TRUE)} -> 2.19 | O50: {=_FV(A50,"Volume")} -> 7954 | P50: {=_FV(A50,"Volume average",TRUE)} -> 7826 | Q50: Trading--Inverse Commodities | R50: Commodities - Gold - Short | S50: Deutsche Bank AG | T50: {=_FV(A50,"Expense ratio",TRUE)} -> #VALUE! | U50: {=_FV(A50,"Market cap",TRUE)} -> #VALUE! | V50: 1847365 | W50: 1847365 | Y50: 2008-02-26 | Z50: 0.99085 | AB50: 0 | AC50: 17617 | AE50: 20.886071 | AF50: -2.0512862 | AI50: 17617 | AJ50: 33648.47 | AL50: 2.19 | AM50: 1.35 | AN50: Low | AO50: {=_FV(A50,"Currency")} -> USD | AP50: {=_FV(A50,"Exchange")} -> NYSE Arca | AQ50: {=_FV(A50,"Exchange abbreviation",TRUE)} -> ARCX | AR50: {=_FV(A50,"Instrument type",TRUE)} -> Stock
A51: #VALUE! | B51: FNGB | C51: Bank Of Montreal MicroSectors FANG+ 3X Leveraged ETNs | D51: {=_FV(A51,"Last trade time",TRUE)} -> 45824.939 | E51: {=_FV(A51,"Price")} -> 21.68 | F51: {=_FV(A51,"Change (%)",TRUE)} -> 0.038812 | G51: {=_FV(A51,"Change")} -> 0.81 | H51: {=_FV(A51,"Open")} -> 21.27 | I51: {=_FV(A51,"Low")} -> 21.23 | J51: {=_FV(A51,"High")} -> 21.91 | K51: {=_FV(A51,"Previous close",TRUE)} -> 20.87 | M51: {=_FV(A51,"52 week low",TRUE)} -> 7.9502 | N51: {=_FV(A51,"52 week high",TRUE)} -> 24.52 | O51: {=_FV(A51,"Volume")} -> 5040029 | P51: {=_FV(A51,"Volume average",TRUE)} -> 7077197 | Q51: Financial | T51: {=_FV(A51,"Expense ratio",TRUE)} -> #VALUE! | U51: {=_FV(A51,"Market cap",TRUE)} -> 104909700000 | AC51: 7014153 | AN51: Unknown | AO51: {=_FV(A51,"Currency")} -> USD | AP51: {=_FV(A51,"Exchange")} -> NYSE Arca | AQ51: {=_FV(A51,"Exchange abbreviation",TRUE)} -> ARCX | AR51: {=_FV(A51,"Instrument type",TRUE)} -> Stock
A52: #VALUE! | B52: BULZ | C52: MicroSectors FANG & Innovation 3X Leveraged ETN | D52: {=_FV(A52,"Last trade time",TRUE)} -> 45824.94 | E52: {=_FV(A52,"Price")} -> 157.1 | F52: {=_FV(A52,"Change (%)",TRUE)} -> 0.071404 | G52: {=_FV(A52,"Change")} -> 10.47 | H52: {=_FV(A52,"Open")} -> 151.49 | I52: {=_FV(A52,"Low")} -> 151.29 | J52: {=_FV(A52,"High")} -> 158.035 | K52: {=_FV(A52,"Previous close",TRUE)} -> 146.63 | M52: {=_FV(A52,"52 week low",TRUE)} -> 57 | N52: {=_FV(A52,"52 week high",TRUE)} -> 206.23 | O52: {=_FV(A52,"Volume")} -> 301974 | P52: {=_FV(A52,"Volume average",TRUE)} -> 254477 | Q52: Trading--Leveraged Equity | S52: BMO Capital Markets | T52: {=_FV(A52,"Expense ratio",TRUE)} -> #VALUE! | U52: {=_FV(A52,"Market cap",TRUE)} -> 104909700000 | V52: 1165577088 | W52: 1165577088 | X52: 7.21% | Y52: 2021-08-16 | Z52: 145.93102 | AA52: 50.063004 | AB52: 0 | AC52: 269671 | AE52: -6.8676761 | AF52: 10.406703 | AI52: 269671 | AJ52: 39312638 | AL52: 206.23 | AM52: 57 | AN52: High | AO52: {=_FV(A52,"Currency")} -> USD | AP52: {=_FV(A52,"Exchange")} -> NYSE Arca | AQ52: {=_FV(A52,"Exchange abbreviation",TRUE)} -> ARCX | AR52: {=_FV(A52,"Instrument type",TRUE)} -> Stock
A53: #VALUE! | B53: SPYU | C53: Bank Of Montreal MAX S&P 500 4X Leveraged ETNs due October 30 | D53: {=_FV(A53,"Last trade time",TRUE)} -> 45824.939 | E53: {=_FV(A53,"Price")} -> 39.01 | F53: {=_FV(A53,"Change (%)",TRUE)} -> 0.032011 | G53: {=_FV(A53,"Change")} -> 1.21 | H53: {=_FV(A53,"Open")} -> 38.63 | I53: {=_FV(A53,"Low")} -> 38.615 | J53: {=_FV(A53,"High")} -> 39.65 | K53: {=_FV(A53,"Previous close",TRUE)} -> 37.8 | M53: {=_FV(A53,"52 week low",TRUE)} -> 18.15 | N53: {=_FV(A53,"52 week high",TRUE)} -> 55.3935 | O53: {=_FV(A53,"Volume")} -> 943364 | P53: {=_FV(A53,"Volume average",TRUE)} -> 1569043 | Q53: Trading--Leveraged Equity | S53: Bank of Montreal | T53: {=_FV(A53,"Expense ratio",TRUE)} -> #VALUE! | U53: {=_FV(A53,"Market cap",TRUE)} -> 104909700000 | V53: 292380832 | W53: 292380832 | Y53: 2023-12-03 | Z53: 38.59127 | AB53: 0 | AC53: 1954755 | AE53: -16.374648 | AF53: -2.4722491 | AI53: 1954755 | AJ53: 75316710 | AL53: 55.394 | AM53: 18.15 | AN53: High | AO53: {=_FV(A53,"Currency")} -> USD | AP53: {=_FV(A53,"Exchange")} -> NYSE Arca | AQ53: {=_FV(A53,"Exchange abbreviation",TRUE)} -> ARCX | AR53: {=_FV(A53,"Instrument type",TRUE)} -> Stock
A54: #VALUE! | B54: HDLB | C54: ETRACS Monthly Pay 2xLeveraged US High Dividend Low Volatility | D54: {=_FV(A54,"Last trade time",TRUE)} -> 45824.84 | E54: {=_FV(A54,"Price")} -> 15.0231 | F54: {=_FV(A54,"Change (%)",TRUE)} -> 0.001834 | G54: {=_FV(A54,"Change")} -> 0.0275 | H54: {=_FV(A54,"Open")} -> 15.17 | I54: {=_FV(A54,"Low")} -> 15.0231 | J54: {=_FV(A54,"High")} -> 15.17 | K54: {=_FV(A54,"Previous close",TRUE)} -> 14.9956 | M54: {=_FV(A54,"52 week low",TRUE)} -> 11.31 | N54: {=_FV(A54,"52 week high",TRUE)} -> 17.24 | O54: {=_FV(A54,"Volume")} -> 346 | P54: {=_FV(A54,"Volume average",TRUE)} -> 1466 | Q54: Dividend/Income | T54: {=_FV(A54,"Expense ratio",TRUE)} -> #VALUE! | U54: {=_FV(A54,"Market cap",TRUE)} -> 76546930000 | AC54: 1461 | AN54: Unknown | AO54: {=_FV(A54,"Currency")} -> USD | AP54: {=_FV(A54,"Exchange")} -> NYSE Arca | AQ54: {=_FV(A54,"Exchange abbreviation",TRUE)} -> ARCX | AR54: {=_FV(A54,"Instrument type",TRUE)} -> Stock
A55: #VALUE! | B55: DULL | C55: Bank Of Montreal MicroSectors Gold -3X Inverse Leveraged ETNs | D55: {=_FV(A55,"Last trade time",TRUE)} -> 45824.909 | E55: {=_FV(A55,"Price")} -> 3.74 | F55: {=_FV(A55,"Change (%)",TRUE)} -> 0.036011 | G55: {=_FV(A55,"Change")} -> 0.13 | H55: {=_FV(A55,"Open")} -> 3.66 | I55: {=_FV(A55,"Low")} -> 3.655 | J55: {=_FV(A55,"High")} -> 3.7586 | K55: {=_FV(A55,"Previous close",TRUE)} -> 3.61 | M55: {=_FV(A55,"52 week low",TRUE)} -> 3.55 | N55: {=_FV(A55,"52 week high",TRUE)} -> 13.05 | O55: {=_FV(A55,"Volume")} -> 234344 | P55: {=_FV(A55,"Volume average",TRUE)} -> 173927 | Q55: Trading--Inverse Commodities | R55: Commodities - Gold | S55: BMO Capital Markets | T55: {=_FV(A55,"Expense ratio",TRUE)} -> #VALUE! | U55: {=_FV(A55,"Market cap",TRUE)} -> 104909700000 | V55: 14318466 | W55: 14318466 | Y55: 2023-02-20 | Z55: 4.00897 | AB55: 0 | AC55: 208474 | AE55: -52.32362 | AF55: -66.719893 | AI55: 208474 | AJ55: 833896 | AL55: 13.05 | AM55: 3.705 | AN55: Low | AO55: {=_FV(A55,"Currency")} -> USD | AP55: {=_FV(A55,"Exchange")} -> NYSE Arca | AQ55: {=_FV(A55,"Exchange abbreviation",TRUE)} -> ARCX | AR55: {=_FV(A55,"Instrument type",TRUE)} -> Stock
A56: #VALUE! | B56: JETU | C56: Bank Of Montreal MAX Airlines 3X Leveraged ETNs | D56: {=_FV(A56,"Last trade time",TRUE)} -> 45824.84 | E56: {=_FV(A56,"Price")} -> 19.4217 | F56: {=_FV(A56,"Change (%)",TRUE)} -> 0.057827 | G56: {=_FV(A56,"Change")} -> 1.0617 | H56: {=_FV(A56,"Open")} -> 19 | I56: {=_FV(A56,"Low")} -> 19 | J56: {=_FV(A56,"High")} -> 19.5311 | K56: {=_FV(A56,"Previous close",TRUE)} -> 18.36 | M56: {=_FV(A56,"52 week low",TRUE)} -> 10.45 | N56: {=_FV(A56,"52 week high",TRUE)} -> 35.8 | O56: {=_FV(A56,"Volume")} -> 1549 | P56: {=_FV(A56,"Volume average",TRUE)} -> 2347 | Q56: Trading--Leveraged Equity | S56: Bank of Montreal | T56: {=_FV(A56,"Expense ratio",TRUE)} -> #VALUE! | U56: {=_FV(A56,"Market cap",TRUE)} -> 104909700000 | V56: 3203732 | W56: 3203732 | Y56: 2023-06-19 | Z56: 21.35608 | AA56: 16.744171 | AB56: 0 | AC56: 4698 | AE56: -21.588549 | AI56: 4698 | AJ56: 100462.03 | AL56: 35.8 | AM56: 10.45 | AN56: Low | AO56: {=_FV(A56,"Currency")} -> USD | AP56: {=_FV(A56,"Exchange")} -> NYSE Arca | AQ56: {=_FV(A56,"Exchange abbreviation",TRUE)} -> ARCX | AR56: {=_FV(A56,"Instrument type",TRUE)} -> Stock
A57: #VALUE! | B57: DGZ | C57: DB Gold Short ETN Exp 15 Feb 2038 | D57: {=_FV(A57,"Last trade time",TRUE)} -> 45824.84 | E57: {=_FV(A57,"Price")} -> 6.725 | F57: {=_FV(A57,"Change (%)",TRUE)} -> -0.00298 | G57: {=_FV(A57,"Change")} -> -0.0201 | H57: {=_FV(A57,"Open")} -> 6.78 | I57: {=_FV(A57,"Low")} -> 6.65 | J57: {=_FV(A57,"High")} -> 6.8 | K57: {=_FV(A57,"Previous close",TRUE)} -> 6.7451 | M57: {=_FV(A57,"52 week low",TRUE)} -> 6.52 | N57: {=_FV(A57,"52 week high",TRUE)} -> 9.2445 | O57: {=_FV(A57,"Volume")} -> 2769 | P57: {=_FV(A57,"Volume average",TRUE)} -> 3814 | Q57: Trading--Inverse Commodities | R57: Commodities - Gold - Short | S57: Deutsche Bank AG | T57: {=_FV(A57,"Expense ratio",TRUE)} -> #VALUE! | U57: {=_FV(A57,"Market cap",TRUE)} -> #VALUE! | V57: 2169340 | W57: 2169340 | Y57: 2008-02-26 | Z57: 6.75834 | AB57: 0 | AC57: 6784 | AE57: -15.563726 | AF57: -22.930647 | AI57: 6784 | AJ57: 47235.635 | AL57: 9.24 | AM57: 6.52 | AN57: Low | AO57: {=_FV(A57,"Currency")} -> USD | AP57: {=_FV(A57,"Exchange")} -> NYSE Arca | AQ57: {=_FV(A57,"Exchange abbreviation",TRUE)} -> ARCX | AR57: {=_FV(A57,"Instrument type",TRUE)} -> Stock
A58: #VALUE! | B58: OILD | C58: MicroSectors Oil & Gas Exp. & Prod. -3x Inverse Leveraged ETN | D58: {=_FV(A58,"Last trade time",TRUE)} -> 45824.924 | E58: {=_FV(A58,"Price")} -> 12.22 | F58: {=_FV(A58,"Change (%)",TRUE)} -> 0.013267 | G58: {=_FV(A58,"Change")} -> 0.16 | H58: {=_FV(A58,"Open")} -> 12.17 | I58: {=_FV(A58,"Low")} -> 11.83 | J58: {=_FV(A58,"High")} -> 12.48 | K58: {=_FV(A58,"Previous close",TRUE)} -> 12.06 | M58: {=_FV(A58,"52 week low",TRUE)} -> 11.83 | N58: {=_FV(A58,"52 week high",TRUE)} -> 24.01 | O58: {=_FV(A58,"Volume")} -> 482666 | P58: {=_FV(A58,"Volume average",TRUE)} -> 240588 | Q58: Trading--Inverse Equity | R58: Equities - - Short | S58: BMO Capital Markets | T58: {=_FV(A58,"Expense ratio",TRUE)} -> #VALUE! | U58: {=_FV(A58,"Market cap",TRUE)} -> 104909700000 | V58: 15587461 | W58: 15587461 | Y58: 2021-11-07 | Z58: 14.34972 | AA58: 13.181272 | AB58: 0 | AC58: 233907 | AE58: -14.896143 | AF58: -9.8680057 | AI58: 233907 | AJ58: 3363582.7 | AL58: 24.01 | AM58: 12.259 | AN58: Medium | AO58: {=_FV(A58,"Currency")} -> USD | AP58: {=_FV(A58,"Exchange")} -> NYSE Arca | AQ58: {=_FV(A58,"Exchange abbreviation",TRUE)} -> ARCX | AR58: {=_FV(A58,"Instrument type",TRUE)} -> Stock
A59: #VALUE! | B59: WTID | C59: Bank Of Montreal MicroSectors Energy 3X Inverse Leveraged ETNs | D59: {=_FV(A59,"Last trade time",TRUE)} -> 45824.84 | E59: {=_FV(A59,"Price")} -> 13.4409 | F59: {=_FV(A59,"Change (%)",TRUE)} -> -0.006585 | G59: {=_FV(A59,"Change")} -> -0.0891 | H59: {=_FV(A59,"Open")} -> 13.6 | I59: {=_FV(A59,"Low")} -> 13.16 | J59: {=_FV(A59,"High")} -> 13.7 | K59: {=_FV(A59,"Previous close",TRUE)} -> 13.53 | M59: {=_FV(A59,"52 week low",TRUE)} -> 13.16 | N59: {=_FV(A59,"52 week high",TRUE)} -> 29.43 | O59: {=_FV(A59,"Volume")} -> 14028 | P59: {=_FV(A59,"Volume average",TRUE)} -> 4384 | Q59: Trading--Inverse Equity | R59: Equities - - Short | S59: BMO Capital Markets | T59: {=_FV(A59,"Expense ratio",TRUE)} -> #VALUE! | U59: {=_FV(A59,"Market cap",TRUE)} -> 104909700000 | V59: 2812744 | W59: 2812744 | Y59: 2023-02-15 | Z59: 16.27596 | AA59: 13.014131 | AB59: 0 | AC59: 5030 | AE59: -20.76729 | AF59: -4.4252531 | AI59: 5030 | AJ59: 81795.345 | AL59: 29.43 | AM59: 14.67 | AN59: Low | AO59: {=_FV(A59,"Currency")} -> USD | AP59: {=_FV(A59,"Exchange")} -> NYSE Arca | AQ59: {=_FV(A59,"Exchange abbreviation",TRUE)} -> ARCX | AR59: {=_FV(A59,"Instrument type",TRUE)} -> Stock
A60: #VALUE! | B60: GDXD | C60: MicroSectors Gold Miners -3X Inverse Leveraged ETNs | D60: {=_FV(A60,"Last trade time",TRUE)} -> 45824.937 | E60: {=_FV(A60,"Price")} -> 2.875 | F60: {=_FV(A60,"Change (%)",TRUE)} -> 0.04927 | G60: {=_FV(A60,"Change")} -> 0.135 | H60: {=_FV(A60,"Open")} -> 2.83 | I60: {=_FV(A60,"Low")} -> 2.77 | J60: {=_FV(A60,"High")} -> 2.89 | K60: {=_FV(A60,"Previous close",TRUE)} -> 2.74 | M60: {=_FV(A60,"52 week low",TRUE)} -> 2.7 | N60: {=_FV(A60,"52 week high",TRUE)} -> 25.78 | O60: {=_FV(A60,"Volume")} -> 9700552 | P60: {=_FV(A60,"Volume average",TRUE)} -> 8999609 | Q60: Trading--Inverse Commodities | R60: Commodities - Gold | S60: BMO Capital Markets | T60: {=_FV(A60,"Expense ratio",TRUE)} -> #VALUE! | U60: {=_FV(A60,"Market cap",TRUE)} -> 104909700000 | V60: 92357168 | W60: 92357168 | Y60: 2020-12-01 | Z60: 3.16386 | AA60: 16.56368 | AB60: 0 | AC60: 8355414 | AE60: -79.328859 | AF60: -84.661355 | AI60: 8355414 | AJ60: 26486662 | AL60: 25.78 | AM60: 2.71 | AN60: High | AO60: {=_FV(A60,"Currency")} -> USD | AP60: {=_FV(A60,"Exchange")} -> NYSE Arca | AQ60: {=_FV(A60,"Exchange abbreviation",TRUE)} -> ARCX | AR60: {=_FV(A60,"Instrument type",TRUE)} -> Stock
A61: #VALUE! | B61: DAT | C61: ProShares Big Data Refiners ETF | D61: {=_FV(A61,"Last trade time",TRUE)} -> 45824.337 | E61: {=_FV(A61,"Price")} -> 7500 | F61: {=_FV(A61,"Change (%)",TRUE)} -> 0.053371 | G61: {=_FV(A61,"Change")} -> 380 | H61: {=_FV(A61,"Open")} -> 7120 | I61: {=_FV(A61,"Low")} -> 7120 | J61: {=_FV(A61,"High")} -> 7500 | K61: {=_FV(A61,"Previous close",TRUE)} -> 7120 | M61: {=_FV(A61,"52 week low",TRUE)} -> 6240 | N61: {=_FV(A61,"52 week high",TRUE)} -> 9182 | O61: {=_FV(A61,"Volume")} -> 600 | P61: {=_FV(A61,"Volume average",TRUE)} -> 1650 | Q61: Other | T61: {=_FV(A61,"Expense ratio",TRUE)} -> #VALUE! | U61: {=_FV(A61,"Market cap",TRUE)} -> 492905800000 | AC61: 1424 | AN61: Unknown | AO61: {=_FV(A61,"Currency")} -> VND | AP61: {=_FV(A61,"Exchange")} -> Hochiminh Stock Exchange | AQ61: {=_FV(A61,"Exchange abbreviation",TRUE)} -> XSTC | AR61: {=_FV(A61,"Instrument type",TRUE)} -> Stock
A62: #VALUE! | B62: ETHE | C62: Grayscale Ethereum Trust (ETH) Common units of fractional undi | D62: {=_FV(A62,"Last trade time",TRUE)} -> 45824.939 | E62: {=_FV(A62,"Price")} -> 22.07 | F62: {=_FV(A62,"Change (%)",TRUE)} -> 0.052958 | G62: {=_FV(A62,"Change")} -> 1.11 | H62: {=_FV(A62,"Open")} -> 21.65 | I62: {=_FV(A62,"Low")} -> 21.64 | J62: {=_FV(A62,"High")} -> 22.15 | K62: {=_FV(A62,"Previous close",TRUE)} -> 20.96 | M62: {=_FV(A62,"52 week low",TRUE)} -> 12.105 | N62: {=_FV(A62,"52 week high",TRUE)} -> 34.53 | O62: {=_FV(A62,"Volume")} -> 2862038 | P62: {=_FV(A62,"Volume average",TRUE)} -> 4388608 | Q62: Digital Assets | S62: Grayscale | T62: {=_FV(A62,"Expense ratio",TRUE)} -> #VALUE! | U62: {=_FV(A62,"Market cap",TRUE)} -> #VALUE! | V62: 2924731904 | W62: 2924731904 | Y62: 2017-12-13 | Z62: 20.62 | AB62: 0 | AC62: 4583903 | AE62: -25.968189 | AF62: -39.22793 | AI62: 4583903 | AJ62: 94474241 | AL62: 34.53 | AM62: 12.105 | AN62: High | AO62: {=_FV(A62,"Currency")} -> USD | AP62: {=_FV(A62,"Exchange")} -> NYSE Arca | AQ62: {=_FV(A62,"Exchange abbreviation",TRUE)} -> ARCX | AR62: {=_FV(A62,"Instrument type",TRUE)} -> ETF
A63: #VALUE! | B63: ETHW | C63: Bitwise Ethereum ETF Common shares of beneficial interest | D63: {=_FV(A63,"Last trade time",TRUE)} -> 45824.924 | E63: {=_FV(A63,"Price")} -> 19.1 | F63: {=_FV(A63,"Change (%)",TRUE)} -> 0.054084 | G63: {=_FV(A63,"Change")} -> 0.98 | H63: {=_FV(A63,"Open")} -> 18.75 | I63: {=_FV(A63,"Low")} -> 18.7201 | J63: {=_FV(A63,"High")} -> 19.16 | K63: {=_FV(A63,"Previous close",TRUE)} -> 18.12 | M63: {=_FV(A63,"52 week low",TRUE)} -> 10.42 | N63: {=_FV(A63,"52 week high",TRUE)} -> 29.52 | O63: {=_FV(A63,"Volume")} -> 854305 | P63: {=_FV(A63,"Volume average",TRUE)} -> 394851 | Q63: Digital Assets | S63: Bitwise Investments | T63: {=_FV(A63,"Expense ratio",TRUE)} -> #VALUE! | U63: {=_FV(A63,"Market cap",TRUE)} -> #VALUE! | V63: 249908048 | W63: 249908048 | Y63: 2024-07-21 | Z63: 17.883 | AC63: 348642 | AE63: -25.221952 | AI63: 348642 | AJ63: 6216286.9 | AL63: 29.52 | AM63: 10.42 | AN63: Medium | AO63: {=_FV(A63,"Currency")} -> USD | AP63: {=_FV(A63,"Exchange")} -> NYSE Arca | AQ63: {=_FV(A63,"Exchange abbreviation",TRUE)} -> ARCX | AR63: {=_FV(A63,"Instrument type",TRUE)} -> ETF
A64: #VALUE! | B64: NRGD | C64: Bank Of Montreal MicroSectors U.S. Big Oil -3 Inverse Levera | D64: {=_FV(A64,"Last trade time",TRUE)} -> 45824.84 | E64: {=_FV(A64,"Price")} -> 20.4028 | F64: {=_FV(A64,"Change (%)",TRUE)} -> 0.010325 | G64: {=_FV(A64,"Change")} -> 0.2085 | H64: {=_FV(A64,"Open")} -> 20.29 | I64: {=_FV(A64,"Low")} -> 19.98 | J64: {=_FV(A64,"High")} -> 20.91 | K64: {=_FV(A64,"Previous close",TRUE)} -> 20.1943 | M64: {=_FV(A64,"52 week low",TRUE)} -> 19.98 | N64: {=_FV(A64,"52 week high",TRUE)} -> 46.73 | O64: {=_FV(A64,"Volume")} -> 17612 | P64: {=_FV(A64,"Volume average",TRUE)} -> 1677 | Q64: Financial | T64: {=_FV(A64,"Expense ratio",TRUE)} -> #VALUE! | U64: {=_FV(A64,"Market cap",TRUE)} -> 104909700000 | Z64: 24.411 | AA64: 0.40142342 | AC64: 1858 | AE64: 2.2193324 | AI64: 1858 | AJ64: 46419.529 | AL64: 46.73 | AM64: 22.746 | AN64: Low | AO64: {=_FV(A64,"Currency")} -> USD | AP64: {=_FV(A64,"Exchange")} -> NYSE Arca | AQ64: {=_FV(A64,"Exchange abbreviation",TRUE)} -> ARCX | AR64: {=_FV(A64,"Instrument type",TRUE)} -> Stock
A65: #VALUE! | B65: CARU | C65: Bank Of Montreal MAX Auto Industry 3x Leveraged ETN | D65: {=_FV(A65,"Last trade time",TRUE)} -> 45824.84 | E65: {=_FV(A65,"Price")} -> 25.4917 | F65: {=_FV(A65,"Change (%)",TRUE)} -> 0.025175 | G65: {=_FV(A65,"Change")} -> 0.626 | H65: {=_FV(A65,"Open")} -> 25.78 | I65: {=_FV(A65,"Low")} -> 25.4917 | J65: {=_FV(A65,"High")} -> 25.78 | K65: {=_FV(A65,"Previous close",TRUE)} -> 24.8657 | M65: {=_FV(A65,"52 week low",TRUE)} -> 14.0099 | N65: {=_FV(A65,"52 week high",TRUE)} -> 35.49 | O65: {=_FV(A65,"Volume")} -> 397 | P65: {=_FV(A65,"Volume average",TRUE)} -> 919 | Q65: Trading--Leveraged Equity | S65: Bank of Montreal | T65: {=_FV(A65,"Expense ratio",TRUE)} -> #VALUE! | U65: {=_FV(A65,"Market cap",TRUE)} -> 104909700000 | V65: 4469601 | W65: 4469601 | X65: 39.27% | Y65: 2023-06-26 | Z65: 26.42956 | AA65: 14.367297 | AB65: 0 | AC65: 2376 | AE65: -1.0027334 | AI65: 2376 | AJ65: 62746.121 | AL65: 35.49 | AM65: 14.01 | AN65: Low | AO65: {=_FV(A65,"Currency")} -> USD | AP65: {=_FV(A65,"Exchange")} -> NYSE Arca | AQ65: {=_FV(A65,"Exchange abbreviation",TRUE)} -> ARCX | AR65: {=_FV(A65,"Instrument type",TRUE)} -> Stock
A66: #VALUE! | B66: BNKU | C66: Bank Of Montreal MicroSectors U.S. Big Banks 3 Leveraged ETN | D66: {=_FV(A66,"Last trade time",TRUE)} -> 45824.896 | E66: {=_FV(A66,"Price")} -> 18.06 | F66: {=_FV(A66,"Change (%)",TRUE)} -> 0.039125 | G66: {=_FV(A66,"Change")} -> 0.68 | H66: {=_FV(A66,"Open")} -> 17.73 | I66: {=_FV(A66,"Low")} -> 17.73 | J66: {=_FV(A66,"High")} -> 18.401 | K66: {=_FV(A66,"Previous close",TRUE)} -> 17.38 | M66: {=_FV(A66,"52 week low",TRUE)} -> 8.51 | N66: {=_FV(A66,"52 week high",TRUE)} -> 25.11 | O66: {=_FV(A66,"Volume")} -> 26555 | P66: {=_FV(A66,"Volume average",TRUE)} -> 15245 | Q66: Financial | T66: {=_FV(A66,"Expense ratio",TRUE)} -> #VALUE! | U66: {=_FV(A66,"Market cap",TRUE)} -> 104909700000 | X66: -20.11% | AC66: 14356 | AN66: Unknown | AO66: {=_FV(A66,"Currency")} -> USD | AP66: {=_FV(A66,"Exchange")} -> NYSE Arca | AQ66: {=_FV(A66,"Exchange abbreviation",TRUE)} -> ARCX | AR66: {=_FV(A66,"Instrument type",TRUE)} -> Stock
A67: #VALUE! | B67: FLYU | C67: Bank of Montreal MicroSectors Travel 3x Leveraged ETN | D67: {=_FV(A67,"Last trade time",TRUE)} -> 45824.84 | E67: {=_FV(A67,"Price")} -> 43.7273 | F67: {=_FV(A67,"Change (%)",TRUE)} -> 0.082627 | G67: {=_FV(A67,"Change")} -> 3.3373 | H67: {=_FV(A67,"Open")} -> 43.721 | I67: {=_FV(A67,"Low")} -> 43.721 | J67: {=_FV(A67,"High")} -> 43.7273 | K67: {=_FV(A67,"Previous close",TRUE)} -> 40.39 | M67: {=_FV(A67,"52 week low",TRUE)} -> 21.617 | N67: {=_FV(A67,"52 week high",TRUE)} -> 71.01 | O67: {=_FV(A67,"Volume")} -> 788 | P67: {=_FV(A67,"Volume average",TRUE)} -> 2629 | Q67: Financial | T67: {=_FV(A67,"Expense ratio",TRUE)} -> #VALUE! | U67: {=_FV(A67,"Market cap",TRUE)} -> 104909700000 | AC67: 2702 | AN67: Unknown | AO67: {=_FV(A67,"Currency")} -> USD | AP67: {=_FV(A67,"Exchange")} -> NYSE Arca | AQ67: {=_FV(A67,"Exchange abbreviation",TRUE)} -> ARCX | AR67: {=_FV(A67,"Instrument type",TRUE)} -> Stock
A68: #VALUE! | B68: ORR | C68: Militia Long/Short Equity ETF | D68: {=_FV(A68,"Last trade time",TRUE)} -> 45824.844 | E68: {=_FV(A68,"Price")} -> 28.8306 | F68: {=_FV(A68,"Change (%)",TRUE)} -> 0.001101 | G68: {=_FV(A68,"Change")} -> 0.0317 | H68: {=_FV(A68,"Open")} -> 29.22 | I68: {=_FV(A68,"Low")} -> 28.8 | J68: {=_FV(A68,"High")} -> 29.29 | K68: {=_FV(A68,"Previous close",TRUE)} -> 28.7989 | M68: {=_FV(A68,"52 week low",TRUE)} -> 25.63 | N68: {=_FV(A68,"52 week high",TRUE)} -> 29.29 | O68: {=_FV(A68,"Volume")} -> 39092 | P68: {=_FV(A68,"Volume average",TRUE)} -> 38570 | Q68: Long-Short Equity | S68: Militia Investments, LLC | T68: {=_FV(A68,"Expense ratio",TRUE)} -> 0.1848 | U68: {=_FV(A68,"Market cap",TRUE)} -> 76555736 | V68: 76555736 | W68: 76555736 | Y68: 2025-01-13 | Z68: 28.4581 | AA68: 11.03348 | AC68: 45969 | AE68: 9.9922636 | AI68: 45969 | AJ68: 1317011.9 | AL68: 28.9 | AM68: 25.63 | AN68: Medium | AO68: {=_FV(A68,"Currency")} -> USD | AP68: {=_FV(A68,"Exchange")} -> Nasdaq Stock Market | AQ68: {=_FV(A68,"Exchange abbreviation",TRUE)} -> XNAS | AR68: {=_FV(A68,"Instrument type",TRUE)} -> ETF
A69: #VALUE! | B69: PBDC | C69: Putnam ETF Trust Putnam BDC Income ETF | D69: {=_FV(A69,"Last trade time",TRUE)} -> 45824.909 | E69: {=_FV(A69,"Price")} -> 33.02 | F69: {=_FV(A69,"Change (%)",TRUE)} -> -0.010192 | G69: {=_FV(A69,"Change")} -> -0.34 | H69: {=_FV(A69,"Open")} -> 33.49 | I69: {=_FV(A69,"Low")} -> 33.02 | J69: {=_FV(A69,"High")} -> 33.59 | K69: {=_FV(A69,"Previous close",TRUE)} -> 33.36 | M69: {=_FV(A69,"52 week low",TRUE)} -> 27.85 | N69: {=_FV(A69,"52 week high",TRUE)} -> 36.86 | O69: {=_FV(A69,"Volume")} -> 68492 | P69: {=_FV(A69,"Volume average",TRUE)} -> 52297 | Q69: Financial | S69: Franklin Templeton Investments | T69: {=_FV(A69,"Expense ratio",TRUE)} -> 0.1394 | U69: {=_FV(A69,"Market cap",TRUE)} -> 2.1781481e+08 | V69: 217814800 | W69: 217814800 | Y69: 2022-09-28 | Z69: 33.48669 | AA69: 9.666201 | AB69: 0.096599996 | AC69: 67414 | AE69: -0.42129297 | AF69: 6.9197736 | AI69: 67414 | AJ69: 2261065.6 | AL69: 36.86 | AM69: 27.85 | AN69: Medium | AO69: {=_FV(A69,"Currency")} -> USD | AP69: {=_FV(A69,"Exchange")} -> NYSE Arca | AQ69: {=_FV(A69,"Exchange abbreviation",TRUE)} -> ARCX | AR69: {=_FV(A69,"Instrument type",TRUE)} -> ETF
A70: #VALUE! | B70: BIZD | C70: VanEck BDC Income ETF | D70: {=_FV(A70,"Last trade time",TRUE)} -> 45824.923 | E70: {=_FV(A70,"Price")} -> 16.05 | F70: {=_FV(A70,"Change (%)",TRUE)} -> -0.004342 | G70: {=_FV(A70,"Change")} -> -0.07 | H70: {=_FV(A70,"Open")} -> 16.15 | I70: {=_FV(A70,"Low")} -> 15.94 | J70: {=_FV(A70,"High")} -> 16.28 | K70: {=_FV(A70,"Previous close",TRUE)} -> 16.12 | M70: {=_FV(A70,"52 week low",TRUE)} -> 13.5 | N70: {=_FV(A70,"52 week high",TRUE)} -> 17.8565 | O70: {=_FV(A70,"Volume")} -> 1010713 | P70: {=_FV(A70,"Volume average",TRUE)} -> 959469 | Q70: Dividend/Income | T70: {=_FV(A70,"Expense ratio",TRUE)} -> 0.1333 | U70: {=_FV(A70,"Market cap",TRUE)} -> 1.5677835e+09 | X70: -6.04% | AC70: 1020249 | AN70: Unknown | AO70: {=_FV(A70,"Currency")} -> USD | AP70: {=_FV(A70,"Exchange")} -> NYSE Arca | AQ70: {=_FV(A70,"Exchange abbreviation",TRUE)} -> ARCX | AR70: {=_FV(A70,"Instrument type",TRUE)} -> ETF
A71: #VALUE! | B71: VPC | C71: Virtus Private Credit Strategy ETF | D71: {=_FV(A71,"Last trade time",TRUE)} -> 45824.84 | E71: {=_FV(A71,"Price")} -> 20.7197 | F71: {=_FV(A71,"Change (%)",TRUE)} -> -0.003381 | G71: {=_FV(A71,"Change")} -> -0.0703 | H71: {=_FV(A71,"Open")} -> 20.89 | I71: {=_FV(A71,"Low")} -> 20.69 | J71: {=_FV(A71,"High")} -> 20.93 | K71: {=_FV(A71,"Previous close",TRUE)} -> 20.79 | M71: {=_FV(A71,"52 week low",TRUE)} -> 17.985 | N71: {=_FV(A71,"52 week high",TRUE)} -> 23.24 | O71: {=_FV(A71,"Volume")} -> 12030 | P71: {=_FV(A71,"Volume average",TRUE)} -> 14278 | Q71: Nontraditional Bond | S71: Virtus | T71: {=_FV(A71,"Expense ratio",TRUE)} -> 0.0986 | U71: {=_FV(A71,"Market cap",TRUE)} -> 54891096 | V71: 54891096 | W71: 54891096 | Y71: 2019-02-06 | Z71: 20.69965 | AA71: 9.122651 | AB71: 0.1153 | AC71: 25773 | AE71: -2.8555213 | AF71: 0.35435117 | AI71: 25773 | AJ71: 533753.68 | AL71: 23.34 | AM71: 17.985 | AN71: Low | AO71: {=_FV(A71,"Currency")} -> USD | AP71: {=_FV(A71,"Exchange")} -> NYSE Arca | AQ71: {=_FV(A71,"Exchange abbreviation",TRUE)} -> ARCX | AR71: {=_FV(A71,"Instrument type",TRUE)} -> ETF
A72: #VALUE! | B72: MAXI | C72: Simplify Bitcoin Strategy PLUS Income ETF | D72: {=_FV(A72,"Last trade time",TRUE)} -> 45824.881 | E72: {=_FV(A72,"Price")} -> 30.37 | F72: {=_FV(A72,"Change (%)",TRUE)} -> 0.01504 | G72: {=_FV(A72,"Change")} -> 0.45 | H72: {=_FV(A72,"Open")} -> 30 | I72: {=_FV(A72,"Low")} -> 29.7 | J72: {=_FV(A72,"High")} -> 30.88 | K72: {=_FV(A72,"Previous close",TRUE)} -> 29.92 | M72: {=_FV(A72,"52 week low",TRUE)} -> 13.82 | N72: {=_FV(A72,"52 week high",TRUE)} -> 35.7699 | O72: {=_FV(A72,"Volume")} -> 23389 | P72: {=_FV(A72,"Volume average",TRUE)} -> 37020 | Q72: Digital Assets | S72: Simplify Asset Management | T72: {=_FV(A72,"Expense ratio",TRUE)} -> 0.061 | U72: {=_FV(A72,"Market cap",TRUE)} -> 50345428 | V72: 50344216 | W72: 50344216 | Y72: 2022-09-28 | Z72: 29.954 | AB72: 0.29930001 | AC72: 39842 | AE72: 22.252452 | AF72: 47.528897 | AI72: 39842 | AJ72: 1201236.3 | AL72: 35.77 | AM72: 13.82 | AN72: Medium | AO72: {=_FV(A72,"Currency")} -> USD | AP72: {=_FV(A72,"Exchange")} -> Nasdaq Stock Market | AQ72: {=_FV(A72,"Exchange abbreviation",TRUE)} -> XNAS | AR72: {=_FV(A72,"Instrument type",TRUE)} -> ETF
A73: #VALUE! | B73: KBWD | C73: Invesco KBW High Dividend Yield Financial ETF | D73: {=_FV(A73,"Last trade time",TRUE)} -> 45824.938 | E73: {=_FV(A73,"Price")} -> 13.68 | F73: {=_FV(A73,"Change (%)",TRUE)} -> -0.00146 | G73: {=_FV(A73,"Change")} -> -0.02 | H73: {=_FV(A73,"Open")} -> 13.8 | I73: {=_FV(A73,"Low")} -> 13.665 | J73: {=_FV(A73,"High")} -> 13.86 | K73: {=_FV(A73,"Previous close",TRUE)} -> 13.7 | M73: {=_FV(A73,"52 week low",TRUE)} -> 11.96 | N73: {=_FV(A73,"52 week high",TRUE)} -> 16.38 | O73: {=_FV(A73,"Volume")} -> 158808 | P73: {=_FV(A73,"Volume average",TRUE)} -> 185188 | Q73: Financial | S73: Invesco | T73: {=_FV(A73,"Expense ratio",TRUE)} -> 0.0493 | U73: {=_FV(A73,"Market cap",TRUE)} -> 3.901015e+08 | V73: 390105216 | W73: 390105216 | Y73: 2010-12-01 | Z73: 13.68 | AA73: 10.126204 | AB73: 0.1337 | AC73: 251098 | AE73: -1.6996515 | AF73: 2.2021958 | AI73: 251098 | AJ73: 3437531.6 | AL73: 16.38 | AM73: 11.96 | AN73: Medium | AO73: {=_FV(A73,"Currency")} -> USD | AP73: {=_FV(A73,"Exchange")} -> Nasdaq Stock Market | AQ73: {=_FV(A73,"Exchange abbreviation",TRUE)} -> XNAS | AR73: {=_FV(A73,"Instrument type",TRUE)} -> ETF
A74: #VALUE! | B74: YBIT | C74: Tidal Trust II YieldMax Bitcoin Option Income Strategy ETF | D74: {=_FV(A74,"Last trade time",TRUE)} -> 45824.935 | E74: {=_FV(A74,"Price")} -> 10.52 | F74: {=_FV(A74,"Change (%)",TRUE)} -> 0.032385 | G74: {=_FV(A74,"Change")} -> 0.33 | H74: {=_FV(A74,"Open")} -> 10.34 | I74: {=_FV(A74,"Low")} -> 10.33 | J74: {=_FV(A74,"High")} -> 10.545 | K74: {=_FV(A74,"Previous close",TRUE)} -> 10.19 | M74: {=_FV(A74,"52 week low",TRUE)} -> 9.04 | N74: {=_FV(A74,"52 week high",TRUE)} -> 18.3 | O74: {=_FV(A74,"Volume")} -> 608374 | P74: {=_FV(A74,"Volume average",TRUE)} -> 477731 | Q74: Digital Assets | S74: YieldMax ETFs | T74: {=_FV(A74,"Expense ratio",TRUE)} -> 0.0476 | U74: {=_FV(A74,"Market cap",TRUE)} -> 1.3072315e+08 | V74: 130723144 | W74: 130723144 | Y74: 2024-04-21 | Z74: 10.539 | AB74: 0.9979 | AC74: 276906 | AE74: 11.404396 | AF74: 14.543696 | AI74: 276906 | AJ74: 2918589.2 | AL74: 19.1 | AM74: 9.04 | AN74: Medium | AO74: {=_FV(A74,"Currency")} -> USD | AP74: {=_FV(A74,"Exchange")} -> NYSE Arca | AQ74: {=_FV(A74,"Exchange abbreviation",TRUE)} -> ARCX | AR74: {=_FV(A74,"Instrument type",TRUE)} -> ETF
A75: #VALUE! | B75: RTAI | C75: Rareview Tax Advantaged Income ETF | D75: {=_FV(A75,"Last trade time",TRUE)} -> 45824.84 | E75: {=_FV(A75,"Price")} -> 20.315 | F75: {=_FV(A75,"Change (%)",TRUE)} -> 0.000128 | G75: {=_FV(A75,"Change")} -> 0.0026 | H75: {=_FV(A75,"Open")} -> 20.315 | I75: {=_FV(A75,"Low")} -> 20.315 | J75: {=_FV(A75,"High")} -> 20.315 | K75: {=_FV(A75,"Previous close",TRUE)} -> 20.3124 | M75: {=_FV(A75,"52 week low",TRUE)} -> 19.56 | N75: {=_FV(A75,"52 week high",TRUE)} -> 23.55 | O75: {=_FV(A75,"Volume")} -> 3 | P75: {=_FV(A75,"Volume average",TRUE)} -> 903 | Q75: Muni National Long | S75: Rareview Capital | T75: {=_FV(A75,"Expense ratio",TRUE)} -> 0.0472 | U75: {=_FV(A75,"Market cap",TRUE)} -> 17302134 | V75: 17302134 | W75: 17302134 | Y75: 2020-10-19 | Z75: 20.15 | AB75: 0.0619 | AC75: 1900 | AE75: -3.7390733 | AF75: 1.2012325 | AI75: 1900 | AJ75: 38294.5 | AL75: 23.55 | AM75: 19.56 | AN75: Low | AO75: {=_FV(A75,"Currency")} -> USD | AP75: {=_FV(A75,"Exchange")} -> CBOE BZX Exchange | AQ75: {=_FV(A75,"Exchange abbreviation",TRUE)} -> BATS | AR75: {=_FV(A75,"Instrument type",TRUE)} -> ETF
A76: #VALUE! | B76: RDFI | C76: Rareview Dynamic Fixed Income ETF | D76: {=_FV(A76,"Last trade time",TRUE)} -> 45824.84 | E76: {=_FV(A76,"Price")} -> 23.3949 | F76: {=_FV(A76,"Change (%)",TRUE)} -> 0.001275 | G76: {=_FV(A76,"Change")} -> 0.0298 | H76: {=_FV(A76,"Open")} -> 23.445 | I76: {=_FV(A76,"Low")} -> 23.3801 | J76: {=_FV(A76,"High")} -> 23.46 | K76: {=_FV(A76,"Previous close",TRUE)} -> 23.3651 | M76: {=_FV(A76,"52 week low",TRUE)} -> 21.98 | N76: {=_FV(A76,"52 week high",TRUE)} -> 27.9217 | O76: {=_FV(A76,"Volume")} -> 2893 | P76: {=_FV(A76,"Volume average",TRUE)} -> 5147 | Q76: Multisector Bond | S76: Rareview Capital | T76: {=_FV(A76,"Expense ratio",TRUE)} -> 0.0446 | U76: {=_FV(A76,"Market cap",TRUE)} -> 49267306 | V76: 49267304 | W76: 49267304 | Y76: 2020-10-19 | Z76: 23.28 | AA76: 21.497221 | AB76: 0.0842 | AC76: 11128 | AE76: 1.6515103 | AF76: 10.005124 | AI76: 11128 | AJ76: 258892.92 | AL76: 27.922 | AM76: 21.98 | AN76: Low | AO76: {=_FV(A76,"Currency")} -> USD | AP76: {=_FV(A76,"Exchange")} -> CBOE BZX Exchange | AQ76: {=_FV(A76,"Exchange abbreviation",TRUE)} -> BATS | AR76: {=_FV(A76,"Instrument type",TRUE)} -> ETF
A77: #VALUE! | B77: CANE | C77: Teucrium Sugar Fund ETV | D77: {=_FV(A77,"Last trade time",TRUE)} -> 45824.84 | E77: {=_FV(A77,"Price")} -> 11.26 | F77: {=_FV(A77,"Change (%)",TRUE)} -> 0.02925 | G77: {=_FV(A77,"Change")} -> 0.32 | H77: {=_FV(A77,"Open")} -> 10.94 | I77: {=_FV(A77,"Low")} -> 10.92 | J77: {=_FV(A77,"High")} -> 11.27 | K77: {=_FV(A77,"Previous close",TRUE)} -> 10.94 | M77: {=_FV(A77,"52 week low",TRUE)} -> 10.77 | N77: {=_FV(A77,"52 week high",TRUE)} -> 13.73 | O77: {=_FV(A77,"Volume")} -> 44352 | P77: {=_FV(A77,"Volume average",TRUE)} -> 25500 | Q77: Commodities Focused | R77: Commodities - Sugar | S77: Teucrium | T77: {=_FV(A77,"Expense ratio",TRUE)} -> 0.0442 | U77: {=_FV(A77,"Market cap",TRUE)} -> 10748977 | V77: 10748976 | W77: 10748976 | X77: -4.54% | Y77: 2011-09-15 | Z77: 11.1305 | AB77: 0 | AC77: 35876 | AE77: -3.8560395 | AF77: -3.9383564 | AI77: 35876 | AJ77: 400017.4 | AL77: 13.73 | AM77: 10.77 | AN77: Low | AO77: {=_FV(A77,"Currency")} -> USD | AP77: {=_FV(A77,"Exchange")} -> NYSE Arca | AQ77: {=_FV(A77,"Exchange abbreviation",TRUE)} -> ARCX | AR77: {=_FV(A77,"Instrument type",TRUE)} -> ETF
A78: #VALUE! | B78: CEFS | C78: Saba Closed-End Funds ETF | D78: {=_FV(A78,"Last trade time",TRUE)} -> 45824.84 | E78: {=_FV(A78,"Price")} -> 22.15 | F78: {=_FV(A78,"Change (%)",TRUE)} -> 0.006388 | G78: {=_FV(A78,"Change")} -> 0.1406 | H78: {=_FV(A78,"Open")} -> 22.01 | I78: {=_FV(A78,"Low")} -> 22.01 | J78: {=_FV(A78,"High")} -> 22.2296 | K78: {=_FV(A78,"Previous close",TRUE)} -> 22.0094 | M78: {=_FV(A78,"52 week low",TRUE)} -> 18.59 | N78: {=_FV(A78,"52 week high",TRUE)} -> 22.7 | O78: {=_FV(A78,"Volume")} -> 45794 | P78: {=_FV(A78,"Volume average",TRUE)} -> 68687 | Q78: Tactical Allocation | S78: SABA ETF | T78: {=_FV(A78,"Expense ratio",TRUE)} -> 0.0429 | U78: {=_FV(A78,"Market cap",TRUE)} -> 2.8203855e+08 | V78: 282038560 | W78: 282038560 | X78: 5.92% | Y78: 2017-03-19 | Z78: 22.06 | AA78: 21.540356 | AB78: 0.0806 | AC78: 92603 | AE78: 7.0930877 | AF78: 13.543199 | AI78: 92603 | AJ78: 2055786.6 | AL78: 22.7 | AM78: 18.59 | AN78: Medium | AO78: {=_FV(A78,"Currency")} -> USD | AP78: {=_FV(A78,"Exchange")} -> CBOE BZX Exchange | AQ78: {=_FV(A78,"Exchange abbreviation",TRUE)} -> BATS | AR78: {=_FV(A78,"Instrument type",TRUE)} -> ETF
A79: #VALUE! | B79: DWSH | C79: AdvisorShares Dorsey Wright Short ETF | D79: {=_FV(A79,"Last trade time",TRUE)} -> 45824.844 | E79: {=_FV(A79,"Price")} -> 7.39 | F79: {=_FV(A79,"Change (%)",TRUE)} -> -0.012587 | G79: {=_FV(A79,"Change")} -> -0.0942 | H79: {=_FV(A79,"Open")} -> 7.46 | I79: {=_FV(A79,"Low")} -> 7.3605 | J79: {=_FV(A79,"High")} -> 7.46 | K79: {=_FV(A79,"Previous close",TRUE)} -> 7.4842 | M79: {=_FV(A79,"52 week low",TRUE)} -> 6.66 | N79: {=_FV(A79,"52 week high",TRUE)} -> 9.08 | O79: {=_FV(A79,"Volume")} -> 12918 | P79: {=_FV(A79,"Volume average",TRUE)} -> 23846 | Q79: Trading--Inverse Equity | R79: Equities - - Short | S79: AdvisorShares | T79: {=_FV(A79,"Expense ratio",TRUE)} -> 0.0405 | U79: {=_FV(A79,"Market cap",TRUE)} -> 12721621 | V79: 12724384 | W79: 12724384 | Y79: 2018-07-09 | Z79: 7.61658 | AB79: 0.0547 | AC79: 64298 | AE79: 6.2411286 | AF79: 8.4500967 | AI79: 64298 | AJ79: 491236.72 | AL79: 9.08 | AM79: 6.66 | AN79: Low | AO79: {=_FV(A79,"Currency")} -> USD | AP79: {=_FV(A79,"Exchange")} -> Nasdaq Stock Market | AQ79: {=_FV(A79,"Exchange abbreviation",TRUE)} -> XNAS | AR79: {=_FV(A79,"Instrument type",TRUE)} -> ETF
A80: #VALUE! | B80: CCEF | C80: Calamos ETF Trust Calamos CEF Income & Arbitrage ETF | D80: {=_FV(A80,"Last trade time",TRUE)} -> 45824.84 | E80: {=_FV(A80,"Price")} -> 27.8567 | F80: {=_FV(A80,"Change (%)",TRUE)} -> -0.0004772 | G80: {=_FV(A80,"Change")} -> -0.0133 | H80: {=_FV(A80,"Open")} -> 27.959 | I80: {=_FV(A80,"Low")} -> 27.8567 | J80: {=_FV(A80,"High")} -> 27.959 | K80: {=_FV(A80,"Previous close",TRUE)} -> 27.87 | M80: {=_FV(A80,"52 week low",TRUE)} -> 24.03 | N80: {=_FV(A80,"52 week high",TRUE)} -> 29.27 | O80: {=_FV(A80,"Volume")} -> 681 | P80: {=_FV(A80,"Volume average",TRUE)} -> 2353 | Q80: Relative Value Arbitrage | S80: Calamos | T80: {=_FV(A80,"Expense ratio",TRUE)} -> 0.0404 | U80: {=_FV(A80,"Market cap",TRUE)} -> 15918216 | V80: 15918216 | W80: 15918216 | X80: 4.44% | Y80: 2024-01-15 | Z80: 27.73 | AB80: 0.076799996 | AC80: 5509 | AE80: 3.1983527 | AF80: 12.504277 | AI80: 5509 | AJ80: 152865.38 | AL80: 29.27 | AM80: 24.03 | AN80: Low | AO80: {=_FV(A80,"Currency")} -> USD | AP80: {=_FV(A80,"Exchange")} -> NYSE Arca | AQ80: {=_FV(A80,"Exchange abbreviation",TRUE)} -> ARCX | AR80: {=_FV(A80,"Instrument type",TRUE)} -> ETF
A81: #VALUE! | B81: HDGE | C81: Ranger Equity Bear Bear ETF | D81: {=_FV(A81,"Last trade time",TRUE)} -> 45824.936 | E81: {=_FV(A81,"Price")} -> 17.255 | F81: {=_FV(A81,"Change (%)",TRUE)} -> -0.014 | G81: {=_FV(A81,"Change")} -> -0.245 | H81: {=_FV(A81,"Open")} -> 17.36 | I81: {=_FV(A81,"Low")} -> 17.18 | J81: {=_FV(A81,"High")} -> 17.36 | K81: {=_FV(A81,"Previous close",TRUE)} -> 17.5 | M81: {=_FV(A81,"52 week low",TRUE)} -> 15.39 | N81: {=_FV(A81,"52 week high",TRUE)} -> 21.32 | O81: {=_FV(A81,"Volume")} -> 180331 | P81: {=_FV(A81,"Volume average",TRUE)} -> 66223 | Q81: Other | T81: {=_FV(A81,"Expense ratio",TRUE)} -> 0.038 | U81: {=_FV(A81,"Market cap",TRUE)} -> 47519307 | AC81: 74383 | AN81: Unknown | AO81: {=_FV(A81,"Currency")} -> USD | AP81: {=_FV(A81,"Exchange")} -> NYSE Arca | AQ81: {=_FV(A81,"Exchange abbreviation",TRUE)} -> ARCX | AR81: {=_FV(A81,"Instrument type",TRUE)} -> ETF
A82: #VALUE! | B82: FCEF | C82: First Trust Income Opportunities ETF | D82: {=_FV(A82,"Last trade time",TRUE)} -> 45824.906 | E82: {=_FV(A82,"Price")} -> 22.01 | F82: {=_FV(A82,"Change (%)",TRUE)} -> 0.00379 | G82: {=_FV(A82,"Change")} -> 0.0831 | H82: {=_FV(A82,"Open")} -> 22.028 | I82: {=_FV(A82,"Low")} -> 21.92 | J82: {=_FV(A82,"High")} -> 22.06 | K82: {=_FV(A82,"Previous close",TRUE)} -> 21.9269 | M82: {=_FV(A82,"52 week low",TRUE)} -> 18.8517 | N82: {=_FV(A82,"52 week high",TRUE)} -> 22.64 | O82: {=_FV(A82,"Volume")} -> 16605 | P82: {=_FV(A82,"Volume average",TRUE)} -> 8052 | Q82: Global Moderately Conservative Allocation | S82: First Trust | T82: {=_FV(A82,"Expense ratio",TRUE)} -> 0.0367 | U82: {=_FV(A82,"Market cap",TRUE)} -> 44758743 | V82: 44757784 | W82: 44757784 | Y82: 2016-09-26 | Z82: 21.99 | AA82: 19.708141 | AB82: 0.0714 | AC82: 7852 | AE82: 5.7053293 | AF82: 12.766902 | AI82: 7852 | AJ82: 172351.4 | AL82: 22.64 | AM82: 18.852 | AN82: Low | AO82: {=_FV(A82,"Currency")} -> USD | AP82: {=_FV(A82,"Exchange")} -> Nasdaq Stock Market | AQ82: {=_FV(A82,"Exchange abbreviation",TRUE)} -> XNAS | AR82: {=_FV(A82,"Instrument type",TRUE)} -> ETF
A83: #VALUE! | B83: SOYB | C83: Teucrium Soybean Fund ETV | D83: {=_FV(A83,"Last trade time",TRUE)} -> 45824.84 | E83: {=_FV(A83,"Price")} -> 22.38 | F83: {=_FV(A83,"Change (%)",TRUE)} -> 0.004038 | G83: {=_FV(A83,"Change")} -> 0.09 | H83: {=_FV(A83,"Open")} -> 22.41 | I83: {=_FV(A83,"Low")} -> 22.26 | J83: {=_FV(A83,"High")} -> 22.51 | K83: {=_FV(A83,"Previous close",TRUE)} -> 22.29 | M83: {=_FV(A83,"52 week low",TRUE)} -> 20.2 | N83: {=_FV(A83,"52 week high",TRUE)} -> 24.31 | O83: {=_FV(A83,"Volume")} -> 133771 | P83: {=_FV(A83,"Volume average",TRUE)} -> 27539 | Q83: Other | T83: {=_FV(A83,"Expense ratio",TRUE)} -> 0.0356 | U83: {=_FV(A83,"Market cap",TRUE)} -> 25438435 | AC83: 24295 | AN83: Unknown | AO83: {=_FV(A83,"Currency")} -> USD | AP83: {=_FV(A83,"Exchange")} -> NYSE Arca | AQ83: {=_FV(A83,"Exchange abbreviation",TRUE)} -> ARCX | AR83: {=_FV(A83,"Instrument type",TRUE)} -> ETF
A84: #VALUE! | B84: CORN | C84: Teucrium Corn Fund ETV | D84: {=_FV(A84,"Last trade time",TRUE)} -> 45824.903 | E84: {=_FV(A84,"Price")} -> 18.09 | F84: {=_FV(A84,"Change (%)",TRUE)} -> -0.016313 | G84: {=_FV(A84,"Change")} -> -0.3 | H84: {=_FV(A84,"Open")} -> 18.23 | I84: {=_FV(A84,"Low")} -> 18.06 | J84: {=_FV(A84,"High")} -> 18.24 | K84: {=_FV(A84,"Previous close",TRUE)} -> 18.39 | M84: {=_FV(A84,"52 week low",TRUE)} -> 17.021 | N84: {=_FV(A84,"52 week high",TRUE)} -> 20.69 | O84: {=_FV(A84,"Volume")} -> 62683 | P84: {=_FV(A84,"Volume average",TRUE)} -> 56653 | Q84: Commodities Focused | R84: Commodities - Corn | S84: Teucrium | T84: {=_FV(A84,"Expense ratio",TRUE)} -> 0.0327 | U84: {=_FV(A84,"Market cap",TRUE)} -> 48890412 | V84: 48890412 | W84: 48890412 | Y84: 2010-06-08 | Z84: 18.6082 | AB84: 0 | AC84: 75780 | AE84: -3.3350936 | AF84: -9.0637435 | AI84: 75780 | AJ84: 1411023.6 | AL84: 20.69 | AM84: 17.02 | AN84: Medium | AO84: {=_FV(A84,"Currency")} -> USD | AP84: {=_FV(A84,"Exchange")} -> NYSE Arca | AQ84: {=_FV(A84,"Exchange abbreviation",TRUE)} -> ARCX | AR84: {=_FV(A84,"Instrument type",TRUE)} -> ETF
A85: #VALUE! | B85: YYY | C85: Amplify High Income ETF | D85: {=_FV(A85,"Last trade time",TRUE)} -> 45824.912 | E85: {=_FV(A85,"Price")} -> 11.63 | F85: {=_FV(A85,"Change (%)",TRUE)} -> 0.002586 | G85: {=_FV(A85,"Change")} -> 0.03 | H85: {=_FV(A85,"Open")} -> 11.6 | I85: {=_FV(A85,"Low")} -> 11.6 | J85: {=_FV(A85,"High")} -> 11.67 | K85: {=_FV(A85,"Previous close",TRUE)} -> 11.6 | M85: {=_FV(A85,"52 week low",TRUE)} -> 9.872 | N85: {=_FV(A85,"52 week high",TRUE)} -> 12.4 | O85: {=_FV(A85,"Volume")} -> 222378 | P85: {=_FV(A85,"Volume average",TRUE)} -> 218628 | Q85: Dividend/Income | T85: {=_FV(A85,"Expense ratio",TRUE)} -> 0.0325 | U85: {=_FV(A85,"Market cap",TRUE)} -> 5.5018424e+08 | AC85: 214312 | AN85: Unknown | AO85: {=_FV(A85,"Currency")} -> USD | AP85: {=_FV(A85,"Exchange")} -> NYSE Arca | AQ85: {=_FV(A85,"Exchange abbreviation",TRUE)} -> ARCX | AR85: {=_FV(A85,"Instrument type",TRUE)} -> ETF
A86: #VALUE! | B86: WEAT | C86: Teucrium Wheat Fund ETV | D86: {=_FV(A86,"Last trade time",TRUE)} -> 45824.915 | E86: {=_FV(A86,"Price")} -> 4.56 | F86: {=_FV(A86,"Change (%)",TRUE)} -> -0.012987 | G86: {=_FV(A86,"Change")} -> -0.06 | H86: {=_FV(A86,"Open")} -> 4.59 | I86: {=_FV(A86,"Low")} -> 4.5245 | J86: {=_FV(A86,"High")} -> 4.59 | K86: {=_FV(A86,"Previous close",TRUE)} -> 4.62 | M86: {=_FV(A86,"52 week low",TRUE)} -> 4.33 | N86: {=_FV(A86,"52 week high",TRUE)} -> 5.63 | O86: {=_FV(A86,"Volume")} -> 524368 | P86: {=_FV(A86,"Volume average",TRUE)} -> 731519 | Q86: Commodities Focused | R86: Commodities - Wheat | S86: Teucrium | T86: {=_FV(A86,"Expense ratio",TRUE)} -> 0.032 | U86: {=_FV(A86,"Market cap",TRUE)} -> 1.1958271e+08 | V86: 119582704 | W86: 119582704 | Y86: 2011-09-15 | Z86: 4.6817 | AB86: 0 | AC86: 895344 | AE86: -3.5564868 | AF86: -23.166664 | AI86: 895344 | AJ86: 4190209.9 | AL86: 5.94 | AM86: 4.33 | AN86: Medium | AO86: {=_FV(A86,"Currency")} -> USD | AP86: {=_FV(A86,"Exchange")} -> NYSE Arca | AQ86: {=_FV(A86,"Exchange abbreviation",TRUE)} -> ARCX | AR86: {=_FV(A86,"Instrument type",TRUE)} -> ETF
A87: #VALUE! | B87: ICAP | C87: Infrastructure Capital Equity Income ETF | D87: {=_FV(A87,"Last trade time",TRUE)} -> 45824.84 | E87: {=_FV(A87,"Price")} -> 25.51 | F87: {=_FV(A87,"Change (%)",TRUE)} -> 0.00783 | G87: {=_FV(A87,"Change")} -> 0.1982 | H87: {=_FV(A87,"Open")} -> 25.22 | I87: {=_FV(A87,"Low")} -> 25.22 | J87: {=_FV(A87,"High")} -> 25.7235 | K87: {=_FV(A87,"Previous close",TRUE)} -> 25.3118 | M87: {=_FV(A87,"52 week low",TRUE)} -> 21.25 | N87: {=_FV(A87,"52 week high",TRUE)} -> 28.45 | O87: {=_FV(A87,"Volume")} -> 5722 | P87: {=_FV(A87,"Volume average",TRUE)} -> 8069 | Q87: Mid-Cap Value | S87: InfraCap | T87: {=_FV(A87,"Expense ratio",TRUE)} -> 0.0319 | U87: {=_FV(A87,"Market cap",TRUE)} -> 59445834 | V87: 59445832 | W87: 59445832 | Y87: 2021-12-27 | Z87: 25.4385 | AA87: 18.507357 | AB87: 0.0908 | AC87: 10985 | AE87: 0.53394016 | AF87: 11.543889 | AI87: 10985 | AJ87: 279600.11 | AL87: 28.45 | AM87: 21.25 | AN87: Low | AO87: {=_FV(A87,"Currency")} -> USD | AP87: {=_FV(A87,"Exchange")} -> NYSE Arca | AQ87: {=_FV(A87,"Exchange abbreviation",TRUE)} -> ARCX | AR87: {=_FV(A87,"Instrument type",TRUE)} -> ETF
A88: #VALUE! | B88: PCEF | C88: Invesco CEF Income Composite ETF | D88: {=_FV(A88,"Last trade time",TRUE)} -> 45824.84 | E88: {=_FV(A88,"Price")} -> 19.31 | F88: {=_FV(A88,"Change (%)",TRUE)} -> 0.002284 | G88: {=_FV(A88,"Change")} -> 0.044 | H88: {=_FV(A88,"Open")} -> 19.3 | I88: {=_FV(A88,"Low")} -> 19.28 | J88: {=_FV(A88,"High")} -> 19.36 | K88: {=_FV(A88,"Previous close",TRUE)} -> 19.266 | M88: {=_FV(A88,"52 week low",TRUE)} -> 16.3508 | N88: {=_FV(A88,"52 week high",TRUE)} -> 19.95 | O88: {=_FV(A88,"Volume")} -> 93328 | P88: {=_FV(A88,"Volume average",TRUE)} -> 122795 | Q88: Global Moderate Allocation | S88: Invesco | T88: {=_FV(A88,"Expense ratio",TRUE)} -> 0.0307 | U88: {=_FV(A88,"Market cap",TRUE)} -> 7.9694095e+08 | V88: 796951552 | W88: 796951552 | Y88: 2010-02-18 | Z88: 19.18 | AA88: 22.912483 | AB88: 0.0747 | AC88: 187838 | AE88: 3.4810807 | AF88: 11.835842 | AI88: 187838 | AJ88: 3609964.6 | AL88: 19.95 | AM88: 16.35 | AN88: Medium | AO88: {=_FV(A88,"Currency")} -> USD | AP88: {=_FV(A88,"Exchange")} -> NYSE Arca | AQ88: {=_FV(A88,"Exchange abbreviation",TRUE)} -> ARCX | AR88: {=_FV(A88,"Instrument type",TRUE)} -> ETF
A89: #VALUE! | B89: AMZA | C89: InfraCap MLP ETF | D89: {=_FV(A89,"Last trade time",TRUE)} -> 45824.918 | E89: {=_FV(A89,"Price")} -> 43.2509 | F89: {=_FV(A89,"Change (%)",TRUE)} -> -0.011672 | G89: {=_FV(A89,"Change")} -> -0.5108 | H89: {=_FV(A89,"Open")} -> 43.78 | I89: {=_FV(A89,"Low")} -> 43.1 | J89: {=_FV(A89,"High")} -> 44.0702 | K89: {=_FV(A89,"Previous close",TRUE)} -> 43.7617 | M89: {=_FV(A89,"52 week low",TRUE)} -> 37.18 | N89: {=_FV(A89,"52 week high",TRUE)} -> 48.98 | O89: {=_FV(A89,"Volume")} -> 20758 | P89: {=_FV(A89,"Volume average",TRUE)} -> 30496 | Q89: Energy Limited Partnership | S89: Virtus | T89: {=_FV(A89,"Expense ratio",TRUE)} -> 0.0275 | U89: {=_FV(A89,"Market cap",TRUE)} -> 3.9699034e+08 | V89: 396990336 | W89: 396990336 | X89: 9.75% | Y89: 2014-09-30 | Z89: 43.09086 | AA89: 13.545773 | AB89: 0.0657 | AC89: 35980 | AE89: 1.2662175 | AF89: 17.457727 | AI89: 35980 | AJ89: 1549133.3 | AL89: 48.98 | AM89: 37.18 | AN89: Medium | AO89: {=_FV(A89,"Currency")} -> USD | AP89: {=_FV(A89,"Exchange")} -> NYSE Arca | AQ89: {=_FV(A89,"Exchange abbreviation",TRUE)} -> ARCX | AR89: {=_FV(A89,"Instrument type",TRUE)} -> ETF
A90: #VALUE! | B90: CBLS | C90: Elevation Series Trust Clough Hedged Equity ETF | D90: {=_FV(A90,"Last trade time",TRUE)} -> 45824.84 | E90: {=_FV(A90,"Price")} -> 28.373 | F90: {=_FV(A90,"Change (%)",TRUE)} -> 0.00258 | G90: {=_FV(A90,"Change")} -> 0.073 | H90: {=_FV(A90,"Open")} -> 28.35 | I90: {=_FV(A90,"Low")} -> 28.35 | J90: {=_FV(A90,"High")} -> 28.43 | K90: {=_FV(A90,"Previous close",TRUE)} -> 28.3 | M90: {=_FV(A90,"52 week low",TRUE)} -> 24.1469 | N90: {=_FV(A90,"52 week high",TRUE)} -> 28.83 | O90: {=_FV(A90,"Volume")} -> 28133 | P90: {=_FV(A90,"Volume average",TRUE)} -> 11329 | Q90: Equity Hedged | S90: Clough Capital Partners L.P. | T90: {=_FV(A90,"Expense ratio",TRUE)} -> 0.0259 | U90: {=_FV(A90,"Market cap",TRUE)} -> 42597655 | V90: 42597656 | W90: 42597656 | X90: -1.83% | Y90: 2020-11-11 | Z90: 28.2337 | AA90: 24.036148 | AB90: 0.0068 | AC90: 7147 | AE90: 6.5559499 | AF90: 10.40985 | AI90: 7147 | AJ90: 201743.37 | AL90: 28.83 | AM90: 24.147 | AN90: Low | AO90: {=_FV(A90,"Currency")} -> USD | AP90: {=_FV(A90,"Exchange")} -> NYSE Arca | AQ90: {=_FV(A90,"Exchange abbreviation",TRUE)} -> ARCX | AR90: {=_FV(A90,"Instrument type",TRUE)} -> ETF
A91: #VALUE! | B91: SURI | C91: Simplify Exchange Traded Funds Simplify Propel Opportunities E | D91: {=_FV(A91,"Last trade time",TRUE)} -> 45824.916 | E91: {=_FV(A91,"Price")} -> 16.2454 | F91: {=_FV(A91,"Change (%)",TRUE)} -> 0.0006406 | G91: {=_FV(A91,"Change")} -> 0.0104 | H91: {=_FV(A91,"Open")} -> 16.29 | I91: {=_FV(A91,"Low")} -> 16.173 | J91: {=_FV(A91,"High")} -> 16.29 | K91: {=_FV(A91,"Previous close",TRUE)} -> 16.235 | M91: {=_FV(A91,"52 week low",TRUE)} -> 12.7086 | N91: {=_FV(A91,"52 week high",TRUE)} -> 27.52 | O91: {=_FV(A91,"Volume")} -> 3505 | P91: {=_FV(A91,"Volume average",TRUE)} -> 1194 | Q91: Health | S91: Simplify Asset Management | T91: {=_FV(A91,"Expense ratio",TRUE)} -> 0.0254 | U91: {=_FV(A91,"Market cap",TRUE)} -> 63516592 | V91: 63516592 | W91: 63516592 | Y91: 2023-02-06 | Z91: 16.0374 | AB91: 0.2258 | AC91: 2893 | AE91: 4.0640494 | AF91: -16.719984 | AI91: 2893 | AJ91: 46471.416 | AL91: 27.52 | AM91: 12.709 | AN91: Low | AO91: {=_FV(A91,"Currency")} -> USD | AP91: {=_FV(A91,"Exchange")} -> NYSE Arca | AQ91: {=_FV(A91,"Exchange abbreviation",TRUE)} -> ARCX | AR91: {=_FV(A91,"Instrument type",TRUE)} -> ETF
A92: #VALUE! | B92: FXED | C92: Sound Enhanced Fixed Income ETF | D92: {=_FV(A92,"Last trade time",TRUE)} -> 45824.84 | E92: {=_FV(A92,"Price")} -> 17.8047 | F92: {=_FV(A92,"Change (%)",TRUE)} -> -0.001346 | G92: {=_FV(A92,"Change")} -> -0.024 | H92: {=_FV(A92,"Open")} -> 17.9075 | I92: {=_FV(A92,"Low")} -> 17.75 | J92: {=_FV(A92,"High")} -> 17.9088 | K92: {=_FV(A92,"Previous close",TRUE)} -> 17.8287 | M92: {=_FV(A92,"52 week low",TRUE)} -> 16.85 | N92: {=_FV(A92,"52 week high",TRUE)} -> 19.57 | O92: {=_FV(A92,"Volume")} -> 8537 | P92: {=_FV(A92,"Volume average",TRUE)} -> 9784 | Q92: Conservative Allocation | S92: Sound ETF | T92: {=_FV(A92,"Expense ratio",TRUE)} -> 0.0251 | U92: {=_FV(A92,"Market cap",TRUE)} -> 40198802 | V92: 40198800 | W92: 40198800 | Y92: 2020-12-29 | Z92: 17.9104 | AA92: 11.032406 | AB92: 0.0681 | AC92: 8069 | AE92: 0.10587703 | AF92: 3.5258033 | AI92: 8069 | AJ92: 144475.45 | AL92: 19.57 | AM92: 16.85 | AN92: Low | AO92: {=_FV(A92,"Currency")} -> USD | AP92: {=_FV(A92,"Exchange")} -> New York Stock Exchange | AQ92: {=_FV(A92,"Exchange abbreviation",TRUE)} -> XNYS | AR92: {=_FV(A92,"Instrument type",TRUE)} -> ETF
A93: #VALUE! | B93: PFFA | C93: Virtus InfraCap U.S. Preferred Stock ETF | D93: {=_FV(A93,"Last trade time",TRUE)} -> 45824.924 | E93: {=_FV(A93,"Price")} -> 20.75 | F93: {=_FV(A93,"Change (%)",TRUE)} -> 0.00387 | G93: {=_FV(A93,"Change")} -> 0.08 | H93: {=_FV(A93,"Open")} -> 20.73 | I93: {=_FV(A93,"Low")} -> 20.73 | J93: {=_FV(A93,"High")} -> 20.85 | K93: {=_FV(A93,"Previous close",TRUE)} -> 20.67 | M93: {=_FV(A93,"52 week low",TRUE)} -> 19.2 | N93: {=_FV(A93,"52 week high",TRUE)} -> 23.2372 | O93: {=_FV(A93,"Volume")} -> 305366 | P93: {=_FV(A93,"Volume average",TRUE)} -> 517810 | Q93: Other | T93: {=_FV(A93,"Expense ratio",TRUE)} -> 0.0248 | U93: {=_FV(A93,"Market cap",TRUE)} -> 1.5056177e+09 | AC93: 511717 | AN93: Unknown | AO93: {=_FV(A93,"Currency")} -> USD | AP93: {=_FV(A93,"Exchange")} -> NYSE Arca | AQ93: {=_FV(A93,"Exchange abbreviation",TRUE)} -> ARCX | AR93: {=_FV(A93,"Instrument type",TRUE)} -> ETF
A94: #VALUE! | B94: UVIX | C94: VS TR 2x Long VIX Futures ETF | D94: {=_FV(A94,"Last trade time",TRUE)} -> 45824.941 | E94: {=_FV(A94,"Price")} -> 26.015 | F94: {=_FV(A94,"Change (%)",TRUE)} -> -0.140852 | G94: {=_FV(A94,"Change")} -> -4.265 | H94: {=_FV(A94,"Open")} -> 27.8 | I94: {=_FV(A94,"Low")} -> 25.5 | J94: {=_FV(A94,"High")} -> 27.8 | K94: {=_FV(A94,"Previous close",TRUE)} -> 30.28 | M94: {=_FV(A94,"52 week low",TRUE)} -> 23.63 | N94: {=_FV(A94,"52 week high",TRUE)} -> 199.7 | O94: {=_FV(A94,"Volume")} -> 14927651 | P94: {=_FV(A94,"Volume average",TRUE)} -> 10573902 | Q94: Alternative/Volatility | T94: {=_FV(A94,"Expense ratio",TRUE)} -> 0.0236 | U94: {=_FV(A94,"Market cap",TRUE)} -> 3.799431e+08 | AC94: 9374363 | AN94: Unknown | AO94: {=_FV(A94,"Currency")} -> USD | AP94: {=_FV(A94,"Exchange")} -> CBOE BZX Exchange | AQ94: {=_FV(A94,"Exchange abbreviation",TRUE)} -> BATS | AR94: {=_FV(A94,"Instrument type",TRUE)} -> ETF
A95: #VALUE! | B95: SPCX | C95: SPAC and New Issue ETF | D95: {=_FV(A95,"Last trade time",TRUE)} -> 45824.844 | E95: {=_FV(A95,"Price")} -> 25.895 | F95: {=_FV(A95,"Change (%)",TRUE)} -> 0.008875 | G95: {=_FV(A95,"Change")} -> 0.2278 | H95: {=_FV(A95,"Open")} -> 25.74 | I95: {=_FV(A95,"Low")} -> 25.74 | J95: {=_FV(A95,"High")} -> 25.895 | K95: {=_FV(A95,"Previous close",TRUE)} -> 25.6672 | M95: {=_FV(A95,"52 week low",TRUE)} -> 22.4 | N95: {=_FV(A95,"52 week high",TRUE)} -> 25.99 | O95: {=_FV(A95,"Volume")} -> 1970 | P95: {=_FV(A95,"Volume average",TRUE)} -> 2647 | Q95: Other | T95: {=_FV(A95,"Expense ratio",TRUE)} -> 0.0231 | U95: {=_FV(A95,"Market cap",TRUE)} -> 8830754.4 | AC95: 2827 | AN95: Unknown | AO95: {=_FV(A95,"Currency")} -> USD | AP95: {=_FV(A95,"Exchange")} -> Nasdaq Stock Market | AQ95: {=_FV(A95,"Exchange abbreviation",TRUE)} -> XNAS | AR95: {=_FV(A95,"Instrument type",TRUE)} -> ETF
A96: #VALUE! | B96: NDOW | C96: Collaborative Investment Series Trust Anydrus Advantage ETF | D96: {=_FV(A96,"Last trade time",TRUE)} -> 45824.84 | E96: {=_FV(A96,"Price")} -> 25.56 | F96: {=_FV(A96,"Change (%)",TRUE)} -> 0.007886 | G96: {=_FV(A96,"Change")} -> 0.2 | H96: {=_FV(A96,"Open")} -> 25.614 | I96: {=_FV(A96,"Low")} -> 25.56 | J96: {=_FV(A96,"High")} -> 25.614 | K96: {=_FV(A96,"Previous close",TRUE)} -> 25.36 | M96: {=_FV(A96,"52 week low",TRUE)} -> 22.7749 | N96: {=_FV(A96,"52 week high",TRUE)} -> 25.614 | O96: {=_FV(A96,"Volume")} -> 1870 | P96: {=_FV(A96,"Volume average",TRUE)} -> 12240 | Q96: Global Moderately Conservative Allocation | S96: Anydrus | T96: {=_FV(A96,"Expense ratio",TRUE)} -> 0.021 | U96: {=_FV(A96,"Market cap",TRUE)} -> 43302643 | V96: 43302640 | W96: 43302640 | Y96: 2024-05-12 | Z96: 25.37 | AA96: 18.022715 | AB96: 0.013400001 | AC96: 9920 | AE96: 4.5138727 | AF96: 2.6801189 | AI96: 9920 | AJ96: 251846.98 | AL96: 25.537 | AM96: 22.775 | AN96: Low | AO96: {=_FV(A96,"Currency")} -> USD | AP96: {=_FV(A96,"Exchange")} -> CBOE BZX Exchange | AQ96: {=_FV(A96,"Exchange abbreviation",TRUE)} -> BATS | AR96: {=_FV(A96,"Instrument type",TRUE)} -> ETF
A97: #VALUE! | B97: TFPN | C97: Blueprint Chesapeake Multi-Asset Trend ETF | D97: {=_FV(A97,"Last trade time",TRUE)} -> 45824.84 | E97: {=_FV(A97,"Price")} -> 22.61 | F97: {=_FV(A97,"Change (%)",TRUE)} -> 0.014811 | G97: {=_FV(A97,"Change")} -> 0.33 | H97: {=_FV(A97,"Open")} -> 22.53 | I97: {=_FV(A97,"Low")} -> 22.42 | J97: {=_FV(A97,"High")} -> 22.61 | K97: {=_FV(A97,"Previous close",TRUE)} -> 22.28 | M97: {=_FV(A97,"52 week low",TRUE)} -> 20.32 | N97: {=_FV(A97,"52 week high",TRUE)} -> 26.14 | O97: {=_FV(A97,"Volume")} -> 4464 | P97: {=_FV(A97,"Volume average",TRUE)} -> 11302 | Q97: Systematic Trend | R97: Systematic Trend | S97: Blueprint Chesapeake | T97: {=_FV(A97,"Expense ratio",TRUE)} -> 0.0206 | U97: {=_FV(A97,"Market cap",TRUE)} -> 1.1367151e+08 | V97: 113671512 | W97: 113671512 | Y97: 2023-07-10 | Z97: 22.4893 | AA97: 20.727974 | AB97: 0.0105 | AC97: 19952 | AE97: -8.3705864 | AF97: -12.239809 | AI97: 19952 | AJ97: 449119.52 | AL97: 26.14 | AM97: 20.32 | AN97: Low | AO97: {=_FV(A97,"Currency")} -> USD | AP97: {=_FV(A97,"Exchange")} -> NYSE Arca | AQ97: {=_FV(A97,"Exchange abbreviation",TRUE)} -> ARCX | AR97: {=_FV(A97,"Instrument type",TRUE)} -> ETF
A98: #VALUE! | B98: XMPT | C98: VanEck CEF Muni Income ETF | D98: {=_FV(A98,"Last trade time",TRUE)} -> 45824.84 | E98: {=_FV(A98,"Price")} -> 20.8 | F98: {=_FV(A98,"Change (%)",TRUE)} -> 0.0009625 | G98: {=_FV(A98,"Change")} -> 0.02 | H98: {=_FV(A98,"Open")} -> 20.805 | I98: {=_FV(A98,"Low")} -> 20.77 | J98: {=_FV(A98,"High")} -> 20.85 | K98: {=_FV(A98,"Previous close",TRUE)} -> 20.78 | M98: {=_FV(A98,"52 week low",TRUE)} -> 19.73 | N98: {=_FV(A98,"52 week high",TRUE)} -> 23.2065 | O98: {=_FV(A98,"Volume")} -> 38079 | P98: {=_FV(A98,"Volume average",TRUE)} -> 52364 | Q98: High Yield Muni | S98: VanEck | T98: {=_FV(A98,"Expense ratio",TRUE)} -> 0.0198 | U98: {=_FV(A98,"Market cap",TRUE)} -> 1.6725858e+08 | V98: 167258576 | W98: 167258576 | Y98: 2011-07-11 | Z98: 20.66 | AB98: 0.060500003 | AC98: 61450 | AE98: -1.9346639 | AF98: 2.0829218 | AI98: 61450 | AJ98: 1271646.3 | AL98: 23.21 | AM98: 19.73 | AN98: Medium | AO98: {=_FV(A98,"Currency")} -> USD | AP98: {=_FV(A98,"Exchange")} -> CBOE BZX Exchange | AQ98: {=_FV(A98,"Exchange abbreviation",TRUE)} -> BATS | AR98: {=_FV(A98,"Instrument type",TRUE)} -> ETF
A99: #VALUE! | B99: LSEQ | C99: Harbor ETF Trust Harbor Long-Short Equity ETF | D99: {=_FV(A99,"Last trade time",TRUE)} -> 45824.84 | E99: {=_FV(A99,"Price")} -> 27.6383 | F99: {=_FV(A99,"Change (%)",TRUE)} -> 0.014056 | G99: {=_FV(A99,"Change")} -> 0.3831 | H99: {=_FV(A99,"Open")} -> 27.54 | I99: {=_FV(A99,"Low")} -> 27.53 | J99: {=_FV(A99,"High")} -> 27.74 | K99: {=_FV(A99,"Previous close",TRUE)} -> 27.2552 | M99: {=_FV(A99,"52 week low",TRUE)} -> 26.2148 | N99: {=_FV(A99,"52 week high",TRUE)} -> 30.25 | O99: {=_FV(A99,"Volume")} -> 2422 | P99: {=_FV(A99,"Volume average",TRUE)} -> 545 | Q99: Long-Short Equity | S99: Harbor | T99: {=_FV(A99,"Expense ratio",TRUE)} -> 0.0198 | U99: {=_FV(A99,"Market cap",TRUE)} -> 20232723 | V99: 20232722 | W99: 20232722 | Y99: 2023-12-03 | Z99: 28.27728 | AA99: 24.315887 | AB99: 0 | AC99: 1568 | AE99: 2.8357307 | AF99: 2.7640137 | AI99: 1568 | AJ99: 44329.712 | AL99: 30.25 | AM99: 26.215 | AN99: Low | AO99: {=_FV(A99,"Currency")} -> USD | AP99: {=_FV(A99,"Exchange")} -> NYSE Arca | AQ99: {=_FV(A99,"Exchange abbreviation",TRUE)} -> ARCX | AR99: {=_FV(A99,"Instrument type",TRUE)} -> ETF
A100: #VALUE! | B100: SCAP | C100: Infrastructure Capital Small Cap Income ETF | D100: {=_FV(A100,"Last trade time",TRUE)} -> 45824.84 | E100: {=_FV(A100,"Price")} -> 32.7999 | F100: {=_FV(A100,"Change (%)",TRUE)} -> 0.009725 | G100: {=_FV(A100,"Change")} -> 0.3159 | H100: {=_FV(A100,"Open")} -> 32.955 | I100: {=_FV(A100,"Low")} -> 32.7999 | J100: {=_FV(A100,"High")} -> 32.955 | K100: {=_FV(A100,"Previous close",TRUE)} -> 32.484 | M100: {=_FV(A100,"52 week low",TRUE)} -> 27.5 | N100: {=_FV(A100,"52 week high",TRUE)} -> 38.86 | O100: {=_FV(A100,"Volume")} -> 1763 | P100: {=_FV(A100,"Volume average",TRUE)} -> 1600 | Q100: Small Value | S100: InfraCap | T100: {=_FV(A100,"Expense ratio",TRUE)} -> 0.0196 | U100: {=_FV(A100,"Market cap",TRUE)} -> 13433238 | V100: 13433238 | W100: 13433238 | Y100: 2023-12-10 | Z100: 32.6127 | AA100: 15.137759 | AB100: 0.0699 | AC100: 2246 | AE100: -2.4032108 | AF100: 6.9549183 | AI100: 2246 | AJ100: 73363.344 | AL100: 38.86 | AM100: 27.5 | AN100: Low | AO100: {=_FV(A100,"Currency")} -> USD | AP100: {=_FV(A100,"Exchange")} -> NYSE Arca | AQ100: {=_FV(A100,"Exchange abbreviation",TRUE)} -> ARCX | AR100: {=_FV(A100,"Instrument type",TRUE)} -> ETF
...

Sheet ETFs Filtered
A1: Names | B1: Ticker | C1: Asset Class | D1: Sector | E1: Sub Sector | F1: Sub Sub Sector | G1: Strategy Description | H1: Ticker | I1: Last Update | J1: Last Price | K1: 1d% | L1: Net Change | M1: Open | N1: Lo | O1: Hi | P1: Prev Cls | Q1: 52W Lo | R1: 52W Hi | S1: Volume | T1: Avg Volume | U1: Avg $ volume | V1: Expense Ratio (net) | W1: Market Cap
A2: AltShares Merger Arbitrage ETF | B2: ARB | C2: Alternatives | D2: Hedge Fund Replication | Y2: =IF(B2=B1,"XXX","")
A3: PMV Adaptive Risk Parity ETF | B3: ARP | C3: Alternatives | D3: Risk parity | G3: Alternative risk premia multi-factor | H3: #VALUE! | I3: {=_FV(H3,"Last trade time",TRUE)} -> 45824.84 | J3: {=_FV(H3,"Price")} -> 28.46 | K3: {=_FV(H3,"Change (%)",TRUE)} -> 0.0004922 | L3: {=_FV(H3,"Change")} -> 0.014 | M3: {=_FV(H3,"Open")} -> 28.53 | N3: {=_FV(H3,"Low")} -> 28.45 | O3: {=_FV(H3,"High")} -> 28.53 | P3: {=_FV(H3,"Previous close",TRUE)} -> 28.446 | Q3: {=_FV(H3,"52 week low",TRUE)} -> 26.3 | R3: {=_FV(H3,"52 week high",TRUE)} -> 30.22 | S3: {=_FV(H3,"Volume")} -> 12017 | T3: {=_FV(H3,"Volume average",TRUE)} -> 4632 | V3: {=_FV(H3,"Expense ratio",TRUE)} -> 0.0147 | W3: {=_FV(H3,"Market cap",TRUE)} -> 40790904 | Y3: =IF(B3=B2,"XXX","")
A4: VanEck BDC Income ETF | B4: BIZD | C4: Alternatives | D4: Business Development Company | E4: venture capital | G4: buys shares of firms that in turn invest in the debt and equity of mid-sized private firms | H4: #VALUE! | I4: {=_FV(H4,"Last trade time",TRUE)} -> 45824.923 | J4: {=_FV(H4,"Price")} -> 16.05 | K4: {=_FV(H4,"Change (%)",TRUE)} -> -0.004342 | L4: {=_FV(H4,"Change")} -> -0.07 | M4: {=_FV(H4,"Open")} -> 16.15 | N4: {=_FV(H4,"Low")} -> 15.94 | O4: {=_FV(H4,"High")} -> 16.28 | P4: {=_FV(H4,"Previous close",TRUE)} -> 16.12 | Q4: {=_FV(H4,"52 week low",TRUE)} -> 13.5 | R4: {=_FV(H4,"52 week high",TRUE)} -> 17.8565 | S4: {=_FV(H4,"Volume")} -> 1010713 | T4: {=_FV(H4,"Volume average",TRUE)} -> 959469 | V4: {=_FV(H4,"Expense ratio",TRUE)} -> 0.1333 | W4: {=_FV(H4,"Market cap",TRUE)} -> 1.5677835e+09 | Y4: =IF(B4=B3,"XXX","")
A5: AGF U.S. Market Neutral Anti-Beta ETF | B5: BTAL | C5: Alternatives | D5: Equity long short tactical | Y5: =IF(B5=B4,"XXX","")
A6: Blackstone Alternative Multi-Strategy Fund;D | B6: BXMDX | C6: Alternatives | D6: Hedge Fund Replication | G6: BlackRock Multi-Asset Income Fund | H6: #VALUE! | I6: {=_FV(H6,"Last trade time",TRUE)} -> 45824.94 | J6: {=_FV(H6,"Price")} -> 10.84 | K6: {=_FV(H6,"Change (%)",TRUE)} -> -0.0009217 | L6: {=_FV(H6,"Change")} -> -0.01 | M6: {=_FV(H6,"Open")} -> #VALUE! | N6: {=_FV(H6,"Low")} -> #VALUE! | O6: {=_FV(H6,"High")} -> #VALUE! | P6: {=_FV(H6,"Previous close",TRUE)} -> 10.85 | Q6: {=_FV(H6,"52 week low",TRUE)} -> #VALUE! | R6: {=_FV(H6,"52 week high",TRUE)} -> #VALUE! | S6: {=_FV(H6,"Volume")} -> #VALUE! | T6: {=_FV(H6,"Volume average",TRUE)} -> #VALUE! | V6: {=_FV(H6,"Expense ratio",TRUE)} -> 0.0548 | W6: {=_FV(H6,"Market cap",TRUE)} -> #VALUE! | Y6: =IF(B6=B5,"XXX","")
A7: Clough Hedged Equity ETF | B7: CBLS | C7: Alternatives | D7: Equity long short tactical | G7: Attempts to replicate merger arbitrage strategies | H7: #VALUE! | I7: {=_FV(H7,"Last trade time",TRUE)} -> 45824.84 | J7: {=_FV(H7,"Price")} -> 28.373 | K7: {=_FV(H7,"Change (%)",TRUE)} -> 0.00258 | L7: {=_FV(H7,"Change")} -> 0.073 | M7: {=_FV(H7,"Open")} -> 28.35 | N7: {=_FV(H7,"Low")} -> 28.35 | O7: {=_FV(H7,"High")} -> 28.43 | P7: {=_FV(H7,"Previous close",TRUE)} -> 28.3 | Q7: {=_FV(H7,"52 week low",TRUE)} -> 24.1469 | R7: {=_FV(H7,"52 week high",TRUE)} -> 28.83 | S7: {=_FV(H7,"Volume")} -> 28133 | T7: {=_FV(H7,"Volume average",TRUE)} -> 11329 | V7: {=_FV(H7,"Expense ratio",TRUE)} -> 0.0259 | W7: {=_FV(H7,"Market cap",TRUE)} -> 42597655 | Y7: =IF(B7=B6,"XXX","")
A8: Simplify Managed Futures Strategy ETF | B8: CTA | C8: Alternatives | D8: Managed Futures | G8: Managed futures and trend following strategies | H8: #VALUE! | I8: {=_FV(H8,"Last trade time",TRUE)} -> 45824.843 | J8: {=_FV(H8,"Price")} -> 28.3 | K8: {=_FV(H8,"Change (%)",TRUE)} -> 0.013247 | L8: {=_FV(H8,"Change")} -> 0.37 | M8: {=_FV(H8,"Open")} -> 28.03 | N8: {=_FV(H8,"Low")} -> 28.02 | O8: {=_FV(H8,"High")} -> 28.3 | P8: {=_FV(H8,"Previous close",TRUE)} -> 27.93 | Q8: {=_FV(H8,"52 week low",TRUE)} -> 25.6601 | R8: {=_FV(H8,"52 week high",TRUE)} -> 30.213 | S8: {=_FV(H8,"Volume")} -> 254045 | T8: {=_FV(H8,"Volume average",TRUE)} -> 447032 | V8: {=_FV(H8,"Expense ratio",TRUE)} -> 0.0076 | W8: {=_FV(H8,"Market cap",TRUE)} -> 1.0721217e+09 | Y8: =IF(B8=B7,"XXX","")
A9: Simplify Managed Futures Strategy ETF | B9: CTA | C9: Alternatives | D9: Managed Future | Y9: =IF(B9=B8,"XXX","") -> XXX
A10: iMGP DBi Managed Futures Strategy ETF | B10: DBMF | C10: Alternatives | D10: Managed Futures | G10: Managed futures multi-strategy approach | H10: #VALUE! | I10: {=_FV(H10,"Last trade time",TRUE)} -> 45824.918 | J10: {=_FV(H10,"Price")} -> 25.63 | K10: {=_FV(H10,"Change (%)",TRUE)} -> -0.002336 | L10: {=_FV(H10,"Change")} -> -0.06 | M10: {=_FV(H10,"Open")} -> 25.72 | N10: {=_FV(H10,"Low")} -> 25.625 | O10: {=_FV(H10,"High")} -> 25.72 | P10: {=_FV(H10,"Previous close",TRUE)} -> 25.69 | Q10: {=_FV(H10,"52 week low",TRUE)} -> 24.5201 | R10: {=_FV(H10,"52 week high",TRUE)} -> 30.6299 | S10: {=_FV(H10,"Volume")} -> 483001 | T10: {=_FV(H10,"Volume average",TRUE)} -> 354904 | V10: {=_FV(H10,"Expense ratio",TRUE)} -> 0.0085 | W10: {=_FV(H10,"Market cap",TRUE)} -> 1.193e+09 | Y10: =IF(B10=B9,"XXX","")
A11: iMGP DBi Managed Futures Strategy ETF | B11: DBMF | C11: Alternatives | D11: Managed Future | Y11: =IF(B11=B10,"XXX","") -> XXX
A12: First Trust Managed Futures Strategy Fund | B12: FMF | C12: Alternatives | D12: Managed Futures | G12: Multi-manager alternative strategies | H12: #VALUE! | I12: {=_FV(H12,"Last trade time",TRUE)} -> 45824.84 | J12: {=_FV(H12,"Price")} -> 45.9935 | K12: {=_FV(H12,"Change (%)",TRUE)} -> 0.009028 | L12: {=_FV(H12,"Change")} -> 0.4115 | M12: {=_FV(H12,"Open")} -> 45.63 | N12: {=_FV(H12,"Low")} -> 45.5 | O12: {=_FV(H12,"High")} -> 46.16 | P12: {=_FV(H12,"Previous close",TRUE)} -> 45.582 | Q12: {=_FV(H12,"52 week low",TRUE)} -> 44.0788 | R12: {=_FV(H12,"52 week high",TRUE)} -> 49.9099 | S12: {=_FV(H12,"Volume")} -> 29934 | T12: {=_FV(H12,"Volume average",TRUE)} -> 20878 | V12: {=_FV(H12,"Expense ratio",TRUE)} -> 0.0095 | W12: {=_FV(H12,"Market cap",TRUE)} -> 1.5317759e+08 | Y12: =IF(B12=B11,"XXX","")
A13: Formidable ETF | B13: FORH | C13: Alternatives | D13: Hedge Fund Replication | G13: Long-short equity strategy targeting value stocks | H13: #VALUE! | I13: {=_FV(H13,"Last trade time",TRUE)} -> 45824.84 | J13: {=_FV(H13,"Price")} -> 22.7949 | K13: {=_FV(H13,"Change (%)",TRUE)} -> -0.00218 | L13: {=_FV(H13,"Change")} -> -0.0498 | M13: {=_FV(H13,"Open")} -> 22.7901 | N13: {=_FV(H13,"Low")} -> 22.7901 | O13: {=_FV(H13,"High")} -> 22.7949 | P13: {=_FV(H13,"Previous close",TRUE)} -> 22.8447 | Q13: {=_FV(H13,"52 week low",TRUE)} -> 19.13 | R13: {=_FV(H13,"52 week high",TRUE)} -> 23.8 | S13: {=_FV(H13,"Volume")} -> 291 | T13: {=_FV(H13,"Volume average",TRUE)} -> 2526 | V13: {=_FV(H13,"Expense ratio",TRUE)} -> 0.0119 | W13: {=_FV(H13,"Market cap",TRUE)} -> 19625360 | Y13: =IF(B13=B12,"XXX","")
A14: Greenlight Capital Re, Ltd. | B14: GLRE | C14: Alternatives | D14: Hedge Fund Replication | Y14: =IF(B14=B13,"XXX","")
A15: ProShares Hedge Replication ETF | B15: HDG | C15: Alternatives | D15: Hedge Fund Replication | G15: Currency hedged international equity exposure | H15: #VALUE! | I15: {=_FV(H15,"Last trade time",TRUE)} -> 45824.84 | J15: {=_FV(H15,"Price")} -> 49.5079 | K15: {=_FV(H15,"Change (%)",TRUE)} -> 0.001704 | L15: {=_FV(H15,"Change")} -> 0.0842 | M15: {=_FV(H15,"Open")} -> 49.44 | N15: {=_FV(H15,"Low")} -> 49.44 | O15: {=_FV(H15,"High")} -> 49.5079 | P15: {=_FV(H15,"Previous close",TRUE)} -> 49.4237 | Q15: {=_FV(H15,"52 week low",TRUE)} -> 46.28 | R15: {=_FV(H15,"52 week high",TRUE)} -> 50.6981 | S15: {=_FV(H15,"Volume")} -> 442 | T15: {=_FV(H15,"Volume average",TRUE)} -> 844 | V15: {=_FV(H15,"Expense ratio",TRUE)} -> 0.0095 | W15: {=_FV(H15,"Market cap",TRUE)} -> 24418944 | Y15: =IF(B15=B14,"XXX","")
A16: Int. Hedged Equity | B16: HEDJ | C16: Alternatives | D16: Equity long short tactical | G16: Euro hedged European equity index | H16: #VALUE! | I16: {=_FV(H16,"Last trade time",TRUE)} -> 45824.84 | J16: {=_FV(H16,"Price")} -> 49.03 | K16: {=_FV(H16,"Change (%)",TRUE)} -> 0.009471 | L16: {=_FV(H16,"Change")} -> 0.46 | M16: {=_FV(H16,"Open")} -> 48.85 | N16: {=_FV(H16,"Low")} -> 48.85 | O16: {=_FV(H16,"High")} -> 49.23 | P16: {=_FV(H16,"Previous close",TRUE)} -> 48.57 | Q16: {=_FV(H16,"52 week low",TRUE)} -> 40.83 | R16: {=_FV(H16,"52 week high",TRUE)} -> 50.78 | S16: {=_FV(H16,"Volume")} -> 61815 | T16: {=_FV(H16,"Volume average",TRUE)} -> 152308 | V16: {=_FV(H16,"Expense ratio",TRUE)} -> 0.0058 | W16: {=_FV(H16,"Market cap",TRUE)} -> 1.7761079e+09 | Y16: =IF(B16=B15,"XXX","")
A17: Unlimited HFND Multi-Strategy Return Tracker ETF | B17: HFND | C17: Alternatives | D17: Hedge Fund Replication | Y17: =IF(B17=B16,"XXX","")
A18: HERCULES CAPITAL, INC. (XNYS:HTGC) | B18: HTGC | C18: Alternatives | D18: Business Development Company | E18: Broad Markets | G18: specializing in providing private equity, venture debt, and growth capital to privately held venture capital-backed companies at all stages of development | H18: #VALUE! | I18: {=_FV(H18,"Last trade time",TRUE)} -> 45824.855 | J18: {=_FV(H18,"Price")} -> 17.87 | K18: {=_FV(H18,"Change (%)",TRUE)} -> -0.006118 | L18: {=_FV(H18,"Change")} -> -0.11 | M18: {=_FV(H18,"Open")} -> 18.12 | N18: {=_FV(H18,"Low")} -> 17.8335 | O18: {=_FV(H18,"High")} -> 18.21 | P18: {=_FV(H18,"Previous close",TRUE)} -> 17.98 | Q18: {=_FV(H18,"52 week low",TRUE)} -> 15.65 | R18: {=_FV(H18,"52 week high",TRUE)} -> 22.04 | S18: {=_FV(H18,"Volume")} -> 856414 | T18: {=_FV(H18,"Volume average",TRUE)} -> 1358314 | V18: {=_FV(H18,"Expense ratio",TRUE)} -> #VALUE! | W18: {=_FV(H18,"Market cap",TRUE)} -> 3134864407 | Y18: =IF(B18=B17,"XXX","")
A19: Capitol Series Trust Hull Tactical US ETF | B19: HTUS | C19: Alternatives | D19: Equity long short tactical | G19: Hedged equity strategy with downside protection | H19: #VALUE! | I19: {=_FV(H19,"Last trade time",TRUE)} -> 45824.84 | J19: {=_FV(H19,"Price")} -> 38.7693 | K19: {=_FV(H19,"Change (%)",TRUE)} -> 0.002309 | L19: {=_FV(H19,"Change")} -> 0.0893 | M19: {=_FV(H19,"Open")} -> 38.89 | N19: {=_FV(H19,"Low")} -> 38.7693 | O19: {=_FV(H19,"High")} -> 38.89 | P19: {=_FV(H19,"Previous close",TRUE)} -> 38.68 | Q19: {=_FV(H19,"52 week low",TRUE)} -> 27.5 | R19: {=_FV(H19,"52 week high",TRUE)} -> 47.73 | S19: {=_FV(H19,"Volume")} -> 3601 | T19: {=_FV(H19,"Volume average",TRUE)} -> 12667 | V19: {=_FV(H19,"Expense ratio",TRUE)} -> 0.0096 | W19: {=_FV(H19,"Market cap",TRUE)} -> 1.1863005e+08 | Y19: =IF(B19=B18,"XXX","")
A20: Vest 2 Year Interest Rate Hedge ETF | B20: HYKE | C20: Alternatives | D20: Interest Rate and Inflation Hedge | G20: High yield corporate bond ETF | H20: #VALUE! | I20: {=_FV(H20,"Last trade time",TRUE)} -> 45824.84 | J20: {=_FV(H20,"Price")} -> 25.8967 | K20: {=_FV(H20,"Change (%)",TRUE)} -> 0.004722 | L20: {=_FV(H20,"Change")} -> 0.1217 | M20: {=_FV(H20,"Open")} -> 25.8967 | N20: {=_FV(H20,"Low")} -> 25.8967 | O20: {=_FV(H20,"High")} -> 25.8967 | P20: {=_FV(H20,"Previous close",TRUE)} -> 25.775 | Q20: {=_FV(H20,"52 week low",TRUE)} -> 23.6494 | R20: {=_FV(H20,"52 week high",TRUE)} -> 29.8452 | S20: {=_FV(H20,"Volume")} -> 5 | T20: {=_FV(H20,"Volume average",TRUE)} -> 4 | V20: {=_FV(H20,"Expense ratio",TRUE)} -> 0.009 | W20: {=_FV(H20,"Market cap",TRUE)} -> 1271182.5 | Y20: =IF(B20=B19,"XXX","")
A21: Icahn Enterprises L.P. | B21: IEP | C21: Alternatives | D21: Hedge Fund Replication | Y21: =IF(B21=B20,"XXX","")
A22: KFA Mount Lucas Managed Futures Index Strategy ETF | B22: KMLM | C22: Alternatives | D22: Managed Futures | G22: Alternative risk premia capture | H22: #VALUE! | I22: {=_FV(H22,"Last trade time",TRUE)} -> 45824.84 | J22: {=_FV(H22,"Price")} -> 26.01 | K22: {=_FV(H22,"Change (%)",TRUE)} -> -0.002684 | L22: {=_FV(H22,"Change")} -> -0.07 | M22: {=_FV(H22,"Open")} -> 26.12 | N22: {=_FV(H22,"Low")} -> 26.01 | O22: {=_FV(H22,"High")} -> 26.3 | P22: {=_FV(H22,"Previous close",TRUE)} -> 26.08 | Q22: {=_FV(H22,"52 week low",TRUE)} -> 25.91 | R22: {=_FV(H22,"52 week high",TRUE)} -> 30.19 | S22: {=_FV(H22,"Volume")} -> 18115 | T22: {=_FV(H22,"Volume average",TRUE)} -> 70652 | V22: {=_FV(H22,"Expense ratio",TRUE)} -> 0.009 | W22: {=_FV(H22,"Market cap",TRUE)} -> 1.9256577e+08 | Y22: =IF(B22=B21,"XXX","")
A23: First Trust Multi-Strategy Alternative ETF | B23: LALT | C23: Alternatives | D23: Hedge Fund Replication | Y23: =IF(B23=B22,"XXX","")
A24: ProShares Global Listed Private Equity ETF | B24: PEX | C24: Alternatives | D24: Business Development Company | G24: ProShares Global Listed Private Equity | H24: #VALUE! | I24: {=_FV(H24,"Last trade time",TRUE)} -> 45824.863 | J24: {=_FV(H24,"Price")} -> 27.6575 | K24: {=_FV(H24,"Change (%)",TRUE)} -> -0.003333 | L24: {=_FV(H24,"Change")} -> -0.0925 | M24: {=_FV(H24,"Open")} -> 28.14 | N24: {=_FV(H24,"Low")} -> 27.6575 | O24: {=_FV(H24,"High")} -> 28.14 | P24: {=_FV(H24,"Previous close",TRUE)} -> 27.75 | Q24: {=_FV(H24,"52 week low",TRUE)} -> 23.46 | R24: {=_FV(H24,"52 week high",TRUE)} -> 30.34 | S24: {=_FV(H24,"Volume")} -> 1523 | T24: {=_FV(H24,"Volume average",TRUE)} -> 3291 | V24: {=_FV(H24,"Expense ratio",TRUE)} -> 0.006 | W24: {=_FV(H24,"Market cap",TRUE)} -> 13538777 | Y24: =IF(B24=B23,"XXX","")
A25: Simplify Interest Rate Hedge ETF | B25: PFIX | C25: Alternatives | D25: Interest Rate and Inflation Hedge | G25: Inflation-protected securities with variable duration | H25: #VALUE! | I25: {=_FV(H25,"Last trade time",TRUE)} -> 45824.841 | J25: {=_FV(H25,"Price")} -> 59.5 | K25: {=_FV(H25,"Change (%)",TRUE)} -> 0.048828 | L25: {=_FV(H25,"Change")} -> 2.77 | M25: {=_FV(H25,"Open")} -> 57.12 | N25: {=_FV(H25,"Low")} -> 56.65 | O25: {=_FV(H25,"High")} -> 59.5 | P25: {=_FV(H25,"Previous close",TRUE)} -> 56.73 | Q25: {=_FV(H25,"52 week low",TRUE)} -> 37 | R25: {=_FV(H25,"52 week high",TRUE)} -> 65.1521 | S25: {=_FV(H25,"Volume")} -> 269712 | T25: {=_FV(H25,"Volume average",TRUE)} -> 177127 | V25: {=_FV(H25,"Expense ratio",TRUE)} -> 0.005 | W25: {=_FV(H25,"Market cap",TRUE)} -> 1.6781209e+08 | Y25: =IF(B25=B24,"XXX","")
A26: Pershing Square Holdings Ltd. | B26: PSH | C26: Alternatives | D26: Hedge Fund Replication | Y26: =IF(B26=B25,"XXX","")
A27: NYLI Hedge Multi-Strategy Tracker ETF | B27: QAI | C27: Alternatives | D27: Hedge Fund Replication | G27: Multi-alternative strategies replication | H27: #VALUE! | I27: {=_FV(H27,"Last trade time",TRUE)} -> 45824.84 | J27: {=_FV(H27,"Price")} -> 32.09 | K27: {=_FV(H27,"Change (%)",TRUE)} -> 0.005011 | L27: {=_FV(H27,"Change")} -> 0.16 | M27: {=_FV(H27,"Open")} -> 32.01 | N27: {=_FV(H27,"Low")} -> 32.01 | O27: {=_FV(H27,"High")} -> 32.1 | P27: {=_FV(H27,"Previous close",TRUE)} -> 31.93 | Q27: {=_FV(H27,"52 week low",TRUE)} -> 29.57 | R27: {=_FV(H27,"52 week high",TRUE)} -> 32.7959 | S27: {=_FV(H27,"Volume")} -> 324450 | T27: {=_FV(H27,"Volume average",TRUE)} -> 65537 | V27: {=_FV(H27,"Expense ratio",TRUE)} -> 0.0091 | W27: {=_FV(H27,"Market cap",TRUE)} -> 6.9695524e+08 | Y27: =IF(B27=B26,"XXX","")
A28: Global X Interest Rate Hedge ETF | B28: RATE | C28: Alternatives | D28: Interest Rate and Inflation Hedge | G28: Interest rate hedged high yield bonds | H28: #VALUE! | I28: {=_FV(H28,"Last trade time",TRUE)} -> 45824.84 | J28: {=_FV(H28,"Price")} -> 18.5653 | K28: {=_FV(H28,"Change (%)",TRUE)} -> 0.004322 | L28: {=_FV(H28,"Change")} -> 0.0799 | M28: {=_FV(H28,"Open")} -> 18.5653 | N28: {=_FV(H28,"Low")} -> 18.5653 | O28: {=_FV(H28,"High")} -> 18.5653 | P28: {=_FV(H28,"Previous close",TRUE)} -> 18.4854 | Q28: {=_FV(H28,"52 week low",TRUE)} -> 17.1192 | R28: {=_FV(H28,"52 week high",TRUE)} -> 21.62 | S28: {=_FV(H28,"Volume")} -> 266 | T28: {=_FV(H28,"Volume average",TRUE)} -> 1243 | V28: {=_FV(H28,"Expense ratio",TRUE)} -> 0.0045 | W28: {=_FV(H28,"Market cap",TRUE)} -> 2600296.1 | Y28: =IF(B28=B27,"XXX","")
A29: ProShares Inflation Expectations ETF | B29: RINF | C29: Alternatives | D29: Interest Rate and Inflation Hedge | G29: Real return asset allocation for inflation protection | H29: #VALUE! | I29: {=_FV(H29,"Last trade time",TRUE)} -> 45824.84 | J29: {=_FV(H29,"Price")} -> 33.0704 | K29: {=_FV(H29,"Change (%)",TRUE)} -> 0.004703 | L29: {=_FV(H29,"Change")} -> 0.1548 | M29: {=_FV(H29,"Open")} -> 32.9 | N29: {=_FV(H29,"Low")} -> 32.9 | O29: {=_FV(H29,"High")} -> 33.0704 | P29: {=_FV(H29,"Previous close",TRUE)} -> 32.9156 | Q29: {=_FV(H29,"52 week low",TRUE)} -> 30.91 | R29: {=_FV(H29,"52 week high",TRUE)} -> 33.67 | S29: {=_FV(H29,"Volume")} -> 864 | T29: {=_FV(H29,"Volume average",TRUE)} -> 11679 | V29: {=_FV(H29,"Expense ratio",TRUE)} -> 0.003 | W29: {=_FV(H29,"Market cap",TRUE)} -> 26182845 | Y29: =IF(B29=#REF!,"XXX","") -> #REF!
A30: SPDR SSgA Multi-Asset Real Return ETF | B30: RLY | C30: Alternatives | D30: Risk parity | G30: Strategic beta equity factor rotation | H30: #VALUE! | I30: {=_FV(H30,"Last trade time",TRUE)} -> 45824.84 | J30: {=_FV(H30,"Price")} -> 29.56 | K30: {=_FV(H30,"Change (%)",TRUE)} -> 0.001355 | L30: {=_FV(H30,"Change")} -> 0.04 | M30: {=_FV(H30,"Open")} -> 29.47 | N30: {=_FV(H30,"Low")} -> 29.47 | O30: {=_FV(H30,"High")} -> 29.69 | P30: {=_FV(H30,"Previous close",TRUE)} -> 29.52 | Q30: {=_FV(H30,"52 week low",TRUE)} -> 25.63 | R30: {=_FV(H30,"52 week high",TRUE)} -> 29.69 | S30: {=_FV(H30,"Volume")} -> 40987 | T30: {=_FV(H30,"Volume average",TRUE)} -> 67902 | V30: {=_FV(H30,"Expense ratio",TRUE)} -> 0.005 | W30: {=_FV(H30,"Market cap",TRUE)} -> 4.859269e+08 | Y30: =IF(B30=B29,"XXX","")
A31: Wheat | B31: WEAT | C31: Commodities | D31: Agricultural Commodities | G31: Wheat futures tracking | H31: #VALUE! | I31: {=_FV(H31,"Last trade time",TRUE)} -> 45824.915 | J31: {=_FV(H31,"Price")} -> 4.56 | K31: {=_FV(H31,"Change (%)",TRUE)} -> -0.012987 | L31: {=_FV(H31,"Change")} -> -0.06 | M31: {=_FV(H31,"Open")} -> 4.59 | N31: {=_FV(H31,"Low")} -> 4.5245 | O31: {=_FV(H31,"High")} -> 4.59 | P31: {=_FV(H31,"Previous close",TRUE)} -> 4.62 | Q31: {=_FV(H31,"52 week low",TRUE)} -> 4.33 | R31: {=_FV(H31,"52 week high",TRUE)} -> 5.63 | S31: {=_FV(H31,"Volume")} -> 524368 | T31: {=_FV(H31,"Volume average",TRUE)} -> 731519 | V31: {=_FV(H31,"Expense ratio",TRUE)} -> 0.032 | W31: {=_FV(H31,"Market cap",TRUE)} -> 1.1958271e+08 | Y31: =IF(B31=B30,"XXX","")
A32: Soybeans | B32: SOYB | C32: Commodities | D32: Agricultural Commodities | G32: Soybean futures exposure | H32: #VALUE! | I32: {=_FV(H32,"Last trade time",TRUE)} -> 45824.84 | J32: {=_FV(H32,"Price")} -> 22.38 | K32: {=_FV(H32,"Change (%)",TRUE)} -> 0.004038 | L32: {=_FV(H32,"Change")} -> 0.09 | M32: {=_FV(H32,"Open")} -> 22.41 | N32: {=_FV(H32,"Low")} -> 22.26 | O32: {=_FV(H32,"High")} -> 22.51 | P32: {=_FV(H32,"Previous close",TRUE)} -> 22.29 | Q32: {=_FV(H32,"52 week low",TRUE)} -> 20.2 | R32: {=_FV(H32,"52 week high",TRUE)} -> 24.31 | S32: {=_FV(H32,"Volume")} -> 133771 | T32: {=_FV(H32,"Volume average",TRUE)} -> 27539 | V32: {=_FV(H32,"Expense ratio",TRUE)} -> 0.0356 | W32: {=_FV(H32,"Market cap",TRUE)} -> 25438435 | Y32: =IF(B32=B31,"XXX","")
A33: Corn | B33: CORN | C33: Commodities | D33: Agricultural Commodities | G33: Corn futures tracking | H33: #VALUE! | I33: {=_FV(H33,"Last trade time",TRUE)} -> 45824.903 | J33: {=_FV(H33,"Price")} -> 18.09 | K33: {=_FV(H33,"Change (%)",TRUE)} -> -0.016313 | L33: {=_FV(H33,"Change")} -> -0.3 | M33: {=_FV(H33,"Open")} -> 18.23 | N33: {=_FV(H33,"Low")} -> 18.06 | O33: {=_FV(H33,"High")} -> 18.24 | P33: {=_FV(H33,"Previous close",TRUE)} -> 18.39 | Q33: {=_FV(H33,"52 week low",TRUE)} -> 17.021 | R33: {=_FV(H33,"52 week high",TRUE)} -> 20.69 | S33: {=_FV(H33,"Volume")} -> 62683 | T33: {=_FV(H33,"Volume average",TRUE)} -> 56653 | V33: {=_FV(H33,"Expense ratio",TRUE)} -> 0.0327 | W33: {=_FV(H33,"Market cap",TRUE)} -> 48890412 | Y33: =IF(B33=B32,"XXX","")
A34: Sugar | B34: CANE | C34: Commodities | D34: Agricultural Commodities | G34: Sugar futures exposure | H34: #VALUE! | I34: {=_FV(H34,"Last trade time",TRUE)} -> 45824.84 | J34: {=_FV(H34,"Price")} -> 11.26 | K34: {=_FV(H34,"Change (%)",TRUE)} -> 0.02925 | L34: {=_FV(H34,"Change")} -> 0.32 | M34: {=_FV(H34,"Open")} -> 10.94 | N34: {=_FV(H34,"Low")} -> 10.92 | O34: {=_FV(H34,"High")} -> 11.27 | P34: {=_FV(H34,"Previous close",TRUE)} -> 10.94 | Q34: {=_FV(H34,"52 week low",TRUE)} -> 10.77 | R34: {=_FV(H34,"52 week high",TRUE)} -> 13.73 | S34: {=_FV(H34,"Volume")} -> 44352 | T34: {=_FV(H34,"Volume average",TRUE)} -> 25500 | V34: {=_FV(H34,"Expense ratio",TRUE)} -> 0.0442 | W34: {=_FV(H34,"Market cap",TRUE)} -> 10748977
A35: WT Coffee (XLON:COFF) | B35: COFF | C35: Commodities | D35: Agricultural Commodities | E35: Coffee | G35: Coffee futures exposure | H35: #VALUE! | I35: {=_FV(H35,"Last trade time",TRUE)} -> 45824.646 | J35: {=_FV(H35,"Price")} -> 61.255 | K35: {=_FV(H35,"Change (%)",TRUE)} -> -0.008177 | L35: {=_FV(H35,"Change")} -> -0.505 | M35: {=_FV(H35,"Open")} -> 62.53 | N35: {=_FV(H35,"Low")} -> 61.05 | O35: {=_FV(H35,"High")} -> 62.53 | P35: {=_FV(H35,"Previous close",TRUE)} -> 61.76 | Q35: {=_FV(H35,"52 week low",TRUE)} -> 35.85 | R35: {=_FV(H35,"52 week high",TRUE)} -> 74.9 | S35: {=_FV(H35,"Volume")} -> 3177 | T35: {=_FV(H35,"Volume average",TRUE)} -> #VALUE! | V35: {=_FV(H35,"Expense ratio",TRUE)} -> 0.0099 | W35: {=_FV(H35,"Market cap",TRUE)} -> 39476584
A36: Sensys Gatso Group AB (XSTO:SGG) | B36: SGG | C36: Commodities | D36: Agricultural Commodities | E36: Sugar | G36: iPath Bloomberg Sugar Subindex | H36: #VALUE! | I36: {=_FV(H36,"Last trade time",TRUE)} -> 45824.667 | J36: {=_FV(H36,"Price")} -> 43.7 | K36: {=_FV(H36,"Change (%)",TRUE)} -> 0.028235 | L36: {=_FV(H36,"Change")} -> 1.2 | M36: {=_FV(H36,"Open")} -> 42.1 | N36: {=_FV(H36,"Low")} -> 40.9 | O36: {=_FV(H36,"High")} -> 43.8 | P36: {=_FV(H36,"Previous close",TRUE)} -> 42.5 | Q36: {=_FV(H36,"52 week low",TRUE)} -> 0.78 | R36: {=_FV(H36,"52 week high",TRUE)} -> 88 | S36: {=_FV(H36,"Volume")} -> 10164 | T36: {=_FV(H36,"Volume average",TRUE)} -> 4970 | V36: {=_FV(H36,"Expense ratio",TRUE)} -> #VALUE! | W36: {=_FV(H36,"Market cap",TRUE)} -> 490040200 | Y36: =IF(B36=B33,"XXX","")
A37: iShares Global Agri Idx ETF (NEOE:COW) | B37: COW | C37: Commodities | D37: Agricultural Commodities | G37: iPath Bloomberg Livestock Subindex | H37: #VALUE! | I37: {=_FV(H37,"Last trade time",TRUE)} -> 45824.828 | J37: {=_FV(H37,"Price")} -> 68.54 | K37: {=_FV(H37,"Change (%)",TRUE)} -> 0.015708 | L37: {=_FV(H37,"Change")} -> 1.06 | M37: {=_FV(H37,"Open")} -> 68 | N37: {=_FV(H37,"Low")} -> 68 | O37: {=_FV(H37,"High")} -> 68.58 | P37: {=_FV(H37,"Previous close",TRUE)} -> 67.48 | Q37: {=_FV(H37,"52 week low",TRUE)} -> 58 | R37: {=_FV(H37,"52 week high",TRUE)} -> 69.48 | S37: {=_FV(H37,"Volume")} -> 2889 | T37: {=_FV(H37,"Volume average",TRUE)} -> #VALUE! | V37: {=_FV(H37,"Expense ratio",TRUE)} -> 0.0071 | W37: {=_FV(H37,"Market cap",TRUE)} -> 2.5633935e+08 | Y37: =IF(B37=B36,"XXX","")
A38: NIB HOLDINGS LTD (XASX:NHF) | B38: NIB | C38: Commodities | D38: Agricultural Commodities | E38: Cocoa | G38: iPath Bloomberg Cocoa Subindex | H38: #VALUE! | I38: {=_FV(H38,"Last trade time",TRUE)} -> 45824.375 | J38: {=_FV(H38,"Price")} -> 6.5 | K38: {=_FV(H38,"Change (%)",TRUE)} -> -0.009146 | L38: {=_FV(H38,"Change")} -> -0.06 | M38: {=_FV(H38,"Open")} -> 6.57 | N38: {=_FV(H38,"Low")} -> 6.49 | O38: {=_FV(H38,"High")} -> 6.58 | P38: {=_FV(H38,"Previous close",TRUE)} -> 6.56 | Q38: {=_FV(H38,"52 week low",TRUE)} -> 5.36 | R38: {=_FV(H38,"52 week high",TRUE)} -> 7.6 | S38: {=_FV(H38,"Volume")} -> 1021949 | T38: {=_FV(H38,"Volume average",TRUE)} -> 1145340 | V38: {=_FV(H38,"Expense ratio",TRUE)} -> #VALUE! | W38: {=_FV(H38,"Market cap",TRUE)} -> 3194832000 | Y38: =IF(B38=B37,"XXX","")
A39: Teucrium Agricultural Fund ETV | B39: TAGS | C39: Commodities | D39: Agricultural Commodities | G39: Teucrium Agricultural Fund | H39: #VALUE! | I39: {=_FV(H39,"Last trade time",TRUE)} -> 45824.84 | J39: {=_FV(H39,"Price")} -> 24.7877 | K39: {=_FV(H39,"Change (%)",TRUE)} -> 0.001726 | L39: {=_FV(H39,"Change")} -> 0.0427 | M39: {=_FV(H39,"Open")} -> 24.5447 | N39: {=_FV(H39,"Low")} -> 24.5447 | O39: {=_FV(H39,"High")} -> 24.7877 | P39: {=_FV(H39,"Previous close",TRUE)} -> 24.745 | Q39: {=_FV(H39,"52 week low",TRUE)} -> 24.19 | R39: {=_FV(H39,"52 week high",TRUE)} -> 27.37 | S39: {=_FV(H39,"Volume")} -> 1647 | T39: {=_FV(H39,"Volume average",TRUE)} -> 2228 | V39: {=_FV(H39,"Expense ratio",TRUE)} -> 0.0009 | W39: {=_FV(H39,"Market cap",TRUE)} -> 9825624.9 | Y39: =IF(B39=B38,"XXX","")
A40: Base metals | B40: DBB | C40: Commodities | D40: Base metals | E40: Broad Markets | G40: Base metals futures basket | H40: #VALUE! | I40: {=_FV(H40,"Last trade time",TRUE)} -> 45824.84 | J40: {=_FV(H40,"Price")} -> 18.76 | K40: {=_FV(H40,"Change (%)",TRUE)} -> 0.012959 | L40: {=_FV(H40,"Change")} -> 0.24 | M40: {=_FV(H40,"Open")} -> 18.71 | N40: {=_FV(H40,"Low")} -> 18.6868 | O40: {=_FV(H40,"High")} -> 18.78 | P40: {=_FV(H40,"Previous close",TRUE)} -> 18.52 | Q40: {=_FV(H40,"52 week low",TRUE)} -> 17.125 | R40: {=_FV(H40,"52 week high",TRUE)} -> 21.45 | S40: {=_FV(H40,"Volume")} -> 18849 | T40: {=_FV(H40,"Volume average",TRUE)} -> 54946 | V40: {=_FV(H40,"Expense ratio",TRUE)} -> 0.0075 | W40: {=_FV(H40,"Market cap",TRUE)} -> 1.0537214e+08 | Y40: =IF(B40=B39,"XXX","")
A41: Diversified Commodities - Bloomberg Commodities Index | B41: BCI | C41: Commodities | D41: Commodity Basket | G41: Commodity index exposure | H41: #VALUE! | I41: {=_FV(H41,"Last trade time",TRUE)} -> 45824.84 | J41: {=_FV(H41,"Price")} -> 21.46 | K41: {=_FV(H41,"Change (%)",TRUE)} -> 0.003273 | L41: {=_FV(H41,"Change")} -> 0.07 | M41: {=_FV(H41,"Open")} -> 21.44 | N41: {=_FV(H41,"Low")} -> 21.2346 | O41: {=_FV(H41,"High")} -> 21.485 | P41: {=_FV(H41,"Previous close",TRUE)} -> 21.39 | Q41: {=_FV(H41,"52 week low",TRUE)} -> 18.8 | R41: {=_FV(H41,"52 week high",TRUE)} -> 21.67 | S41: {=_FV(H41,"Volume")} -> 241666 | T41: {=_FV(H41,"Volume average",TRUE)} -> 580562 | V41: {=_FV(H41,"Expense ratio",TRUE)} -> 0.0026 | W41: {=_FV(H41,"Market cap",TRUE)} -> 1.4198006e+09 | Y41: =IF(B41=B40,"XXX","")
A42: Diversified Commodities - Goldman Sachs Commodities Index | B42: GSG | C42: Commodities | D42: Commodity Basket | G42: Broad commodities index | H42: #VALUE! | I42: {=_FV(H42,"Last trade time",TRUE)} -> 45824.911 | J42: {=_FV(H42,"Price")} -> 22.99 | K42: {=_FV(H42,"Change (%)",TRUE)} -> -0.00217 | L42: {=_FV(H42,"Change")} -> -0.05 | M42: {=_FV(H42,"Open")} -> 22.97 | N42: {=_FV(H42,"Low")} -> 22.59 | O42: {=_FV(H42,"High")} -> 23.05 | P42: {=_FV(H42,"Previous close",TRUE)} -> 23.04 | Q42: {=_FV(H42,"52 week low",TRUE)} -> 19.73 | R42: {=_FV(H42,"52 week high",TRUE)} -> 23.32 | S42: {=_FV(H42,"Volume")} -> 1136165 | T42: {=_FV(H42,"Volume average",TRUE)} -> 436167 | V42: {=_FV(H42,"Expense ratio",TRUE)} -> 0.0083 | W42: {=_FV(H42,"Market cap",TRUE)} -> 9.0903364e+08 | Y42: =IF(B42=B41,"XXX","")
A43: Agricultural Commodities | B43: DBA | C43: Commodities | D43: Commodity Basket | G43: Agricultural commodity futures | H43: #VALUE! | I43: {=_FV(H43,"Last trade time",TRUE)} -> 45824.849 | J43: {=_FV(H43,"Price")} -> 27.17 | K43: {=_FV(H43,"Change (%)",TRUE)} -> 0.007789 | L43: {=_FV(H43,"Change")} -> 0.21 | M43: {=_FV(H43,"Open")} -> 26.96 | N43: {=_FV(H43,"Low")} -> 26.91 | O43: {=_FV(H43,"High")} -> 27.1999 | P43: {=_FV(H43,"Previous close",TRUE)} -> 26.96 | Q43: {=_FV(H43,"52 week low",TRUE)} -> 22.79 | R43: {=_FV(H43,"52 week high",TRUE)} -> 28.485 | S43: {=_FV(H43,"Volume")} -> 152789 | T43: {=_FV(H43,"Volume average",TRUE)} -> 262860 | V43: {=_FV(H43,"Expense ratio",TRUE)} -> 0.0088 | W43: {=_FV(H43,"Market cap",TRUE)} -> 8.3520873e+08 | Y43: =IF(B43=B42,"XXX","")
A44: Energy | B44: DBE | C44: Commodities | D44: Commodity Basket | G44: Energy commodity futures | H44: #VALUE! | I44: {=_FV(H44,"Last trade time",TRUE)} -> 45824.84 | J44: {=_FV(H44,"Price")} -> 19.72 | K44: {=_FV(H44,"Change (%)",TRUE)} -> -0.002024 | L44: {=_FV(H44,"Change")} -> -0.04 | M44: {=_FV(H44,"Open")} -> 19.75 | N44: {=_FV(H44,"Low")} -> 19.375 | O44: {=_FV(H44,"High")} -> 19.79 | P44: {=_FV(H44,"Previous close",TRUE)} -> 19.76 | Q44: {=_FV(H44,"52 week low",TRUE)} -> 16.22 | R44: {=_FV(H44,"52 week high",TRUE)} -> 21.51 | S44: {=_FV(H44,"Volume")} -> 74181 | T44: {=_FV(H44,"Volume average",TRUE)} -> 17447 | V44: {=_FV(H44,"Expense ratio",TRUE)} -> 0.0075 | W44: {=_FV(H44,"Market cap",TRUE)} -> 46798550 | Y44: =IF(B44=B43,"XXX","")
A45: Oil | B45: USO | C45: Commodities | D45: Energy | G45: WTI crude oil futures | H45: #VALUE! | I45: {=_FV(H45,"Last trade time",TRUE)} -> 45824.942 | J45: {=_FV(H45,"Price")} -> 78.575 | K45: {=_FV(H45,"Change (%)",TRUE)} -> -0.020506 | L45: {=_FV(H45,"Change")} -> -1.645 | M45: {=_FV(H45,"Open")} -> 79.012 | N45: {=_FV(H45,"Low")} -> 76.25 | O45: {=_FV(H45,"High")} -> 79.6 | P45: {=_FV(H45,"Previous close",TRUE)} -> 80.22 | Q45: {=_FV(H45,"52 week low",TRUE)} -> 60.67 | R45: {=_FV(H45,"52 week high",TRUE)} -> 84.58 | S45: {=_FV(H45,"Volume")} -> 40158306 | T45: {=_FV(H45,"Volume average",TRUE)} -> 6259604 | V45: {=_FV(H45,"Expense ratio",TRUE)} -> 0.0082 | W45: {=_FV(H45,"Market cap",TRUE)} -> 9.0702309e+08 | Y45: =IF(B45=B44,"XXX","")
A46: Brent Oil | B46: BNO | C46: Commodities | D46: Energy | E46: Brent | G46: Brent crude oil futures | H46: #VALUE! | I46: {=_FV(H46,"Last trade time",TRUE)} -> 45824.93 | J46: {=_FV(H46,"Price")} -> 31.3 | K46: {=_FV(H46,"Change (%)",TRUE)} -> -0.017577 | L46: {=_FV(H46,"Change")} -> -0.56 | M46: {=_FV(H46,"Open")} -> 31.44 | N46: {=_FV(H46,"Low")} -> 30.3 | O46: {=_FV(H46,"High")} -> 31.62 | P46: {=_FV(H46,"Previous close",TRUE)} -> 31.86 | Q46: {=_FV(H46,"52 week low",TRUE)} -> 24.715 | R46: {=_FV(H46,"52 week high",TRUE)} -> 33.385 | S46: {=_FV(H46,"Volume")} -> 2361185 | T46: {=_FV(H46,"Volume average",TRUE)} -> 820845 | V46: {=_FV(H46,"Expense ratio",TRUE)} -> 0.0114 | W46: {=_FV(H46,"Market cap",TRUE)} -> 82059088 | Y46: =IF(B46=B45,"XXX","")
A47: Gasoline | B47: UGA | C47: Commodities | D47: Energy | E47: Gasoline | G47: Gasoline futures tracking | H47: #VALUE! | I47: {=_FV(H47,"Last trade time",TRUE)} -> 45824.84 | J47: {=_FV(H47,"Price")} -> 63.98 | K47: {=_FV(H47,"Change (%)",TRUE)} -> -0.0009369 | L47: {=_FV(H47,"Change")} -> -0.06 | M47: {=_FV(H47,"Open")} -> 64.16 | N47: {=_FV(H47,"Low")} -> 63.23 | O47: {=_FV(H47,"High")} -> 64.5899 | P47: {=_FV(H47,"Previous close",TRUE)} -> 64.04 | Q47: {=_FV(H47,"52 week low",TRUE)} -> 52.8 | R47: {=_FV(H47,"52 week high",TRUE)} -> 70.7201 | S47: {=_FV(H47,"Volume")} -> 12304 | T47: {=_FV(H47,"Volume average",TRUE)} -> 17846 | V47: {=_FV(H47,"Expense ratio",TRUE)} -> 0.0102 | W47: {=_FV(H47,"Market cap",TRUE)} -> 69741403 | Y47: =IF(B47=B46,"XXX","")
A48: Natural Gas | B48: UNG | C48: Commodities | D48: Energy | E48: Nautural gas | G48: Natural gas futures exposure | H48: #VALUE! | I48: {=_FV(H48,"Last trade time",TRUE)} -> 45824.94 | J48: {=_FV(H48,"Price")} -> 16.995 | K48: {=_FV(H48,"Change (%)",TRUE)} -> 0.038814 | L48: {=_FV(H48,"Change")} -> 0.635 | M48: {=_FV(H48,"Open")} -> 16.8 | N48: {=_FV(H48,"Low")} -> 16.51 | O48: {=_FV(H48,"High")} -> 17.06 | P48: {=_FV(H48,"Previous close",TRUE)} -> 16.36 | Q48: {=_FV(H48,"52 week low",TRUE)} -> 12.35 | R48: {=_FV(H48,"52 week high",TRUE)} -> 24.33 | S48: {=_FV(H48,"Volume")} -> 5626352 | T48: {=_FV(H48,"Volume average",TRUE)} -> 6397943 | V48: {=_FV(H48,"Expense ratio",TRUE)} -> 0.0124 | W48: {=_FV(H48,"Market cap",TRUE)} -> 3.4211433e+08 | Y48: =IF(B48=B47,"XXX","")
A49: Oil | B49: DBO | C49: Commodities | D49: Energy | E49: Oil | G49: Crude oil futures tracking | H49: #VALUE! | I49: {=_FV(H49,"Last trade time",TRUE)} -> 45824.924 | J49: {=_FV(H49,"Price")} -> 14.19 | K49: {=_FV(H49,"Change (%)",TRUE)} -> -0.009078 | L49: {=_FV(H49,"Change")} -> -0.13 | M49: {=_FV(H49,"Open")} -> 14.23 | N49: {=_FV(H49,"Low")} -> 13.77 | O49: {=_FV(H49,"High")} -> 14.27 | P49: {=_FV(H49,"Previous close",TRUE)} -> 14.32 | Q49: {=_FV(H49,"52 week low",TRUE)} -> 11.59 | R49: {=_FV(H49,"52 week high",TRUE)} -> 16.3864 | S49: {=_FV(H49,"Volume")} -> 1607131 | T49: {=_FV(H49,"Volume average",TRUE)} -> 357585 | V49: {=_FV(H49,"Expense ratio",TRUE)} -> 0.0075 | W49: {=_FV(H49,"Market cap",TRUE)} -> 1.744916e+08 | Y49: =IF(B49=B48,"XXX","")
A50: Rare Earth/Strategic Metals | B50: REMX | C50: Commodities | D50: Industrial Commodities | G50: Rare earth metals mining | H50: #VALUE! | I50: {=_FV(H50,"Last trade time",TRUE)} -> 45824.889 | J50: {=_FV(H50,"Price")} -> 40.25 | K50: {=_FV(H50,"Change (%)",TRUE)} -> 0.015388 | L50: {=_FV(H50,"Change")} -> 0.61 | M50: {=_FV(H50,"Open")} -> 40.14 | N50: {=_FV(H50,"Low")} -> 40.04 | O50: {=_FV(H50,"High")} -> 40.54 | P50: {=_FV(H50,"Previous close",TRUE)} -> 39.64 | Q50: {=_FV(H50,"52 week low",TRUE)} -> 32.36 | R50: {=_FV(H50,"52 week high",TRUE)} -> 51.1 | S50: {=_FV(H50,"Volume")} -> 255702 | T50: {=_FV(H50,"Volume average",TRUE)} -> 189722 | V50: {=_FV(H50,"Expense ratio",TRUE)} -> 0.0056 | W50: {=_FV(H50,"Market cap",TRUE)} -> 2.6272014e+08 | Y50: =IF(B50=B49,"XXX","")
A51: United States Copper Index Fund | B51: CPER | C51: Commodities | D51: Industrial Commodities | G51: Copper futures exposure | H51: #VALUE! | I51: {=_FV(H51,"Last trade time",TRUE)} -> 45824.926 | J51: {=_FV(H51,"Price")} -> 30.2 | K51: {=_FV(H51,"Change (%)",TRUE)} -> 0.014444 | L51: {=_FV(H51,"Change")} -> 0.43 | M51: {=_FV(H51,"Open")} -> 30.21 | N51: {=_FV(H51,"Low")} -> 30.0994 | O51: {=_FV(H51,"High")} -> 30.37 | P51: {=_FV(H51,"Previous close",TRUE)} -> 29.77 | Q51: {=_FV(H51,"52 week low",TRUE)} -> 24.7 | R51: {=_FV(H51,"52 week high",TRUE)} -> 33.11 | S51: {=_FV(H51,"Volume")} -> 82729 | T51: {=_FV(H51,"Volume average",TRUE)} -> 172464 | V51: {=_FV(H51,"Expense ratio",TRUE)} -> 0.0106 | W51: {=_FV(H51,"Market cap",TRUE)} -> 1.7250258e+08 | Y51: =IF(B51=B50,"XXX","")
A52: Aluminum | B52: ALUM | C52: Commodities | D52: Industrial Commodities | G52: Aluminum futures tracking | H52: #VALUE! | I52: {=_FV(H52,"Last trade time",TRUE)} -> 45824.667 | J52: {=_FV(H52,"Price")} -> 2.8155 | K52: {=_FV(H52,"Change (%)",TRUE)} -> 0.001067 | L52: {=_FV(H52,"Change")} -> 0.003 | M52: {=_FV(H52,"Open")} -> 2.813 | N52: {=_FV(H52,"Low")} -> 2.8115 | O52: {=_FV(H52,"High")} -> 2.8155 | P52: {=_FV(H52,"Previous close",TRUE)} -> 2.8125 | Q52: {=_FV(H52,"52 week low",TRUE)} -> 2.64 | R52: {=_FV(H52,"52 week high",TRUE)} -> 3.41 | S52: {=_FV(H52,"Volume")} -> 6500 | T52: {=_FV(H52,"Volume average",TRUE)} -> #VALUE! | V52: {=_FV(H52,"Expense ratio",TRUE)} -> 0.0099 | W52: {=_FV(H52,"Market cap",TRUE)} -> 27242751
A53: Industrial metals | B53: BCIM | C53: Commodities | D53: Industrial Commodities | G53: Commodity momentum strategy | H53: #VALUE! | I53: {=_FV(H53,"Last trade time",TRUE)} -> 45824.84 | J53: {=_FV(H53,"Price")} -> 20.8723 | K53: {=_FV(H53,"Change (%)",TRUE)} -> 0.009538 | L53: {=_FV(H53,"Change")} -> 0.1972 | M53: {=_FV(H53,"Open")} -> 20.88 | N53: {=_FV(H53,"Low")} -> 20.8723 | O53: {=_FV(H53,"High")} -> 20.895 | P53: {=_FV(H53,"Previous close",TRUE)} -> 20.6751 | Q53: {=_FV(H53,"52 week low",TRUE)} -> 18.8971 | R53: {=_FV(H53,"52 week high",TRUE)} -> 24.8327 | S53: {=_FV(H53,"Volume")} -> 658 | T53: {=_FV(H53,"Volume average",TRUE)} -> 9661 | V53: {=_FV(H53,"Expense ratio",TRUE)} -> 0.004 | W53: {=_FV(H53,"Market cap",TRUE)} -> 22971434 | Y53: =IF(B53=B52,"XXX","")
A54: Tin | B54: TINM | C54: Commodities | D54: Industrial Commodities | G54: Tin futures exposure | H54: #VALUE! | I54: {=_FV(H54,"Last trade time",TRUE)} -> 45824.514 | J54: {=_FV(H54,"Price")} -> 73.56 | K54: {=_FV(H54,"Change (%)",TRUE)} -> -0.004197 | L54: {=_FV(H54,"Change")} -> -0.31 | M54: {=_FV(H54,"Open")} -> #VALUE! | N54: {=_FV(H54,"Low")} -> #VALUE! | O54: {=_FV(H54,"High")} -> #VALUE! | P54: {=_FV(H54,"Previous close",TRUE)} -> 73.87 | Q54: {=_FV(H54,"52 week low",TRUE)} -> 61.04 | R54: {=_FV(H54,"52 week high",TRUE)} -> 86.97 | S54: {=_FV(H54,"Volume")} -> 1 | T54: {=_FV(H54,"Volume average",TRUE)} -> #VALUE! | V54: {=_FV(H54,"Expense ratio",TRUE)} -> 0.0099 | W54: {=_FV(H54,"Market cap",TRUE)} -> 4083490.2 | Y54: =IF(B54=B53,"XXX","")
A55: Nickel | B55: NICK | C55: Commodities | D55: Industrial Commodities | G55: Nickel futures tracking | H55: #VALUE! | I55: {=_FV(H55,"Last trade time",TRUE)} -> 45824.385 | J55: {=_FV(H55,"Price")} -> 1070 | K55: {=_FV(H55,"Change (%)",TRUE)} -> 0.014218 | L55: {=_FV(H55,"Change")} -> 15 | M55: {=_FV(H55,"Open")} -> 1055 | N55: {=_FV(H55,"Low")} -> 1055 | O55: {=_FV(H55,"High")} -> 1090 | P55: {=_FV(H55,"Previous close",TRUE)} -> 1055 | Q55: {=_FV(H55,"52 week low",TRUE)} -> 270 | R55: {=_FV(H55,"52 week high",TRUE)} -> 1200 | S55: {=_FV(H55,"Volume")} -> 13700 | T55: {=_FV(H55,"Volume average",TRUE)} -> 23301.961 | V55: {=_FV(H55,"Expense ratio",TRUE)} -> #VALUE! | W55: {=_FV(H55,"Market cap",TRUE)} -> 686963300000 | Y55: =IF(B55=B54,"XXX","")
A56: JJC FI Multimercado Credito Privado | B56: JJC | C56: Commodities | D56: Industrial Metals | E56: Copper | G56: iPath Bloomberg Copper Subindex | H56: #VALUE! | I56: {=_FV(H56,"Last trade time",TRUE)} -> 45820 | J56: {=_FV(H56,"Price")} -> 1.4848 | K56: {=_FV(H56,"Change (%)",TRUE)} -> 0.0007727 | L56: {=_FV(H56,"Change")} -> 0.001146 | M56: {=_FV(H56,"Open")} -> #VALUE! | N56: {=_FV(H56,"Low")} -> #VALUE! | O56: {=_FV(H56,"High")} -> #VALUE! | P56: {=_FV(H56,"Previous close",TRUE)} -> 1.4837 | Q56: {=_FV(H56,"52 week low",TRUE)} -> #VALUE! | R56: {=_FV(H56,"52 week high",TRUE)} -> #VALUE! | S56: {=_FV(H56,"Volume")} -> #VALUE! | T56: {=_FV(H56,"Volume average",TRUE)} -> #VALUE! | V56: {=_FV(H56,"Expense ratio",TRUE)} -> #VALUE! | W56: {=_FV(H56,"Market cap",TRUE)} -> #VALUE! | Y56: =IF(B56=B55,"XXX","")
A57: Invesco DB Commodity Index Tracking Fund | B57: DBC | C57: Commodities | D57: Multi | G57: PowerShares DB Commodity Index Tracking | H57: #VALUE! | I57: {=_FV(H57,"Last trade time",TRUE)} -> 45824.934 | J57: {=_FV(H57,"Price")} -> 22.59 | K57: {=_FV(H57,"Change (%)",TRUE)} -> -0.002649 | L57: {=_FV(H57,"Change")} -> -0.06 | M57: {=_FV(H57,"Open")} -> 22.6 | N57: {=_FV(H57,"Low")} -> 22.24 | O57: {=_FV(H57,"High")} -> 22.6697 | P57: {=_FV(H57,"Previous close",TRUE)} -> 22.65 | Q57: {=_FV(H57,"52 week low",TRUE)} -> 19.8443 | R57: {=_FV(H57,"52 week high",TRUE)} -> 23.895 | S57: {=_FV(H57,"Volume")} -> 2230926 | T57: {=_FV(H57,"Volume average",TRUE)} -> 701175 | V57: {=_FV(H57,"Expense ratio",TRUE)} -> 0.0084 | W57: {=_FV(H57,"Market cap",TRUE)} -> 1.1326878e+09 | Y57: =IF(B57=B56,"XXX","")
A58: iShares GSCI Commodity Dynamic Roll Strategy ETF | B58: COMT | C58: Commodities | D58: Multi | G58: iShares Commodities Select Strategy | H58: #VALUE! | I58: {=_FV(H58,"Last trade time",TRUE)} -> 45824.844 | J58: {=_FV(H58,"Price")} -> 26.88 | K58: {=_FV(H58,"Change (%)",TRUE)} -> -0.005181 | L58: {=_FV(H58,"Change")} -> -0.14 | M58: {=_FV(H58,"Open")} -> 26.92 | N58: {=_FV(H58,"Low")} -> 26.52 | O58: {=_FV(H58,"High")} -> 27.005 | P58: {=_FV(H58,"Previous close",TRUE)} -> 27.02 | Q58: {=_FV(H58,"52 week low",TRUE)} -> 23.11 | R58: {=_FV(H58,"52 week high",TRUE)} -> 27.99 | S58: {=_FV(H58,"Volume")} -> 463336 | T58: {=_FV(H58,"Volume average",TRUE)} -> 121867 | V58: {=_FV(H58,"Expense ratio",TRUE)} -> 0.0048 | W58: {=_FV(H58,"Market cap",TRUE)} -> 5.8449219e+08 | Y58: =IF(B58=B57,"XXX","")
A59: United States Commodity Index Fund ETV | B59: USCI | C59: Commodities | D59: Multi | G59: US Commodity Index Fund | H59: #VALUE! | I59: {=_FV(H59,"Last trade time",TRUE)} -> 45824.873 | J59: {=_FV(H59,"Price")} -> 75.1207 | K59: {=_FV(H59,"Change (%)",TRUE)} -> 0.003885 | L59: {=_FV(H59,"Change")} -> 0.2907 | M59: {=_FV(H59,"Open")} -> 74.83 | N59: {=_FV(H59,"Low")} -> 74.1701 | O59: {=_FV(H59,"High")} -> 75.2451 | P59: {=_FV(H59,"Previous close",TRUE)} -> 74.83 | Q59: {=_FV(H59,"52 week low",TRUE)} -> 58.51 | R59: {=_FV(H59,"52 week high",TRUE)} -> 75.2451 | S59: {=_FV(H59,"Volume")} -> 12628 | T59: {=_FV(H59,"Volume average",TRUE)} -> 15134 | V59: {=_FV(H59,"Expense ratio",TRUE)} -> 0.0116 | W59: {=_FV(H59,"Market cap",TRUE)} -> 2.2578534e+08 | Y59: =IF(B59=B58,"XXX","")
A60: iShares Gold Trust Shares of the iShares Gold Trust | B60: IAU | C60: Commodities | D60: Precious Metals | E60: Gold | G60: Gold Trust ETF | H60: #VALUE! | I60: {=_FV(H60,"Last trade time",TRUE)} -> 45824.943 | J60: {=_FV(H60,"Price")} -> 63.805 | K60: {=_FV(H60,"Change (%)",TRUE)} -> -0.014442 | L60: {=_FV(H60,"Change")} -> -0.935 | M60: {=_FV(H60,"Open")} -> 64.42 | N60: {=_FV(H60,"Low")} -> 63.78 | O60: {=_FV(H60,"High")} -> 64.43 | P60: {=_FV(H60,"Previous close",TRUE)} -> 64.74 | Q60: {=_FV(H60,"52 week low",TRUE)} -> 43.35 | R60: {=_FV(H60,"52 week high",TRUE)} -> 65 | S60: {=_FV(H60,"Volume")} -> 8930906 | T60: {=_FV(H60,"Volume average",TRUE)} -> 8850628 | V60: {=_FV(H60,"Expense ratio",TRUE)} -> 0.0025 | W60: {=_FV(H60,"Market cap",TRUE)} -> 4.549232e+10 | Y60: =IF(B60=B59,"XXX","")
A61: Silver | B61: SLV | C61: Commodities | D61: Precious Metals | G61: Silver bullion exposure | H61: #VALUE! | I61: {=_FV(H61,"Last trade time",TRUE)} -> 45824.943 | J61: {=_FV(H61,"Price")} -> 33.02 | K61: {=_FV(H61,"Change (%)",TRUE)} -> 0.001517 | L61: {=_FV(H61,"Change")} -> 0.05 | M61: {=_FV(H61,"Open")} -> 33.1 | N61: {=_FV(H61,"Low")} -> 32.895 | O61: {=_FV(H61,"High")} -> 33.145 | P61: {=_FV(H61,"Previous close",TRUE)} -> 32.97 | Q61: {=_FV(H61,"52 week low",TRUE)} -> 24.25 | R61: {=_FV(H61,"52 week high",TRUE)} -> 33.54 | S61: {=_FV(H61,"Volume")} -> 14860838 | T61: {=_FV(H61,"Volume average",TRUE)} -> 19965692 | V61: {=_FV(H61,"Expense ratio",TRUE)} -> 0.005 | W61: {=_FV(H61,"Market cap",TRUE)} -> 1.5206647e+10 | Y61: =IF(B61=B60,"XXX","")
A62: Gold | B62: GLD | C62: Commodities | D62: Precious Metals | G62: Gold bullion tracking | H62: #VALUE! | I62: {=_FV(H62,"Last trade time",TRUE)} -> 45824.943 | J62: {=_FV(H62,"Price")} -> 311.82 | K62: {=_FV(H62,"Change (%)",TRUE)} -> -0.014133 | L62: {=_FV(H62,"Change")} -> -4.47 | M62: {=_FV(H62,"Open")} -> 314.8 | N62: {=_FV(H62,"Low")} -> 311.65 | O62: {=_FV(H62,"High")} -> 314.87 | P62: {=_FV(H62,"Previous close",TRUE)} -> 316.29 | Q62: {=_FV(H62,"52 week low",TRUE)} -> 212.1204 | R62: {=_FV(H62,"52 week high",TRUE)} -> 317.63 | S62: {=_FV(H62,"Volume")} -> 12697226 | T62: {=_FV(H62,"Volume average",TRUE)} -> 10604079 | V62: {=_FV(H62,"Expense ratio",TRUE)} -> 0.004 | W62: {=_FV(H62,"Market cap",TRUE)} -> 8.2394162e+10 | Y62: =IF(B62=B61,"XXX","")
A63: Palladium | B63: PALL | C63: Commodities | D63: Precious Metals | G63: Palladium futures exposure | H63: #VALUE! | I63: {=_FV(H63,"Last trade time",TRUE)} -> 45824.922 | J63: {=_FV(H63,"Price")} -> 94.36 | K63: {=_FV(H63,"Change (%)",TRUE)} -> -0.0005296 | L63: {=_FV(H63,"Change")} -> -0.05 | M63: {=_FV(H63,"Open")} -> 95.7 | N63: {=_FV(H63,"Low")} -> 94.0101 | O63: {=_FV(H63,"High")} -> 95.94 | P63: {=_FV(H63,"Previous close",TRUE)} -> 94.41 | Q63: {=_FV(H63,"52 week low",TRUE)} -> 77.5207 | R63: {=_FV(H63,"52 week high",TRUE)} -> 113.92 | S63: {=_FV(H63,"Volume")} -> 183889 | T63: {=_FV(H63,"Volume average",TRUE)} -> 242374 | V63: {=_FV(H63,"Expense ratio",TRUE)} -> 0.006 | W63: {=_FV(H63,"Market cap",TRUE)} -> 3.8334017e+08 | Y63: =IF(B63=B62,"XXX","")
A64: Platinum | B64: PPLT | C64: Commodities | D64: Precious Metals | G64: Platinum futures tracking | H64: #VALUE! | I64: {=_FV(H64,"Last trade time",TRUE)} -> 45824.933 | J64: {=_FV(H64,"Price")} -> 113.76 | K64: {=_FV(H64,"Change (%)",TRUE)} -> 0.015624 | L64: {=_FV(H64,"Change")} -> 1.75 | M64: {=_FV(H64,"Open")} -> 116.15 | N64: {=_FV(H64,"Low")} -> 113.51 | O64: {=_FV(H64,"High")} -> 116.2 | P64: {=_FV(H64,"Previous close",TRUE)} -> 112.01 | Q64: {=_FV(H64,"52 week low",TRUE)} -> 82.35 | R64: {=_FV(H64,"52 week high",TRUE)} -> 118.49 | S64: {=_FV(H64,"Volume")} -> 439499 | T64: {=_FV(H64,"Volume average",TRUE)} -> 451286 | V64: {=_FV(H64,"Expense ratio",TRUE)} -> 0.006 | W64: {=_FV(H64,"Market cap",TRUE)} -> 1.1910256e+09 | Y64: =IF(B64=B63,"XXX","")
A65: Ark 21Shares Bitcoin ETF | B65: ARKB | C65: Crypto | G65: Bitcoin ETF exposure | H65: #VALUE! | I65: {=_FV(H65,"Last trade time",TRUE)} -> 45824.939 | J65: {=_FV(H65,"Price")} -> 36.16 | K65: {=_FV(H65,"Change (%)",TRUE)} -> -0.655258 | L65: {=_FV(H65,"Change")} -> -68.73 | M65: {=_FV(H65,"Open")} -> 35.47 | N65: {=_FV(H65,"Low")} -> 35.39 | O65: {=_FV(H65,"High")} -> 36.23 | P65: {=_FV(H65,"Previous close",TRUE)} -> 104.89 | Q65: {=_FV(H65,"52 week low",TRUE)} -> 35.39 | R65: {=_FV(H65,"52 week high",TRUE)} -> 111.79 | S65: {=_FV(H65,"Volume")} -> 1396669 | T65: {=_FV(H65,"Volume average",TRUE)} -> 900975 | U65: =T65*J65 -> 32579256 | V65: {=_FV(H65,"Expense ratio",TRUE)} -> 0.0021 | W65: {=_FV(H65,"Market cap",TRUE)} -> 4818620822 | Y65: =IF(B65=B64,"XXX","")
A66: Bitwise Bitcoin ETF | B66: BITB | C66: Crypto | G66: Bitcoin futures tracking | H66: #VALUE! | I66: {=_FV(H66,"Last trade time",TRUE)} -> 45824.94 | J66: {=_FV(H66,"Price")} -> 59.16 | K66: {=_FV(H66,"Change (%)",TRUE)} -> 0.033904 | L66: {=_FV(H66,"Change")} -> 1.94 | M66: {=_FV(H66,"Open")} -> 58.015 | N66: {=_FV(H66,"Low")} -> 57.94 | O66: {=_FV(H66,"High")} -> 59.3 | P66: {=_FV(H66,"Previous close",TRUE)} -> 57.22 | Q66: {=_FV(H66,"52 week low",TRUE)} -> 27.02 | R66: {=_FV(H66,"52 week high",TRUE)} -> 60.98 | S66: {=_FV(H66,"Volume")} -> 1072685 | T66: {=_FV(H66,"Volume average",TRUE)} -> 1337604 | U66: =T66*J66 -> 79132653 | V66: {=_FV(H66,"Expense ratio",TRUE)} -> 0.0016 | W66: {=_FV(H66,"Market cap",TRUE)} -> 3.9813801e+09 | Y66: =IF(B66=B65,"XXX","")
A67: ProShares Bitcoin ETF | B67: BITO | C67: Crypto | G67: Bitcoin strategy ETF | H67: #VALUE! | I67: {=_FV(H67,"Last trade time",TRUE)} -> 45824.941 | J67: {=_FV(H67,"Price")} -> 21.785 | K67: {=_FV(H67,"Change (%)",TRUE)} -> 0.034425 | L67: {=_FV(H67,"Change")} -> 0.725 | M67: {=_FV(H67,"Open")} -> 21.36 | N67: {=_FV(H67,"Low")} -> 21.33 | O67: {=_FV(H67,"High")} -> 21.83 | P67: {=_FV(H67,"Previous close",TRUE)} -> 21.06 | Q67: {=_FV(H67,"52 week low",TRUE)} -> 16.11 | R67: {=_FV(H67,"52 week high",TRUE)} -> 27.88 | S67: {=_FV(H67,"Volume")} -> 6024576 | T67: {=_FV(H67,"Volume average",TRUE)} -> 7458129 | U67: =T67*J67 -> 1.6247534e+08 | V67: {=_FV(H67,"Expense ratio",TRUE)} -> 0.0095 | W67: {=_FV(H67,"Market cap",TRUE)} -> 2464556872 | Y67: =IF(B67=B66,"XXX","")
A68: CoinShares Valkyrie Bitcoin Fund | B68: BRRR | C68: Crypto | G68: Bitcoin and crypto exposure | H68: #VALUE! | I68: {=_FV(H68,"Last trade time",TRUE)} -> 45824.878 | J68: {=_FV(H68,"Price")} -> 30.74 | K68: {=_FV(H68,"Change (%)",TRUE)} -> 0.033625 | L68: {=_FV(H68,"Change")} -> 1 | M68: {=_FV(H68,"Open")} -> 30.17 | N68: {=_FV(H68,"Low")} -> 30.12 | O68: {=_FV(H68,"High")} -> 30.81 | P68: {=_FV(H68,"Previous close",TRUE)} -> 29.74 | Q68: {=_FV(H68,"52 week low",TRUE)} -> 14.02 | R68: {=_FV(H68,"52 week high",TRUE)} -> 31.67 | S68: {=_FV(H68,"Volume")} -> 115121 | T68: {=_FV(H68,"Volume average",TRUE)} -> 132409 | U68: =T68*J68 -> 4070252.7 | V68: {=_FV(H68,"Expense ratio",TRUE)} -> 0.0022 | W68: {=_FV(H68,"Market cap",TRUE)} -> 6.2889011e+08 | Y68: =IF(B68=B67,"XXX","")
A69: Grayscale Bitcoin Mini Trust | B69: BTC | C69: Crypto | G69: Bitcoin direct exposure | H69: #VALUE! | I69: {=_FV(H69,"Last trade time",TRUE)} -> 45824.943 | J69: {=_FV(H69,"Price")} -> 48.17 | K69: {=_FV(H69,"Change (%)",TRUE)} -> 0.033469 | L69: {=_FV(H69,"Change")} -> 1.56 | M69: {=_FV(H69,"Open")} -> 47.22 | N69: {=_FV(H69,"Low")} -> 47.18 | O69: {=_FV(H69,"High")} -> 48.2889 | P69: {=_FV(H69,"Previous close",TRUE)} -> 46.61 | Q69: {=_FV(H69,"52 week low",TRUE)} -> 22 | R69: {=_FV(H69,"52 week high",TRUE)} -> 49.65 | S69: {=_FV(H69,"Volume")} -> 628264 | T69: {=_FV(H69,"Volume average",TRUE)} -> 968806 | U69: =T69*J69 -> 46667385 | V69: {=_FV(H69,"Expense ratio",TRUE)} -> 0.0015 | W69: {=_FV(H69,"Market cap",TRUE)} -> 4.5712433e+09 | Y69: =IF(B69=B68,"XXX","")
A70: Invesco Galaxy Bitcoin ETF | B70: BTCO | C70: Crypto | G70: Bitcoin mining and crypto | H70: #VALUE! | I70: {=_FV(H70,"Last trade time",TRUE)} -> 45824.876 | J70: {=_FV(H70,"Price")} -> 108.5 | K70: {=_FV(H70,"Change (%)",TRUE)} -> 0.03353 | L70: {=_FV(H70,"Change")} -> 3.52 | M70: {=_FV(H70,"Open")} -> 106.41 | N70: {=_FV(H70,"Low")} -> 106.35 | O70: {=_FV(H70,"High")} -> 108.6948 | P70: {=_FV(H70,"Previous close",TRUE)} -> 104.98 | Q70: {=_FV(H70,"52 week low",TRUE)} -> 49.51 | R70: {=_FV(H70,"52 week high",TRUE)} -> 111.765 | S70: {=_FV(H70,"Volume")} -> 34975 | T70: {=_FV(H70,"Volume average",TRUE)} -> 129221 | U70: =T70*J70 -> 14020478 | V70: {=_FV(H70,"Expense ratio",TRUE)} -> 0.0025 | W70: {=_FV(H70,"Market cap",TRUE)} -> 5.3834247e+08 | Y70: =IF(B70=B69,"XXX","")
A71: WisdomTree Bitcoin Fund | B71: BTCW | C71: Crypto | G71: Bitcoin futures strategy | H71: #VALUE! | I71: {=_FV(H71,"Last trade time",TRUE)} -> 45824.843 | J71: {=_FV(H71,"Price")} -> 115.3 | K71: {=_FV(H71,"Change (%)",TRUE)} -> 0.034545 | L71: {=_FV(H71,"Change")} -> 3.85 | M71: {=_FV(H71,"Open")} -> 113.15 | N71: {=_FV(H71,"Low")} -> 113.1 | O71: {=_FV(H71,"High")} -> 115.505 | P71: {=_FV(H71,"Previous close",TRUE)} -> 111.45 | Q71: {=_FV(H71,"52 week low",TRUE)} -> 52.61 | R71: {=_FV(H71,"52 week high",TRUE)} -> 118.71 | S71: {=_FV(H71,"Volume")} -> 65929 | T71: {=_FV(H71,"Volume average",TRUE)} -> 58926 | U71: =T71*J71 -> 6794167.8 | V71: {=_FV(H71,"Expense ratio",TRUE)} -> 0.002 | W71: {=_FV(H71,"Market cap",TRUE)} -> 1.6209044e+08 | Y71: =IF(B71=B70,"XXX","")
A72: Hashdex Bitcoin ETF | B72: DEFI | C72: Crypto | G72: Decentralized finance exposure | H72: #VALUE! | I72: {=_FV(H72,"Last trade time",TRUE)} -> 45824.84 | J72: {=_FV(H72,"Price")} -> 122.399 | K72: {=_FV(H72,"Change (%)",TRUE)} -> 0.024265 | L72: {=_FV(H72,"Change")} -> 2.8997 | M72: {=_FV(H72,"Open")} -> 122.58 | N72: {=_FV(H72,"Low")} -> 122.399 | O72: {=_FV(H72,"High")} -> 122.58 | P72: {=_FV(H72,"Previous close",TRUE)} -> 119.4993 | Q72: {=_FV(H72,"52 week low",TRUE)} -> 57.23 | R72: {=_FV(H72,"52 week high",TRUE)} -> 127 | S72: {=_FV(H72,"Volume")} -> 455 | T72: {=_FV(H72,"Volume average",TRUE)} -> 567 | U72: =T72*J72 -> 69400.233 | V72: {=_FV(H72,"Expense ratio",TRUE)} -> 0.0103 | W72: {=_FV(H72,"Market cap",TRUE)} -> 13016485 | Y72: =IF(B72=B71,"XXX","")
A73: iShares Ethereum Trust ETF | B73: ETHA | C73: Crypto | G73: Ethereum futures tracking | H73: #VALUE! | I73: {=_FV(H73,"Last trade time",TRUE)} -> 45824.943 | J73: {=_FV(H73,"Price")} -> 20.16 | K73: {=_FV(H73,"Change (%)",TRUE)} -> 0.053292 | L73: {=_FV(H73,"Change")} -> 1.02 | M73: {=_FV(H73,"Open")} -> 19.77 | N73: {=_FV(H73,"Low")} -> 19.755 | O73: {=_FV(H73,"High")} -> 20.24 | P73: {=_FV(H73,"Previous close",TRUE)} -> 19.14 | Q73: {=_FV(H73,"52 week low",TRUE)} -> 10.99 | R73: {=_FV(H73,"52 week high",TRUE)} -> 31.18 | S73: {=_FV(H73,"Volume")} -> 13025661 | T73: {=_FV(H73,"Volume average",TRUE)} -> 16254478 | U73: =T73*J73 -> 3.2769028e+08 | V73: {=_FV(H73,"Expense ratio",TRUE)} -> 0.0013 | W73: {=_FV(H73,"Market cap",TRUE)} -> 3.5830328e+09 | Y73: =IF(B73=B72,"XXX","")
A74: Franklin Templeton Digital Holdings Trust | B74: EZBC | C74: Crypto | G74: Bitcoin and blockchain | H74: #VALUE! | I74: {=_FV(H74,"Last trade time",TRUE)} -> 45824.873 | J74: {=_FV(H74,"Price")} -> 63.02 | K74: {=_FV(H74,"Change (%)",TRUE)} -> 0.034132 | L74: {=_FV(H74,"Change")} -> 2.08 | M74: {=_FV(H74,"Open")} -> 61.81 | N74: {=_FV(H74,"Low")} -> 61.709 | O74: {=_FV(H74,"High")} -> 63.14 | P74: {=_FV(H74,"Previous close",TRUE)} -> 60.94 | Q74: {=_FV(H74,"52 week low",TRUE)} -> 28.72 | R74: {=_FV(H74,"52 week high",TRUE)} -> 64.85 | S74: {=_FV(H74,"Volume")} -> 40575 | T74: {=_FV(H74,"Volume average",TRUE)} -> 76533 | U74: =T74*J74 -> 4823109.7 | V74: {=_FV(H74,"Expense ratio",TRUE)} -> 0.0019 | W74: {=_FV(H74,"Market cap",TRUE)} -> 5.2776669e+08 | Y74: =IF(B74=B73,"XXX","")
A75: Fidelity Wise Origin Bitcoin Fund | B75: FBTC | C75: Crypto | G75: Bitcoin spot ETF | H75: #VALUE! | I75: {=_FV(H75,"Last trade time",TRUE)} -> 45824.943 | J75: {=_FV(H75,"Price")} -> 94.89 | K75: {=_FV(H75,"Change (%)",TRUE)} -> 0.033773 | L75: {=_FV(H75,"Change")} -> 3.1 | M75: {=_FV(H75,"Open")} -> 93.13 | N75: {=_FV(H75,"Low")} -> 92.96 | O75: {=_FV(H75,"High")} -> 95.12 | P75: {=_FV(H75,"Previous close",TRUE)} -> 91.79 | Q75: {=_FV(H75,"52 week low",TRUE)} -> 43.34 | R75: {=_FV(H75,"52 week high",TRUE)} -> 97.83 | S75: {=_FV(H75,"Volume")} -> 1997796 | T75: {=_FV(H75,"Volume average",TRUE)} -> 3019214 | U75: =T75*J75 -> 2.8649322e+08 | V75: {=_FV(H75,"Expense ratio",TRUE)} -> 0.0014 | W75: {=_FV(H75,"Market cap",TRUE)} -> 2.0761389e+10 | Y75: =IF(B75=B74,"XXX","")
A76: Grayscale Bitcoin Trust | B76: GBTC | C76: Crypto | G76: Bitcoin investment trust | H76: #VALUE! | I76: {=_FV(H76,"Last trade time",TRUE)} -> 45824.937 | J76: {=_FV(H76,"Price")} -> 85.655 | K76: {=_FV(H76,"Change (%)",TRUE)} -> 0.034106 | L76: {=_FV(H76,"Change")} -> 2.825 | M76: {=_FV(H76,"Open")} -> 84.02 | N76: {=_FV(H76,"Low")} -> 83.9 | O76: {=_FV(H76,"High")} -> 85.85 | P76: {=_FV(H76,"Previous close",TRUE)} -> 82.83 | Q76: {=_FV(H76,"52 week low",TRUE)} -> 39.56 | R76: {=_FV(H76,"52 week high",TRUE)} -> 88.355 | S76: {=_FV(H76,"Volume")} -> 1652106 | T76: {=_FV(H76,"Volume average",TRUE)} -> 2102879 | U76: =T76*J76 -> 1.801221e+08 | V76: {=_FV(H76,"Expense ratio",TRUE)} -> #VALUE! | W76: {=_FV(H76,"Market cap",TRUE)} -> #VALUE! | Y76: =IF(B76=B75,"XXX","")
... A78: iShares Bitcoin Trust | B78: IBIT | C78: Crypto | G78: Bitcoin spot exposure | H78: #VALUE! | I78: {=_FV(H78,"Last trade time",TRUE)} -> 45824.942 | J78: {=_FV(H78,"Price")} -> 61.8 | K78: {=_FV(H78,"Change (%)",TRUE)} -> 0.034483 | L78: {=_FV(H78,"Change")} -> 2.06 | M78: {=_FV(H78,"Open")} -> 60.6 | N78: {=_FV(H78,"Low")} -> 60.51 | O78: {=_FV(H78,"High")} -> 61.95 | P78: {=_FV(H78,"Previous close",TRUE)} -> 59.74 | Q78: {=_FV(H78,"52 week low",TRUE)} -> 28.23 | R78: {=_FV(H78,"52 week high",TRUE)} -> 63.7 | S78: {=_FV(H78,"Volume")} -> 41567652 | T78: {=_FV(H78,"Volume average",TRUE)} -> 45827223 | U78: =T78*J78 -> 2.8321224e+09 | V78: {=_FV(H78,"Expense ratio",TRUE)} -> 0.0022 | W78: {=_FV(H78,"Market cap",TRUE)} -> 6.9644296e+10 | Y78: =IF(B78=B77,"XXX","")
A79: Aggressive Asset Allocation | B79: AOA | C79: Equities | D79: Asset Allocation | E79: Aggressive asset allocation | G79: Conservative asset allocation | H79: #VALUE! | I79: {=_FV(H79,"Last trade time",TRUE)} -> 45824.84 | J79: {=_FV(H79,"Price")} -> 81.64 | K79: {=_FV(H79,"Change (%)",TRUE)} -> 0.007777 | L79: {=_FV(H79,"Change")} -> 0.63 | M79: {=_FV(H79,"Open")} -> 81.69 | N79: {=_FV(H79,"Low")} -> 81.37 | O79: {=_FV(H79,"High")} -> 81.975 | P79: {=_FV(H79,"Previous close",TRUE)} -> 81.01 | Q79: {=_FV(H79,"52 week low",TRUE)} -> 68.4501 | R79: {=_FV(H79,"52 week high",TRUE)} -> 81.975 | S79: {=_FV(H79,"Volume")} -> 321013 | T79: {=_FV(H79,"Volume average",TRUE)} -> 107211 | V79: {=_FV(H79,"Expense ratio",TRUE)} -> 0.0015 | W79: {=_FV(H79,"Market cap",TRUE)} -> 2.3229447e+09 | Y79: =IF(B79=#REF!,"XXX","") -> #REF!
A80: Moderate Asset Allocation | B80: AOM | C80: Equities | D80: Asset Allocation | E80: Moderate asset allocation | G80: Moderate asset allocation | H80: #VALUE! | I80: {=_FV(H80,"Last trade time",TRUE)} -> 45824.84 | J80: {=_FV(H80,"Price")} -> 45.21 | K80: {=_FV(H80,"Change (%)",TRUE)} -> 0.002661 | L80: {=_FV(H80,"Change")} -> 0.12 | M80: {=_FV(H80,"Open")} -> 45.14 | N80: {=_FV(H80,"Low")} -> 45.14 | O80: {=_FV(H80,"High")} -> 45.3458 | P80: {=_FV(H80,"Previous close",TRUE)} -> 45.09 | Q80: {=_FV(H80,"52 week low",TRUE)} -> 41.2 | R80: {=_FV(H80,"52 week high",TRUE)} -> 45.44 | S80: {=_FV(H80,"Volume")} -> 188543 | T80: {=_FV(H80,"Volume average",TRUE)} -> 114411 | V80: {=_FV(H80,"Expense ratio",TRUE)} -> 0.0015 | W80: {=_FV(H80,"Market cap",TRUE)} -> 1.4927992e+09 | Y80: =IF(B80=B79,"XXX","")
A81: Conservative Asset Allocation | B81: AOK | C81: Equities | D81: Asset Allocation | E81: Conservative balanced allocation | G81: Conservative balanced allocation | H81: #VALUE! | I81: {=_FV(H81,"Last trade time",TRUE)} -> 45824.856 | J81: {=_FV(H81,"Price")} -> 38.4 | K81: {=_FV(H81,"Change (%)",TRUE)} -> 0.0007819 | L81: {=_FV(H81,"Change")} -> 0.03 | M81: {=_FV(H81,"Open")} -> 38.48 | N81: {=_FV(H81,"Low")} -> 38.4 | O81: {=_FV(H81,"High")} -> 38.54 | P81: {=_FV(H81,"Previous close",TRUE)} -> 38.37 | Q81: {=_FV(H81,"52 week low",TRUE)} -> 35.79 | R81: {=_FV(H81,"52 week high",TRUE)} -> 38.77 | S81: {=_FV(H81,"Volume")} -> 496752 | T81: {=_FV(H81,"Volume average",TRUE)} -> 99332 | V81: {=_FV(H81,"Expense ratio",TRUE)} -> 0.0015 | W81: {=_FV(H81,"Market cap",TRUE)} -> 6.2669801e+08 | Y81: =IF(B81=B80,"XXX","")
A82: Growth Asset Allocation | B82: AOR | C82: Equities | D82: Asset Allocation | E82: Growth asset allocation | G82: Growth asset allocation | H82: #VALUE! | I82: {=_FV(H82,"Last trade time",TRUE)} -> 45824.84 | J82: {=_FV(H82,"Price")} -> 60.31 | K82: {=_FV(H82,"Change (%)",TRUE)} -> 0.004497 | L82: {=_FV(H82,"Change")} -> 0.27 | M82: {=_FV(H82,"Open")} -> 60.4 | N82: {=_FV(H82,"Low")} -> 60.31 | O82: {=_FV(H82,"High")} -> 60.58 | P82: {=_FV(H82,"Previous close",TRUE)} -> 60.04 | Q82: {=_FV(H82,"52 week low",TRUE)} -> 52.97 | R82: {=_FV(H82,"52 week high",TRUE)} -> 60.64 | S82: {=_FV(H82,"Volume")} -> 339606 | T82: {=_FV(H82,"Volume average",TRUE)} -> 201737 | V82: {=_FV(H82,"Expense ratio",TRUE)} -> 0.0015 | W82: {=_FV(H82,"Market cap",TRUE)} -> 2.3688067e+09 | Y82: =IF(B82=B81,"XXX","")
A83: Infrastructure | B83: ENFR | C83: Equities | D83: Commodities | E83: Energy | F83: Infrastructure | G83: energy Infrastructure | H83: #VALUE! | I83: {=_FV(H83,"Last trade time",TRUE)} -> 45824.928 | J83: {=_FV(H83,"Price")} -> 31.81 | K83: {=_FV(H83,"Change (%)",TRUE)} -> -0.012112 | L83: {=_FV(H83,"Change")} -> -0.39 | M83: {=_FV(H83,"Open")} -> 32.29 | N83: {=_FV(H83,"Low")} -> 31.715 | O83: {=_FV(H83,"High")} -> 32.476 | P83: {=_FV(H83,"Previous close",TRUE)} -> 32.2 | Q83: {=_FV(H83,"52 week low",TRUE)} -> 25.47 | R83: {=_FV(H83,"52 week high",TRUE)} -> 34.28 | S83: {=_FV(H83,"Volume")} -> 69139 | T83: {=_FV(H83,"Volume average",TRUE)} -> 48245 | V83: {=_FV(H83,"Expense ratio",TRUE)} -> 0.0035 | W83: {=_FV(H83,"Market cap",TRUE)} -> 2.9748436e+08 | Y83: =IF(B83=B82,"XXX","")
A84: Uranium | B84: URA | C84: Equities | D84: Commodities | E84: Energy | F84: Uranium | G84: 80% of assets invested in underlying index which is comprises companies involved in the uranium industry. | H84: #VALUE! | I84: {=_FV(H84,"Last trade time",TRUE)} -> 45824.942 | J84: {=_FV(H84,"Price")} -> 38.07 | K84: {=_FV(H84,"Change (%)",TRUE)} -> 0.053695 | L84: {=_FV(H84,"Change")} -> 1.94 | M84: {=_FV(H84,"Open")} -> 38.27 | N84: {=_FV(H84,"Low")} -> 37.83 | O84: {=_FV(H84,"High")} -> 39.3 | P84: {=_FV(H84,"Previous close",TRUE)} -> 36.13 | Q84: {=_FV(H84,"52 week low",TRUE)} -> 19.5 | R84: {=_FV(H84,"52 week high",TRUE)} -> 39.3 | S84: {=_FV(H84,"Volume")} -> 9035699 | T84: {=_FV(H84,"Volume average",TRUE)} -> 4004910 | V84: {=_FV(H84,"Expense ratio",TRUE)} -> 0.0069 | W84: {=_FV(H84,"Market cap",TRUE)} -> 3.2283775e+09 | Y84: =IF(B84=B83,"XXX","")
A85: Natural Gas Producers | B85: FCG | C85: Equities | D85: Commodities | E85: Energy | F85: Natural Gas Producers | G85: Natural gas industry - producers | H85: #VALUE! | I85: {=_FV(H85,"Last trade time",TRUE)} -> 45824.917 | J85: {=_FV(H85,"Price")} -> 24.64 | K85: {=_FV(H85,"Change (%)",TRUE)} -> -0.006852 | L85: {=_FV(H85,"Change")} -> -0.17 | M85: {=_FV(H85,"Open")} -> 24.63 | N85: {=_FV(H85,"Low")} -> 24.4 | O85: {=_FV(H85,"High")} -> 24.99 | P85: {=_FV(H85,"Previous close",TRUE)} -> 24.81 | Q85: {=_FV(H85,"52 week low",TRUE)} -> 18.81 | R85: {=_FV(H85,"52 week high",TRUE)} -> 27.72 | S85: {=_FV(H85,"Volume")} -> 666994 | T85: {=_FV(H85,"Volume average",TRUE)} -> 335384 | V85: {=_FV(H85,"Expense ratio",TRUE)} -> 0.0057 | W85: {=_FV(H85,"Market cap",TRUE)} -> 3.174074e+08 | Y85: =IF(B85=B84,"XXX","")
A86: Oil & Gas Exploration & Production | B86: PXE | C86: Equities | D86: Commodities | E86: Energy | F86: Oil & Gas Exploration & Production | G86: Energy exploration and production | H86: #VALUE! | I86: {=_FV(H86,"Last trade time",TRUE)} -> 45824.84 | J86: {=_FV(H86,"Price")} -> 29.84 | K86: {=_FV(H86,"Change (%)",TRUE)} -> -0.004005 | L86: {=_FV(H86,"Change")} -> -0.12 | M86: {=_FV(H86,"Open")} -> 29.79 | N86: {=_FV(H86,"Low")} -> 29.57 | O86: {=_FV(H86,"High")} -> 30.0278 | P86: {=_FV(H86,"Previous close",TRUE)} -> 29.96 | Q86: {=_FV(H86,"52 week low",TRUE)} -> 22.19 | R86: {=_FV(H86,"52 week high",TRUE)} -> 34.47 | S86: {=_FV(H86,"Volume")} -> 19915 | T86: {=_FV(H86,"Volume average",TRUE)} -> 26482 | V86: {=_FV(H86,"Expense ratio",TRUE)} -> 0.0063 | W86: {=_FV(H86,"Market cap",TRUE)} -> 70286611 | Y86: =IF(B86=B85,"XXX","")
A87: Oil & Gas Equip. & Services | B87: PXJ | C87: Equities | D87: Commodities | E87: Energy | F87: Oil & Gas Equip. & Services | G87: Oil and gas equipment services | H87: #VALUE! | I87: {=_FV(H87,"Last trade time",TRUE)} -> 45824.84 | J87: {=_FV(H87,"Price")} -> 25.84 | K87: {=_FV(H87,"Change (%)",TRUE)} -> -0.012987 | L87: {=_FV(H87,"Change")} -> -0.34 | M87: {=_FV(H87,"Open")} -> 26.1 | N87: {=_FV(H87,"Low")} -> 25.6308 | O87: {=_FV(H87,"High")} -> 26.1492 | P87: {=_FV(H87,"Previous close",TRUE)} -> 26.18 | Q87: {=_FV(H87,"52 week low",TRUE)} -> 19.38 | R87: {=_FV(H87,"52 week high",TRUE)} -> 33.85 | S87: {=_FV(H87,"Volume")} -> 7520 | T87: {=_FV(H87,"Volume average",TRUE)} -> 7823 | V87: {=_FV(H87,"Expense ratio",TRUE)} -> 0.0066 | W87: {=_FV(H87,"Market cap",TRUE)} -> 24455403 | Y87: =IF(B87=B86,"XXX","")
A88: Developed Markets Growth | B88: EFG | C88: Equities | D88: Commodities | E88: Broad Markets | G88: MSCI EAFE growth stocks | H88: #VALUE! | I88: {=_FV(H88,"Last trade time",TRUE)} -> 45824.88 | J88: {=_FV(H88,"Price")} -> 109.77 | K88: {=_FV(H88,"Change (%)",TRUE)} -> 0.004337 | L88: {=_FV(H88,"Change")} -> 0.474 | M88: {=_FV(H88,"Open")} -> 110.1 | N88: {=_FV(H88,"Low")} -> 109.75 | O88: {=_FV(H88,"High")} -> 110.775 | P88: {=_FV(H88,"Previous close",TRUE)} -> 109.296 | Q88: {=_FV(H88,"52 week low",TRUE)} -> 88.66 | R88: {=_FV(H88,"52 week high",TRUE)} -> 112.18 | S88: {=_FV(H88,"Volume")} -> 820014 | T88: {=_FV(H88,"Volume average",TRUE)} -> 714552 | V88: {=_FV(H88,"Expense ratio",TRUE)} -> 0.0036 | W88: {=_FV(H88,"Market cap",TRUE)} -> 1.3051913e+10 | Y88: =IF(B88=B87,"XXX","")
A89: Developed Markets Small Caps | B89: SCZ | C89: Equities | D89: Commodities | E89: Broad Markets | G89: MSCI EAFE small-cap stocks | H89: #VALUE! | I89: {=_FV(H89,"Last trade time",TRUE)} -> 45824.844 | J89: {=_FV(H89,"Price")} -> 70.58 | K89: {=_FV(H89,"Change (%)",TRUE)} -> 0.005256 | L89: {=_FV(H89,"Change")} -> 0.369 | M89: {=_FV(H89,"Open")} -> 70.8 | N89: {=_FV(H89,"Low")} -> 70.54 | O89: {=_FV(H89,"High")} -> 71.175 | P89: {=_FV(H89,"Previous close",TRUE)} -> 70.211 | Q89: {=_FV(H89,"52 week low",TRUE)} -> 56.64 | R89: {=_FV(H89,"52 week high",TRUE)} -> 72.19 | S89: {=_FV(H89,"Volume")} -> 566636 | T89: {=_FV(H89,"Volume average",TRUE)} -> 969094 | V89: {=_FV(H89,"Expense ratio",TRUE)} -> 0.004 | W89: {=_FV(H89,"Market cap",TRUE)} -> 1.0207531e+10 | Y89: =IF(B89=B88,"XXX","")
A90: iShares U.S. Basic Materials ETF | B90: IYM | C90: Equities | D90: Commodities | E90: Basic Materials | G90: Basic materials sector | H90: #VALUE! | I90: {=_FV(H90,"Last trade time",TRUE)} -> 45824.84 | J90: {=_FV(H90,"Price")} -> 138.85 | K90: {=_FV(H90,"Change (%)",TRUE)} -> 0.006918 | L90: {=_FV(H90,"Change")} -> 0.954 | M90: {=_FV(H90,"Open")} -> 138.98 | N90: {=_FV(H90,"Low")} -> 138.57 | O90: {=_FV(H90,"High")} -> 139.7799 | P90: {=_FV(H90,"Previous close",TRUE)} -> 137.896 | Q90: {=_FV(H90,"52 week low",TRUE)} -> 115.07 | R90: {=_FV(H90,"52 week high",TRUE)} -> 153.55 | S90: {=_FV(H90,"Volume")} -> 8413 | T90: {=_FV(H90,"Volume average",TRUE)} -> 26770 | V90: {=_FV(H90,"Expense ratio",TRUE)} -> 0.0039 | W90: {=_FV(H90,"Market cap",TRUE)} -> 4.8471411e+08 | Y90: =IF(B90=B89,"XXX","")
A91: International Small Caps | B91: GWX | C91: Equities | D91: Commodities | E91: Broad Markets | G91: Global water infrastructure | H91: #VALUE! | I91: {=_FV(H91,"Last trade time",TRUE)} -> 45824.84 | J91: {=_FV(H91,"Price")} -> 36.54 | K91: {=_FV(H91,"Change (%)",TRUE)} -> 0.007722 | L91: {=_FV(H91,"Change")} -> 0.28 | M91: {=_FV(H91,"Open")} -> 36.74 | N91: {=_FV(H91,"Low")} -> 36.53 | O91: {=_FV(H91,"High")} -> 36.8191 | P91: {=_FV(H91,"Previous close",TRUE)} -> 36.26 | Q91: {=_FV(H91,"52 week low",TRUE)} -> 28.53 | R91: {=_FV(H91,"52 week high",TRUE)} -> 36.84 | S91: {=_FV(H91,"Volume")} -> 90665 | T91: {=_FV(H91,"Volume average",TRUE)} -> 60960 | V91: {=_FV(H91,"Expense ratio",TRUE)} -> 0.004 | W91: {=_FV(H91,"Market cap",TRUE)} -> 6.9237504e+08 | Y91: =IF(B91=B90,"XXX","")
A92: Sprott Gold Miners | B92: SGDM | C92: Equities | D92: Commodities | E92: Gold Miners | G92: Gold mining companies | H92: #VALUE! | I92: {=_FV(H92,"Last trade time",TRUE)} -> 45824.863 | J92: {=_FV(H92,"Price")} -> 46.21 | K92: {=_FV(H92,"Change (%)",TRUE)} -> -0.01081 | L92: {=_FV(H92,"Change")} -> -0.505 | M92: {=_FV(H92,"Open")} -> 46.5 | N92: {=_FV(H92,"Low")} -> 46.0901 | O92: {=_FV(H92,"High")} -> 46.67 | P92: {=_FV(H92,"Previous close",TRUE)} -> 46.715 | Q92: {=_FV(H92,"52 week low",TRUE)} -> 25.78 | R92: {=_FV(H92,"52 week high",TRUE)} -> 47.04 | S92: {=_FV(H92,"Volume")} -> 32835 | T92: {=_FV(H92,"Volume average",TRUE)} -> 47129 | V92: {=_FV(H92,"Expense ratio",TRUE)} -> 0.005 | W92: {=_FV(H92,"Market cap",TRUE)} -> 3.8685267e+08 | Y92: =IF(B92=B91,"XXX","")
A93: Sprott Uranium Miners | B93: URNM | C93: Equities | D93: Commodities | E93: Uranium Miners | G93: Uranium mining companies | H93: #VALUE! | I93: {=_FV(H93,"Last trade time",TRUE)} -> 45824.93 | J93: {=_FV(H93,"Price")} -> 46.3 | K93: {=_FV(H93,"Change (%)",TRUE)} -> 0.069778 | L93: {=_FV(H93,"Change")} -> 3.02 | M93: {=_FV(H93,"Open")} -> 45.8 | N93: {=_FV(H93,"Low")} -> 45.36 | O93: {=_FV(H93,"High")} -> 47.8 | P93: {=_FV(H93,"Previous close",TRUE)} -> 43.28 | Q93: {=_FV(H93,"52 week low",TRUE)} -> 27.6 | R93: {=_FV(H93,"52 week high",TRUE)} -> 53.48 | S93: {=_FV(H93,"Volume")} -> 2259207 | T93: {=_FV(H93,"Volume average",TRUE)} -> 753928 | V93: {=_FV(H93,"Expense ratio",TRUE)} -> 0.0076 | W93: {=_FV(H93,"Market cap",TRUE)} -> 1.489022e+09 | Y93: =IF(B93=B92,"XXX","")
A94: Sprott Sil Min & Ph Sil | B94: SLVR | C94: Equities | D94: Commodities | E94: Silver mining industry | G94: Silver mining industry | H94: #VALUE! | I94: {=_FV(H94,"Last trade time",TRUE)} -> 45824.914 | J94: {=_FV(H94,"Price")} -> 30.3 | K94: {=_FV(H94,"Change (%)",TRUE)} -> -0.002633 | L94: {=_FV(H94,"Change")} -> -0.08 | M94: {=_FV(H94,"Open")} -> 30.53 | N94: {=_FV(H94,"Low")} -> 30.17 | O94: {=_FV(H94,"High")} -> 30.61 | P94: {=_FV(H94,"Previous close",TRUE)} -> 30.38 | Q94: {=_FV(H94,"52 week low",TRUE)} -> 19.6601 | R94: {=_FV(H94,"52 week high",TRUE)} -> 31.15 | S94: {=_FV(H94,"Volume")} -> 111424 | T94: {=_FV(H94,"Volume average",TRUE)} -> 105148 | V94: {=_FV(H94,"Expense ratio",TRUE)} -> 0.0065 | W94: {=_FV(H94,"Market cap",TRUE)} -> 65456063 | Y94: =IF(B94=B93,"XXX","")
A95: Solar | B95: TAN | C95: Equities | D95: Commodities | E95: Alternative Energy | F95: Solar | G95: Solar energy industry | H95: #VALUE! | I95: {=_FV(H95,"Last trade time",TRUE)} -> 45824.942 | J95: {=_FV(H95,"Price")} -> 35.35 | K95: {=_FV(H95,"Change (%)",TRUE)} -> 0.010866 | L95: {=_FV(H95,"Change")} -> 0.38 | M95: {=_FV(H95,"Open")} -> 35.36 | N95: {=_FV(H95,"Low")} -> 34.75 | O95: {=_FV(H95,"High")} -> 35.64 | P95: {=_FV(H95,"Previous close",TRUE)} -> 34.97 | Q95: {=_FV(H95,"52 week low",TRUE)} -> 25.53 | R95: {=_FV(H95,"52 week high",TRUE)} -> 45.86 | S95: {=_FV(H95,"Volume")} -> 907500 | T95: {=_FV(H95,"Volume average",TRUE)} -> 1276950 | V95: {=_FV(H95,"Expense ratio",TRUE)} -> 0.0071 | W95: {=_FV(H95,"Market cap",TRUE)} -> 5.950097e+08 | Y95: =IF(B95=B94,"XXX","")
A96: Sprott Active Au & Ag | B96: GBUG | C96: Equities | D96: Commodities | E96: Gold and Silver mining | G96: Gold mining and precious metals | H96: #VALUE! | I96: {=_FV(H96,"Last trade time",TRUE)} -> 45824.844 | J96: {=_FV(H96,"Price")} -> 26.541 | K96: {=_FV(H96,"Change (%)",TRUE)} -> -0.013346 | L96: {=_FV(H96,"Change")} -> -0.359 | M96: {=_FV(H96,"Open")} -> 26.9 | N96: {=_FV(H96,"Low")} -> 26.4822 | O96: {=_FV(H96,"High")} -> 26.97 | P96: {=_FV(H96,"Previous close",TRUE)} -> 26.9 | Q96: {=_FV(H96,"52 week low",TRUE)} -> 18.39 | R96: {=_FV(H96,"52 week high",TRUE)} -> 27.68 | S96: {=_FV(H96,"Volume")} -> 42448 | T96: {=_FV(H96,"Volume average",TRUE)} -> 42604 | V96: {=_FV(H96,"Expense ratio",TRUE)} -> 0.0089 | W96: {=_FV(H96,"Market cap",TRUE)} -> 41002706 | Y96: =IF(B96=B95,"XXX","")
A97: SPDR S&P Global Natural Resources ETF | B97: GNR | C97: Equities | D97: Commodities | E97: Global natural resources | G97: Global natural resources | H97: #VALUE! | I97: {=_FV(H97,"Last trade time",TRUE)} -> 45824.84 | J97: {=_FV(H97,"Price")} -> 55.03 | K97: {=_FV(H97,"Change (%)",TRUE)} -> 0.003099 | L97: {=_FV(H97,"Change")} -> 0.17 | M97: {=_FV(H97,"Open")} -> 55 | N97: {=_FV(H97,"Low")} -> 54.9844 | O97: {=_FV(H97,"High")} -> 55.4499 | P97: {=_FV(H97,"Previous close",TRUE)} -> 54.86 | Q97: {=_FV(H97,"52 week low",TRUE)} -> 45.18 | R97: {=_FV(H97,"52 week high",TRUE)} -> 58.86 | S97: {=_FV(H97,"Volume")} -> 219008 | T97: {=_FV(H97,"Volume average",TRUE)} -> 192536 | V97: {=_FV(H97,"Expense ratio",TRUE)} -> 0.004 | W97: {=_FV(H97,"Market cap",TRUE)} -> 2.7398154e+09 | Y97: =IF(B97=B96,"XXX","")
A98: Nuclear | B98: NLR | C98: Equities | D98: Commodities | E98: Alternative Energy | F98: Nuclear | G98: Nuclear energy and uranium | H98: #VALUE! | I98: {=_FV(H98,"Last trade time",TRUE)} -> 45824.932 | J98: {=_FV(H98,"Price")} -> 109.76 | K98: {=_FV(H98,"Change (%)",TRUE)} -> 0.045035 | L98: {=_FV(H98,"Change")} -> 4.73 | M98: {=_FV(H98,"Open")} -> 109.78 | N98: {=_FV(H98,"Low")} -> 108.905 | O98: {=_FV(H98,"High")} -> 112.9055 | P98: {=_FV(H98,"Previous close",TRUE)} -> 105.03 | Q98: {=_FV(H98,"52 week low",TRUE)} -> 64.26 | R98: {=_FV(H98,"52 week high",TRUE)} -> 112.9055 | S98: {=_FV(H98,"Volume")} -> 710412 | T98: {=_FV(H98,"Volume average",TRUE)} -> 339970 | V98: {=_FV(H98,"Expense ratio",TRUE)} -> 0.0055 | W98: {=_FV(H98,"Market cap",TRUE)} -> 1.2714256e+09 | Y98: =IF(B98=B97,"XXX","")
A99: Sprott Lithium Miners | B99: LITP | C99: Equities | D99: Commodities | E99: Lithium miners | G99: Lithium miners | H99: #VALUE! | I99: {=_FV(H99,"Last trade time",TRUE)} -> 45824.844 | J99: {=_FV(H99,"Price")} -> 5.685 | K99: {=_FV(H99,"Change (%)",TRUE)} -> 0.002646 | L99: {=_FV(H99,"Change")} -> 0.015 | M99: {=_FV(H99,"Open")} -> 5.71 | N99: {=_FV(H99,"Low")} -> 5.58 | O99: {=_FV(H99,"High")} -> 5.71 | P99: {=_FV(H99,"Previous close",TRUE)} -> 5.67 | Q99: {=_FV(H99,"52 week low",TRUE)} -> 4.63 | R99: {=_FV(H99,"52 week high",TRUE)} -> 9.11 | S99: {=_FV(H99,"Volume")} -> 5528 | T99: {=_FV(H99,"Volume average",TRUE)} -> 10287 | V99: {=_FV(H99,"Expense ratio",TRUE)} -> 0.0065 | W99: {=_FV(H99,"Market cap",TRUE)} -> 11743708 | Y99: =IF(B99=B98,"XXX","")
A100: Global X Copper Miners ETF | B100: COPX | C100: Equities | D100: Commodities | E100: Copper Miners | G100: Copper miners index | H100: #VALUE! | I100: {=_FV(H100,"Last trade time",TRUE)} -> 45824.938 | J100: {=_FV(H100,"Price")} -> 43.47 | K100: {=_FV(H100,"Change (%)",TRUE)} -> 0.013523 | L100: {=_FV(H100,"Change")} -> 0.58 | M100: {=_FV(H100,"Open")} -> 43.41 | N100: {=_FV(H100,"Low")} -> 43.34 | O100: {=_FV(H100,"High")} -> 43.9 | P100: {=_FV(H100,"Previous close",TRUE)} -> 42.89 | Q100: {=_FV(H100,"52 week low",TRUE)} -> 30.77 | R100: {=_FV(H100,"52 week high",TRUE)} -> 48.96 | S100: {=_FV(H100,"Volume")} -> 1046470 | T100: {=_FV(H100,"Volume average",TRUE)} -> 1180466 | V100: {=_FV(H100,"Expense ratio",TRUE)} -> 0.0065 | W100: {=_FV(H100,"Market cap",TRUE)} -> 1.8997939e+09 | Y100: =IF(B100=B99,"XXX","")
A101: Sprott Junior Uranm Mnrs | B101: URNJ | C101: Equities | D101: Commodities | E101: Uranium Miners | G101: Junior uranium miners | H101: #VALUE! | I101: {=_FV(H101,"Last trade time",TRUE)} -> 45824.927 | J101: {=_FV(H101,"Price")} -> 20.77 | K101: {=_FV(H101,"Change (%)",TRUE)} -> 0.105375 | L101: {=_FV(H101,"Change")} -> 1.98 | M101: {=_FV(H101,"Open")} -> 20.35 | N101: {=_FV(H101,"Low")} -> 20.18 | O101: {=_FV(H101,"High")} -> 21.49 | P101: {=_FV(H101,"Previous close",TRUE)} -> 18.79 | Q101: {=_FV(H101,"52 week low",TRUE)} -> 11.52 | R101: {=_FV(H101,"52 week high",TRUE)} -> 26.95 | S101: {=_FV(H101,"Volume")} -> 928768 | T101: {=_FV(H101,"Volume average",TRUE)} -> 265621 | V101: {=_FV(H101,"Expense ratio",TRUE)} -> 0.008 | W101: {=_FV(H101,"Market cap",TRUE)} -> 2.5694546e+08 | Y101: =IF(B101=B100,"XXX","")
...

Sheet Sheet1
B1: ETF Ticker Descriptions
B3: Ticker | C3: Description | G3: Additional ETF Ticker Descriptions
B4: CBLS | C4: Attempts to replicate merger arbitrage strategies
B5: FORH | C5: Long-short equity strategy targeting value stocks
B6: HDG | C6: Currency hedged international equity exposure
B7: HEDJ | C7: Euro hedged European equity index
B8: HTUS | C8: Hedged equity strategy with downside protection
B9: HYKE | C9: High yield corporate bond ETF
B10: PFIX | C10: Inflation-protected securities with variable duration
B11: QAI | C11: Multi-alternative strategies replication
B12: RATE | C12: Interest rate hedged high yield bonds
B13: RINF | C13: Real return asset allocation for inflation protection
B14: RLY | C14: Strategic beta equity factor rotation
B15: RYSE | C15: Risk parity asset allocation strategy
... B454: IOO | C454: iShares Global 100 ETF

Sheet Sheet15
A1: Sector | B1: Subsector | C1: Tickers
A2: alternative_etfs | B2: private_equity_exposure_etfs | C2: BIZD, PSP | D2: BIZD | E2: PSP
A3: alternative_etfs | B3: business_development_companies | C3: HTGC, TPVG, TSLX | D3: HTGC | E3: TPVG | F3: TSLX
A4: alternative_etfs | B4: closed_end_funds_that_hold_private_equity_late_sta | C4: SSSS, SVVC | D4: SSSS | E4: SVVC
A5: alternative_etfs | B5: equity_selection_hedge_fund_holding_clones | C5: GURU | D5: GURU
A6: alternative_etfs | B6: hedge_funds | C6: BXMDX, HDG, MNA, QAI, RCIWX | D6: BXMDX | E6: HDG | F6: MNA | G6: QAI | H6: RCIWX
A7: alternative_etfs | B7: ipo_focused_etfs_late_stage_tech_pre_ipo_th | C7: ARKK, FPX, IPO, PEX | D7: ARKK | E7: FPX | F7: IPO | G7: PEX
A8: commodity_etfs | B8: softs | C8: BAL, CANE, DBA, JO, NIB, SGG | D8: BAL | E8: CANE | F8: DBA | G8: JO | H8: NIB | I8: SGG
A9: commodity_etfs | B9: broad_commodity_etfs | C9: COMT, DBC, GSG, USCI | D9: COMT | E9: DBC | F9: GSG | G9: USCI
A10: commodity_etfs | B10: energy_focused_etfs | C10: BNO, UNG, USO | D10: BNO | E10: UNG | F10: USO
A11: commodity_etfs | B11: grains | C11: CORN, DBA, SOYB, TAGS, WEAT | D11: CORN | E11: DBA | F11: SOYB | G11: TAGS | H11: WEAT
A12: commodity_etfs | B12: industrial_metals | C12: CPER, DBB, FOIL, JJC | D12: CPER | E12: DBB | F12: FOIL | G12: JJC
A13: commodity_etfs | B13: livestock | C13: COW | D13: COW
A14: commodity_etfs | B14: precious_metals_etfs | C14: GLD, IAU, PALL, PPLT, SLV | D14: GLD | E14: IAU | F14: PALL | G14: PPLT | H14: SLV
A15: equity_etfs | B15: single_country_and_regional_etfs_in_emerging_marke | C15: EWT, EWY, EWZ, INDA, MCHI | D15: EWT | E15: EWY | F15: EWZ | G15: INDA | H15: MCHI
A16: equity_etfs | B16: sector_specific_etfs | C16: XLB, XLC, XLE, XLF, XLI, XLK, XLP, XLRE, XLU, XLV, XLY | D16: XLB | E16: XLC | F16: XLE | G16: XLF | H16: XLI | I16: XLK | J16: XLP | K16: XLRE | L16: XLU | M16: XLV | N16: XLY
A17: equity_etfs | B17: barra_styleetfs | C17: IVW, IWF, IWO, IWP, JHMS, MTUM, PDP, QUAL, RFG, RPG, SPHD, SPHQ, SPLV, SPYG, USMV, VBK, VFMF, VFMO, VFMV, VFQY, VFVA, VLUE, VOT, VUG | D17: IVW | E17: IWF | F17: IWO | G17: IWP | H17: JHMS | I17: MTUM | J17: PDP | K17: QUAL | L17: RFG | M17: RPG | N17: SPHD | O17: SPHQ | P17: SPLV | Q17: SPYG | R17: USMV | S17: VBK | T17: VFMF | U17: VFMO | V17: VFMV | W17: VFQY | X17: VFVA | Y17: VLUE | Z17: VOT | AA17: VUG
A18: equity_etfs | B18: broad_us_market | C18: ITOT, IWM, QQQ, SPY, VTI | D18: ITOT | E18: IWM | F18: QQQ | G18: SPY | H18: VTI
A19: equity_etfs | B19: broad_based_emerging_market_equity_etfs | C19: EEM, IEMG, SCHE, VWO | D19: EEM | E19: IEMG | F19: SCHE | G19: VWO
A20: equity_etfs | B20: factor_style_and_specialized_em_etfs | C20: EEMV, KWEB, VMMSX | D20: EEMV | E20: KWEB | F20: VMMSX
A21: equity_etfs | B21: global_international_etfs | C21: ACWI, EZU, FXI, IEFA, IEMG, VEA, VGK, VT, VWO | D21: ACWI | E21: EZU | F21: FXI | G21: IEFA | H21: IEMG | I21: VEA | J21: VGK | K21: VT | L21: VWO
A22: fixed_income_etfs | B22: convertible_bonds | C22: ICVT | D22: ICVT
A23: fixed_income_etfs | B23: high_yield_junk_bond_etfs | C23: ANGL, FALN, HYG, JNK | D23: ANGL | E23: FALN | F23: HYG | G23: JNK
A24: fixed_income_etfs | B24: investment_grade_corporate_bond_etfs | C24: IGSB, LQD, SPBO, VCIT, VTC | D24: IGSB | E24: LQD | F24: SPBO | G24: VCIT | H24: VTC
A25: fixed_income_etfs | B25: treasury_and_inflation_bond_etfs | C25: IEF, SCHP, SHY, TLT, VGIT | D25: IEF | E25: SCHP | F25: SHY | G25: TLT | H25: VGIT
B28: #N/A | C28: VanEck BDC Income ETF | D28: VanEck:BDC Income (ARCX:BIZD) | J28: =IF(ISNA(C28),D28,C28) -> VanEck BDC Income ETF
B29: #N/A | C29: #N/A | D29: HERCULES CAPITAL, INC. (XNYS:HTGC) | J29: =IF(ISNA(C29),D29,C29) -> HERCULES CAPITAL, INC. (XNYS:HTGC)
B30: #N/A | C30: #N/A | D30: TRIPLEPOINT VENTURE GROWTH BDC CORP. (XNYS:TPVG) | J30: =IF(ISNA(C30),D30,C30) -> TRIPLEPOINT VENTURE GROWTH BDC CORP. (XNYS:TPVG)
B31: #N/A | C31: #N/A | D31: SIXTH STREET SPECIALTY LENDING, INC. (XNYS:TSLX) | J31: =IF(ISNA(C31),D31,C31) -> SIXTH STREET SPECIALTY LENDING, INC. (XNYS:TSLX)
B32: #N/A | C32: #N/A | D32: SURO CAPITAL CORP. (XNAS:SSSS) | J32: =IF(ISNA(C32),D32,C32) -> SURO CAPITAL CORP. (XNAS:SSSS)
B33: #N/A | C33: #N/A | D33: Firsthand Technology Val (OTCM:SVVC) | J33: =IF(ISNA(C33),D33,C33) -> Firsthand Technology Val (OTCM:SVVC)
B34: #N/A | C34: #N/A | D34: Blackstone Alternative Multi-Strategy Fund;D | J34: =IF(ISNA(C34),D34,C34) -> Blackstone Alternative Multi-Strategy Fund;D
B35: #N/A | C35: #N/A | D35: Resource Credit Income Fund;W | J35: =IF(ISNA(C35),D35,C35) -> Resource Credit Income Fund;W
B36: #N/A | C36: ARK Innovation ETF | D36: ARK Innovation (BATS:ARKK) | J36: =IF(ISNA(C36),D36,C36) -> ARK Innovation ETF
B37: #N/A | C37: Renaissance IPO ETF | D37: Renaissance IPO (ARCX:IPO) | J37: =IF(ISNA(C37),D37,C37) -> Renaissance IPO ETF
B38: #N/A | C38: ProShares Global Listed Private Equity ETF | D38: ProShares:Gl Lstd Prv Eq (BATS:PEX) | J38: =IF(ISNA(C38),D38,C38) -> ProShares Global Listed Private Equity ETF
B39: #N/A | C39: #N/A | D39: BAL Germany AG (XWBO:BAL) | J39: =IF(ISNA(C39),D39,C39) -> BAL Germany AG (XWBO:BAL)
B40: #N/A | C40: #N/A | D40: JO | J40: =IF(ISNA(C40),D40,C40) -> JO
B41: #N/A | C41: #N/A | D41: NIB HOLDINGS LTD (XASX:NHF) | J41: =IF(ISNA(C41),D41,C41) -> NIB HOLDINGS LTD (XASX:NHF)
B42: #N/A | C42: #N/A | D42: Sensys Gatso Group AB (XSTO:SGG) | J42: =IF(ISNA(C42),D42,C42) -> Sensys Gatso Group AB (XSTO:SGG)
B43: #N/A | C43: iShares GSCI Commodity Dynamic Roll Strategy ETF | D43: iShares:GSCI Comm Dyn RS (XNAS:COMT) | J43: =IF(ISNA(C43),D43,C43) -> iShares GSCI Commodity Dynamic Roll Strategy ETF
B44: #N/A | C44: Invesco DB Commodity Index Tracking Fund | D44: Invesco DB Cm Idx (ARCX:DBC) | J44: =IF(ISNA(C44),D44,C44) -> Invesco DB Commodity Index Tracking Fund
B45: #N/A | C45: United States Commodity Index Fund ETV | D45: United States Comdty Idx (ARCX:USCI) | J45: =IF(ISNA(C45),D45,C45) -> United States Commodity Index Fund ETV
B46: #N/A | C46: Teucrium Agricultural Fund ETV | D46: Teucrium:Agricultural (ARCX:TAGS) | J46: =IF(ISNA(C46),D46,C46) -> Teucrium Agricultural Fund ETV
B47: #N/A | C47: #N/A | D47: FOIL | J47: =IF(ISNA(C47),D47,C47) -> FOIL
B48: #N/A | C48: #N/A | D48: JJC FI Multimercado Credito Privado | J48: =IF(ISNA(C48),D48,C48) -> JJC FI Multimercado Credito Privado
B49: #N/A | C49: #N/A | D49: iShares Global Agri Idx ETF (NEOE:COW) | J49: =IF(ISNA(C49),D49,C49) -> iShares Global Agri Idx ETF (NEOE:COW)
B50: #N/A | C50: iShares Gold Trust Shares of the iShares Gold Trust | D50: IShares:Gold Trust (ARCX:IAU) | J50: =IF(ISNA(C50),D50,C50) -> iShares Gold Trust Shares of the iShares Gold Trust
B51: #N/A | C51: iShares MSCI India ETF | D51: iShares:MSCI India (BATS:INDA) | J51: =IF(ISNA(C51),D51,C51) -> iShares MSCI India ETF
B52: #N/A | C52: iShares S&P 500 Growth ETF | D52: iShares:S&P 500 Gro (ARCX:IVW) | J52: =IF(ISNA(C52),D52,C52) -> iShares S&P 500 Growth ETF
B53: #N/A | C53: #N/A | D53: JHMS | J53: =IF(ISNA(C53),D53,C53) -> JHMS
B54: #N/A | C54: Invesco S&P MidCap 400 Pure Growth ETF | D54: Invesco S&P MC400 PG (ARCX:RFG) | J54: =IF(ISNA(C54),D54,C54) -> Invesco S&P MidCap 400 Pure Growth ETF
B55: #N/A | C55: Invesco S&P 500 Pure Growth ETF | D55: Invesco S&P500 Pr Gr (ARCX:RPG) | J55: =IF(ISNA(C55),D55,C55) -> Invesco S&P 500 Pure Growth ETF
B56: #N/A | C56: Invesco S&P 500 High Dividend Low Volatility ETF | D56: Invesco S&P500 HD LV (ARCX:SPHD) | J56: =IF(ISNA(C56),D56,C56) -> Invesco S&P 500 High Dividend Low Volatility ETF
B57: #N/A | C57: Vanguard Small-Cap Growth ETF | D57: Vanguard SC G Id;ETF (ARCX:VBK) | J57: =IF(ISNA(C57),D57,C57) -> Vanguard Small-Cap Growth ETF
B58: #N/A | C58: Vanguard U.S. Multifactor ETF | D58: Vanguard US Multifactor (BATS:VFMF) | J58: =IF(ISNA(C58),D58,C58) -> Vanguard U.S. Multifactor ETF
B59: #N/A | C59: Vanguard U.S. Momentum Factor ETF | D59: Vanguard US Momentum Ftr (BATS:VFMO) | J59: =IF(ISNA(C59),D59,C59) -> Vanguard U.S. Momentum Factor ETF
B60: #N/A | C60: Vanguard U.S. Minimum Volatility ETF | D60: Vanguard US Minimum Vol (BATS:VFMV) | J60: =IF(ISNA(C60),D60,C60) -> Vanguard U.S. Minimum Volatility ETF
B61: #N/A | C61: Vanguard U.S. Quality Factor ETF | D61: Vanguard US Quality Ftr (BATS:VFQY) | J61: =IF(ISNA(C61),D61,C61) -> Vanguard U.S. Quality Factor ETF
B62: #N/A | C62: Vanguard U.S. Value Factor ETF | D62: Vanguard US Value Factor (BATS:VFVA) | J62: =IF(ISNA(C62),D62,C62) -> Vanguard U.S. Value Factor ETF
B63: #N/A | C63: iShares MSCI USA Value Factor ETF | D63: iShares:MSCI USA Val Fct (BATS:VLUE) | J63: =IF(ISNA(C63),D63,C63) -> iShares MSCI USA Value Factor ETF
B64: #N/A | C64: Vanguard Mid-Cap Growth ETF | D64: Vanguard MC G I;ETF (ARCX:VOT) | J64: =IF(ISNA(C64),D64,C64) -> Vanguard Mid-Cap Growth ETF
B65: #N/A | C65: Vanguard Growth ETF | D65: Vanguard Gro Idx;ETF (ARCX:VUG) | J65: =IF(ISNA(C65),D65,C65) -> Vanguard Growth ETF
... B69: #N/A | C69: iShares MSCI Emerging Markets Min Vol Factor ETF | D69: iShares:MSCI EM MV F (BATS:EEMV) | J69: =IF(ISNA(C69),D69,C69) -> iShares MSCI Emerging Markets Min Vol Factor ETF
B70: #N/A | C70: #N/A | D70: Vanguard Emerging Markets Select Stock;Investor | J70: =IF(ISNA(C70),D70,C70) -> Vanguard Emerging Markets Select Stock;Investor
B71: #N/A | C71: iShares China Large-Cap ETF | D71: iShares:China Large Cp (ARCX:FXI) | J71: =IF(ISNA(C71),D71,C71) -> iShares China Large-Cap ETF
B72: #N/A | C72: Vanguard Total World Stock Index ETF | D72: Vanguard T WldStk;ETF (ARCX:VT) | J72: =IF(ISNA(C72),D72,C72) -> Vanguard Total World Stock Index ETF
B73: #N/A | C73: iShares Convertible Bond ETF | D73: iShares:Convertible Bond (BATS:ICVT) | J73: =IF(ISNA(C73),D73,C73) -> iShares Convertible Bond ETF
B74: #N/A | C74: VanEck Fallen Angel High Yield Bond ETF | D74: VanEck:FA High Yld Bond (XNAS:ANGL) | J74: =IF(ISNA(C74),D74,C74) -> VanEck Fallen Angel High Yield Bond ETF
B75: #N/A | C75: iShares Fallen Angels USD Bond ETF | D75: iShares:Fall Ang USD Bd (XNAS:FALN) | J75: =IF(ISNA(C75),D75,C75) -> iShares Fallen Angels USD Bond ETF
B76: #N/A | C76: iShares iBoxx $ High Yield Corporate Bond ETF | D76: iShares:iBoxx $HY Corp (ARCX:HYG) | J76: =IF(ISNA(C76),D76,C76) -> iShares iBoxx $ High Yield Corporate Bond ETF
B77: #N/A | C77: SPDR Bloomberg High Yield Bond ETF | D77: SPDR Bbg High Yield Bd (ARCX:JNK) | J77: =IF(ISNA(C77),D77,C77) -> SPDR Bloomberg High Yield Bond ETF
B78: #N/A | C78: iShares iBoxx $ Investment Grade Corporate Bond ETF | D78: iShares:iBoxx $IG Corp (ARCX:LQD) | J78: =IF(ISNA(C78),D78,C78) -> iShares iBoxx $ Investment Grade Corporate Bond ETF
B79: #N/A | C79: SPDR Portfolio Corporate Bond ETF | D79: SPDR Ptf Corp Bd (ARCX:SPBO) | J79: =IF(ISNA(C79),D79,C79) -> SPDR Portfolio Corporate Bond ETF
B80: #N/A | C80: Vanguard Intermediate-Term Corporate Bond ETF | D80: Vanguard Int Crp Bd;ETF (XNAS:VCIT) | J80: =IF(ISNA(C80),D80,C80) -> Vanguard Intermediate-Term Corporate Bond ETF
B81: #N/A | C81: Vanguard Total Corporate Bond ETF | D81: Vanguard Total Corp Bond (XNAS:VTC) | J81: =IF(ISNA(C81),D81,C81) -> Vanguard Total Corporate Bond ETF
B82: #N/A | C82: iShares 7-10 Year Treasury Bond ETF | D82: iShares:7-10 Trs Bd (XNAS:IEF) | J82: =IF(ISNA(C82),D82,C82) -> iShares 7-10 Year Treasury Bond ETF
... B85: #N/A | C85: Vanguard Intermediate-Term Treasury ETF | D85: Vanguard Int Trs;ETF (XNAS:VGIT) | J85: =IF(ISNA(C85),D85,C85) -> Vanguard Intermediate-Term Treasury ETF

Sheet Divdends
A2: Dividend Aristocrats
A3: Companies in the S&P 500 that have increased their dividends for at least 25 consecutive years. They must have a minimum market cap of $3 billion, and an average daily trading volume of at least $5 million. To find more dividend stocks, check out the Top Dividend Stocks screener.
A4: Name | B4: Symbol | D4: Symbol | E4: Last Update | F4: Last Price | G4: 1d% | H4: Net Change | I4: Open | J4: Lo | K4: Hi | L4: Prev Cls | M4: 52W Lo | N4: 52W Hi | O4: Volume | P4: Avg Volume | Q4: Expense Ratio (net) | R4: Market Cap
A5: A. O. Smith Corporation | B5: AOS | C5: Equities - Dividend - Old Timers | D5: #VALUE! | E5: {=_FV(D5,"Last trade time",TRUE)} -> 45824.84 | F5: {=_FV(D5,"Price")} -> 64.32 | G5: {=_FV(D5,"Change (%)",TRUE)} -> 0.007992 | H5: {=_FV(D5,"Change")} -> 0.51 | I5: {=_FV(D5,"Open")} -> 64.25 | J5: {=_FV(D5,"Low")} -> 63.48 | K5: {=_FV(D5,"High")} -> 64.3792 | L5: {=_FV(D5,"Previous close",TRUE)} -> 63.81 | M5: {=_FV(D5,"52 week low",TRUE)} -> 58.83 | N5: {=_FV(D5,"52 week high",TRUE)} -> 92.445 | O5: {=_FV(D5,"Volume")} -> 1551842 | P5: {=_FV(D5,"Volume average",TRUE)} -> 1945695 | R5: {=_FV(D5,"Market cap",TRUE)} -> 9140450879
A6: Abbott Laboratories | B6: ABT | C6: Equities - Dividend - Old Timers | D6: #VALUE! | E6: {=_FV(D6,"Last trade time",TRUE)} -> 45824.931 | F6: {=_FV(D6,"Price")} -> 134.01 | G6: {=_FV(D6,"Change (%)",TRUE)} -> -0.011871 | H6: {=_FV(D6,"Change")} -> -1.61 | I6: {=_FV(D6,"Open")} -> 135.56 | J6: {=_FV(D6,"Low")} -> 133.305 | K6: {=_FV(D6,"High")} -> 136.41 | L6: {=_FV(D6,"Previous close",TRUE)} -> 135.62 | M6: {=_FV(D6,"52 week low",TRUE)} -> 99.71 | N6: {=_FV(D6,"52 week high",TRUE)} -> 141.23 | O6: {=_FV(D6,"Volume")} -> 5084061 | P6: {=_FV(D6,"Volume average",TRUE)} -> 5837233 | R6: {=_FV(D6,"Market cap",TRUE)} -> 233155422359
A7: AbbVie Inc. | B7: ABBV | C7: Equities - Dividend - Old Timers | D7: #VALUE! | E7: {=_FV(D7,"Last trade time",TRUE)} -> 45824.94 | F7: {=_FV(D7,"Price")} -> 190.98 | G7: {=_FV(D7,"Change (%)",TRUE)} -> -0.0005233 | H7: {=_FV(D7,"Change")} -> -0.1 | I7: {=_FV(D7,"Open")} -> 190.9 | J7: {=_FV(D7,"Low")} -> 188.93 | K7: {=_FV(D7,"High")} -> 191.6581 | L7: {=_FV(D7,"Previous close",TRUE)} -> 191.08 | M7: {=_FV(D7,"52 week low",TRUE)} -> 163.52 | N7: {=_FV(D7,"52 week high",TRUE)} -> 218.66 | O7: {=_FV(D7,"Volume")} -> 4203633 | P7: {=_FV(D7,"Volume average",TRUE)} -> 6230964 | R7: {=_FV(D7,"Market cap",TRUE)} -> 337347644940
A8: Aflac Incorporated | B8: AFL | C8: Equities - Dividend - Old Timers | D8: #VALUE! | E8: {=_FV(D8,"Last trade time",TRUE)} -> 45824.926 | F8: {=_FV(D8,"Price")} -> 102.72 | G8: {=_FV(D8,"Change (%)",TRUE)} -> 0.005285 | H8: {=_FV(D8,"Change")} -> 0.54 | I8: {=_FV(D8,"Open")} -> 102.77 | J8: {=_FV(D8,"Low")} -> 102.33 | K8: {=_FV(D8,"High")} -> 103.28 | L8: {=_FV(D8,"Previous close",TRUE)} -> 102.18 | M8: {=_FV(D8,"52 week low",TRUE)} -> 86.55 | N8: {=_FV(D8,"52 week high",TRUE)} -> 115.5 | O8: {=_FV(D8,"Volume")} -> 2160819 | P8: {=_FV(D8,"Volume average",TRUE)} -> 2016139 | R8: {=_FV(D8,"Market cap",TRUE)} -> 55535054400
A9: Air Products and Chemicals, Inc. | B9: APD | C9: Equities - Dividend - Old Timers | D9: #VALUE! | E9: {=_FV(D9,"Last trade time",TRUE)} -> 45824.894 | F9: {=_FV(D9,"Price")} -> 280.43 | G9: {=_FV(D9,"Change (%)",TRUE)} -> 0.000214 | H9: {=_FV(D9,"Change")} -> 0.06 | I9: {=_FV(D9,"Open")} -> 283.07 | J9: {=_FV(D9,"Low")} -> 278.76 | K9: {=_FV(D9,"High")} -> 284.0043 | L9: {=_FV(D9,"Previous close",TRUE)} -> 280.37 | M9: {=_FV(D9,"52 week low",TRUE)} -> 243.6921 | N9: {=_FV(D9,"52 week high",TRUE)} -> 341.14 | O9: {=_FV(D9,"Volume")} -> 889365 | P9: {=_FV(D9,"Volume average",TRUE)} -> 1123748 | R9: {=_FV(D9,"Market cap",TRUE)} -> 62408070006
A10: Albemarle Corporation | B10: ALB | C10: Equities - Dividend - Old Timers | D10: #VALUE! | E10: {=_FV(D10,"Last trade time",TRUE)} -> 45824.923 | F10: {=_FV(D10,"Price")} -> 60.96 | G10: {=_FV(D10,"Change (%)",TRUE)} -> 0.003953 | H10: {=_FV(D10,"Change")} -> 0.24 | I10: {=_FV(D10,"Open")} -> 62 | J10: {=_FV(D10,"Low")} -> 60.7 | K10: {=_FV(D10,"High")} -> 62.23 | L10: {=_FV(D10,"Previous close",TRUE)} -> 60.72 | M10: {=_FV(D10,"52 week low",TRUE)} -> 49.4303 | N10: {=_FV(D10,"52 week high",TRUE)} -> 113.91 | O10: {=_FV(D10,"Volume")} -> 2330120 | P10: {=_FV(D10,"Volume average",TRUE)} -> 3455270 | R10: {=_FV(D10,"Market cap",TRUE)} -> 7172608464
A11: Amcor plc | B11: AMCR | C11: Equities - Dividend - Old Timers | D11: #VALUE! | E11: {=_FV(D11,"Last trade time",TRUE)} -> 45824.938 | F11: {=_FV(D11,"Price")} -> 9.2 | G11: {=_FV(D11,"Change (%)",TRUE)} -> 0.010989 | H11: {=_FV(D11,"Change")} -> 0.1 | I11: {=_FV(D11,"Open")} -> 9.11 | J11: {=_FV(D11,"Low")} -> 9.1 | K11: {=_FV(D11,"High")} -> 9.22 | L11: {=_FV(D11,"Previous close",TRUE)} -> 9.1 | M11: {=_FV(D11,"52 week low",TRUE)} -> 8.37 | N11: {=_FV(D11,"52 week high",TRUE)} -> 11.48 | O11: {=_FV(D11,"Volume")} -> 18916701 | P11: {=_FV(D11,"Volume average",TRUE)} -> 26515314 | R11: {=_FV(D11,"Market cap",TRUE)} -> 21209155600
